Workbook

Sheet MEMBERS
C1: HERITAGE CLUB
C3: MEMBERS INFORMATION DATA BASE
A4: S.n | B4: MBR Number | C4: Name | D4: Email Address | E4: Contact Number | F4: Address
A5: 1 | B5: HCFM-AH001 | C5: ADMIRAL AHMED HAYAT | D5: ahmadhayat.btic@gmail.com
A6: 2 | B6: HCFM-0502 | C6: MR. JABIR SHAHZAD | D6: Jabirshah@hotmil.com | E6: 03452430072 | F6: Appt# 76, Tower 04, Precinct-19, Bahria Town Karachi
A7: 3 | B7: HCFM-0503 | C7: MR.GHULAM NABI OTHI | D7: Alirazaothi@gmail.com | E7: 03002237405 | F7: Villa # 689, Street# 11, Iqbal Villa, Preccinct-02, Bahria Town Karachi
A8: 4 | B8: HCFM-0504 | C8: MR.BILAL AHMED | D8: bilalak061@gmail.com | E8: 03468214340 | F8: Quaid Villa# 118, Street# 03, Precinct-02, Bahria Town Karachi
A9: 5 | B9: HCFM-0506 | C9: MR.MUHAMMAD ARIF | D9: maszone1980@gmail.com | E9: 03212669061 | F9: Appt#114, Tower 22, Precinct-19, Bahria Town Karachi
A10: 6 | B10: HCFM-0507 | C10: MR.SYED TAHIR ABBAS | D10: Syed.tahir.abbas@hotmail.com | E10: 03218202201 | F10: Villa# 2509, Street # 60, Precinct- 27, Bahria Town Karachi
A11: 7 | B11: HCFM-0508 | C11: MR.SHIRAZ AHMED | D11: sh-ahmed@hotmail.com | E11: 03452362138 | F11: Apt# 107, 4th Floor , Tower 11, Precinct -19, Bahria Town Karachi
A12: 8 | B12: HCFM-0509 | C12: MR.SYED ABDULLAH ALI | D12: Syedabdullchali89@gmil.com | E12: 03339049974 | F12: Villa# 7546, Street# 23, Road-01, Precinct-16, Bahria Town Karachi
A13: 9 | B13: HCFM-0510 | C13: MR.MUHAMMAD RIZWAN | D13: meshgroup193@gmail.com | E13: 03212245690 | F13: Villa# 536, Street# 15, Road-07, Precinct-04, Bahria Town Karachi
A14: 10 | B14: HCFM-0511 | C14: MR.TALHAR AHMED | D14: Talharshaikh4@gmail.com | E14: 03333653690 | F14: Appt# 104, 4th Floor, TOWER-11, Precinct-19, Bahria Town Karachi
A15: 11 | B15: HCFM-0512 | C15: MR.ZEESHAN IQBAL | D15: zchamdia@gmail.com | E15: 03222409333 | F15: Appt # 113, Tower 04, Precinct-19, Bahria Town Karachi
A16: 12 | B16: HCFM-0513 | C16: MR.SAJJAD ALI | D16: Sajjad.Kazi.isra@gmail.com | E16: 03003012497 | F16: Villa# 06, Road-01, Precinct-04, Bahria Town Karachi
A17: 13 | B17: HCFM-0514 | C17: MR.DILEEP KUMAR | D17: dgomani@yahoo.com | E17: 03332655987 | F17: House# A-50, Palm Enclave Housing Society, Bypass Hyderabad
A18: 14 | B18: HCFM-0515 | C18: MR.TARIQUE ZUBAIR | D18: tariq.zubair@btkarachi.com | E18: 03003895969
A19: 15 | B19: HCFM-0516 | C19: MR.ATIF SHAFQAT | D19: Shafqatatif@hotmail.com | E19: 03364407555 | F19: Quaid Villa# 184, Street# 05, Precinct-02, Bahria Town Karchi
A20: 16 | B20: HCFM-0517 | C20: DR.ATHESHAM UL HAQ RANA | D20: ahaqrana111@icloud.com | E20: 03009318597 | F20: Villa# 728, Street # 11, Road-4, Precinct-10A, Bahria Town Karachi
A21: 17 | B21: HCFM-0518 | C21: DR.SANTOSH KUMAR | D21: drsantoshpamnani@gmail.com | E21: 03212014843 | F21: Appt # 91, Tower 22, Precinct- 19, Bahria Town Karachi
A22: 18 | B22: HCFM-0519 | C22: DR.NAZEER HUSSAIN KALHORO | D22: drnazeerhussain@hotmail.com | E22: 03114605474 | F22: Villa# 756, Street 23 , Precinct- 01, Bahria Town Karachi
A23: 19 | B23: HCFM-0520 | C23: MR.NIZAM UDDIN NIZAMANI | D23: nizambaloch@gmail.com | E23: 03452220862 | F23: Villa # 211, Street # 01, Precinct-11-A, Bahria Town Karachi
A24: 20 | B24: HCFM-0521 | C24: MR.HAFEEZ AHMED SIYAL | D24: hafeezsiyal09@gmail.com | E24: 03008379253 | F24: Villa#1990, Road-15, Precinct-12, Ali Block, Bahria Town Karchi
A25: 21 | B25: HCFM-0522 | C25: MR.IQBAL AHMED MALLAH | D25: Iqbalahmed.Mallah@hotmail.com | E25: 03009249097 | F25: Villa#1642, Loop Road, Precinct 10-A, Bahria Town Karachi.
A26: 22 | B26: HCFM-0523 | C26: MR.KANYO LAL | D26: Kanyolal.Mandhwani@gmail.com | E26: 03335414613 | F26: Pent House # 02, 5th Floor Mustafa Arcade, SMCH- Block-A Karachi
A27: 23 | B27: HCFM-0524 | C27: MR.MANOJ KUMAR | D27: Mkvedani@gmil.com | E27: 03332881142 | F27: Appt # 96, Tower 08, Precinct - 19, Bahria Town Karachi
A28: 24 | B28: HCFM-0525 | C28: DR.SAJJAD AHMED SOLANGI | D28: Solangisajjad1977@gmail.com | E28: 03272102384 | F28: Villa # 230, Street # 03, Precinct - 10-A, Bahria Town Karachi
A29: 25 | B29: HCFM-0526 | C29: MR.MUIED AHMED DURRANI | D29: Muied@outlook.com | E29: 03462885409 | F29: Villa # 1012 , Street # 13 , Precinct-31 , Bahria Town Karachi
A30: 26 | B30: HCFM-0527 | C30: MR.SAEED AHMED | D30: Sanoorhafsa123@gmail.com | E30: 03212112153 | F30: Villa # 05, Street # 31, Precinct-35, Sportcity, Bahria Town Karachi
... A32: 28 | B32: HCFM-0529 | C32: DR.UMER QAZI | D32: docuk1982@yahoo.com | E32: 03361853609 | F32: Villa# 06, Road-01, Precinct-04, Bahria Town Karachi
A33: 29 | B33: HCFM-0530 | C33: MR.MUHAMMAD HANIF | D33: haneef_pk@hotmail.com | E33: 3002021430 | F33: Villa# 105, Loop Road, Precinct-06, Bahria Town Karachi
A34: 30 | B34: HCFM-0532 | C34: MR.KHALID JAVED | D34: khalid.javed@omsltd.net | E34: 03458437686 | F34: Villa# 1575, Street # 23, Precinct-08, Bahria Town Karachi
A35: 31 | B35: HCFM-0533 | C35: MR.ZULQARNAIN | D35: zulqarnainhabib@gmail.com | E35: 3332110598 | F35: Villa # 594, Street # 19, Precinct # 01, Bahria Town Karachi
A36: 32 | B36: HCFM-0534 | C36: MR.PIR MUJEEB JAN SARHANDI | D36: hamzajan1996@hotmail.com | E36: 03003029453 | F36: Appt # 118, 5th Floor, Tower# 15, Bahria Town Karachi
A37: 33 | B37: HCFM-0535 | C37: MR.MUHAMMAD ASIF | D37: hammadasif801@gmail.com | E37: 03002901230 | F37: Villa# 164, Precinct # 02, Quaid Block, Bahria Town Karachi
A38: 34 | B38: HCFM-0536 | C38: MR.ASHOK KUMAR | D38: arta_ashoka@hotmail.com | E38: 03332638079 | F38: Quaid Villa # 141, Street # 4, Precinct # 02, Bahria Town Karachi
A39: 35 | B39: HCFM-0538 | C39: MR.MUHAMMAD ZAIN | D39: zuraaco_z@gmail.com | E39: 03212106668 | F39: Villa# 0236, Street 06, Precinct #02, Quaid Block, Bahria Town Karachi
A40: 36 | B40: HCFM-0539 | C40: MR.QAMARUZZAMAN | D40: Qamar@ezzaintl.com | E40: 03008269322 | F40: A2 3/30 Flat C4 , 3rd Floor , Nazimabad # 2 , Awan-e-Hashim , Karachi
A41: 37 | B41: HCFM-0540 | C41: MR.MUHAMMAD SALIQ SIDDIQUI | D41: ssiddiqi2@yahoo.com | E41: 030021333997 | F41: Dolmen Arcade, Block 3 , B.Y.J.C.H.S, Appt #609, Bahadurabad, Karachi
A42: 38 | B42: HCFM-0541 | C42: MR.SHAN ELAHI SEHGAL | D42: Shanelahisehgal@hotmail.com | E42: 03367890911 | F42: Villa# 1567, Precinct #10-A, Bahria Town Karachi
A43: 39 | B43: HCFM-0542 | C43: MR.HANIF AHSAN ZUBEDI | D43: Haneefahsan@hotmail.com | E43: 03332624474 | F43: Appt # 149, Tower # 24, Precinct-19, Bahria Town Karachi
A44: 40 | B44: HCFM-0543 | C44: MR.MUHAMMAD ATIF USMANI | D44: ma.usmani@live.com | E44: 03009382539 | F44: Quaid Villa # 184 , Street # 5 , Precinct -2 , Bahria Town Karachi
A45: 41 | B45: HCFM-0544 | C45: MR.MOHAMMAD ASHRAF SHAIKH | D45: ashrafsheikh@hotmail.com | E45: 03332604818 | F45: Villa# 712, Street # 22, Precinct # 04, Bahria Town Karachi
A46: 42 | B46: HCFM-0545 | C46: MR. HASAN KARIM | D46: hasan@nasraschool.edu.pk | E46: 3332149596 | F46: B/28, Block "C" North nazimabad, Hyderi.
A47: 43 | B47: HCFM-0546 | C47: MR.ATHER TARIQ | D47: athar.tariq@logistics-leaders.com | E47: 03232316561 | F47: Appt # 55, Tower# 23, Precinct# 19, Bahria Town Karachi
A48: 44 | B48: HCFM-0547 | C48: MR.GOBIND RAM | D48: gobind.lund@nbp.com.pk | E48: 03003300006 | F48: Appt # 602, Paradise Residency, Ferere Town, Clifton Karachi
A49: 45 | B49: HCFM-0548 | C49: MR.ZAIN FAROOQ | D49: zainfarooq@hotmail.com | E49: 3002788801 | F49: Appt # 04 , Tower # 7 , Precinct 19 , Bahria Town Karachi
A50: 46 | B50: HCFM-0549 | C50: MR.WAQAR UDDIN | D50: sadaat_waqar@yahoo.com | E50: 03333498034 | F50: Quaid Villa # 107 , Street # 3 , Precicnt-2 , Bahria Town Karachi
A51: 47 | B51: HCFM-0551 | C51: MR.ASIF ALI | D51: asifali.sbp@gmail.com | E51: 03000910659 | F51: Villa# 620, Road-06, Precinct-08, Bahria Town Karachi
A52: 48 | B52: HCFM-0553 | C52: MR.FAISAL MERCHANT | D52: faisalmerchant@yahoo.com | E52: 03342467497 | F52: Villa # 919, Street # 30 , Precinct -4 , Bahria Town Keachi
A53: 49 | B53: HCFM-0554 | C53: MR.IMRAN WAZEER | D53: imranwazeerpk@gmail.com | E53: 03018383404 | F53: Villa # 295 , Street # 5 , Precicnt -8 , Bahria Town Karachi
A54: 50 | B54: HCFM-0556 | C54: MR.SYED SALMAN RAZA | D54: salman4raza@msn.com | E54: 03055555646 | F54: Villa # 1008 , Road # 10 , Precinct 4 Bahria Town Karachi
A55: 51 | B55: HCFM-0557 | C55: MR.KHADIM HUSSAIN | D55: khadim2016@icloud.com | E55: 03332124863 | F55: Villa # 122 , Street # 3 , Precicnt -29 , Bahria Town Karachi
A56: 52 | B56: HCFM-0558 | C56: MUHAMMAD EBRAHIM TIWANA | D56: ebrahim.nsps@gmail.com | E56: 03463308767 | F56: Villa # 4032 , Road 1 , Precicnt # 1 , Bahria Town Karachi
A57: 53 | B57: HCFM-0559 | C57: MR.SYED HAMID SHAH | D57: hamid.forecast@gmail.com | E57: 03005006020 | F57: Quaid Villa #122, Street # 3, Precinct-2, Bahria Town Karachi
A58: 54 | B58: HCFM-0581 | C58: BRIG DR. GHULAM MEHDI (Retd) | D58: Mehdighulam1@gmail.com | E58: 03214751278 | F58: Quaid Villa # 150 , Street # 4 , Precicnt -2 , Bahria Town Karachi
A59: 55 | B59: HCFM-0583 | C59: MR.CAREL HEDRIK BURGER | D59: Callie.hendrik@btkarachi.com | E59: 03458207222 | F59: Villa # 03 , Street # 09, Precinct- 35, Sportcity, Bahria Town Karachi
A60: 56 | B60: HCFM-0585 | C60: DGM AMJAD ALI SHAIKH | D60: engr.amjadalishaikh@gmail.com | E60: 03333851445 | F60: Iqbal Villa # 866 , Street # 17 , Precicnt-2 Bahria Town Karachi
A61: 57 | B61: HCFM-0586 | C61: MR.SYED MURTAZA ALI | D61: mrtali@yahoo.com | E61: 03312469273 | F61: Villa # 1590 , Loop Road , Precicnt- 10 A , Bhaira Town Karachi
... A66: 62 | B66: HCFM-0593 | C66: CAPT.HAMID UZ ZAFAR | D66: huzaffar@btkarachi.com | E66: 03332394721 | F66: H # 126-H , Model Town , Lahore
A67: 63 | B67: HCFM-0595 | C67: BRIG.KHALID MEHMOOD | D67: khalid.mahmood@btkarachi.com | E67: 3212294044
A68: 64 | B68: HCFM-0596 | C68: DGM AZFAR ALI | D68: azfar.ali@btkarachi.com | E68: 3453655775 | F68: Iqbal Villa # 863 , Street # 17 , Precicnt -2 , Bahria Town Karachi
A69: 65 | B69: HCFM-0597 | C69: GM GHULAM DASTAGEER | D69: g.dastageer@btkarachi.com | E69: 3003140270
A70: 66 | B70: HCFM-0598 | C70: DGM FATIMA ZAHID | D70: fatima.zahid@btkarachi.com | E70: 03455276997
A71: 67 | B71: HCFM-0599 | C71: CDR.RAZA REHMAN | D71: raza.rehman@btkarachi.com | E71: 3212684804 | F71: Villa # 1197 , Street # 18 , Precicnt -8 , Bhaira Town Karachi
A72: 68 | B72: HCFM-0600 | C72: DR.FAKHRUNISSA WAHEED | D72: drfakhrunisa@gmail.com | E72: 03002666888 | F72: Villa # 354 , Street # 8 , Quaid Block , Bahria Town Karachi
A73: 69 | B73: HCFM-0601 | C73: GM HAROON RASHEED | D73: haroonrasheedbahria@gmail.com | E73: 03332167222 | F73: Quaid Villa # 437 , Road -01 , Precinct # 02 , Bahria Town Karachi
A74: 70 | B74: HCFM-0603 | C74: CAPT.ZAHID AWAN | D74: zahid.awan@btkarachi.com | E74: 3012172230 | F74: H # D-27 , Street # B-50 , NHS Phase 4 , Karsaz , Karachi
A75: 71 | B75: HCFM-0605 | C75: DR.QURATULAIN RAZI | D75: docburni@gmail.com | E75: 3002020885 | F75: Quaid Villa # 518, Street# 10-B, Precinct- 02, Bahria Town Karachi
A76: 72 | B76: HCFM-0606 | C76: DR.FAREYA | D76: fareyausmani@gmail.com | E76: 3219294138 | F76: M 21/1/1 , Phase-7 , Ittehad DHA
A77: 73 | B77: HCFM-0607 | C77: DIR. ZIA UR REHMAN KHAN | D77: zia.khan@btkarachi.com | E77: 3002231183 | F77: SUH 425 , Street # 4 , Sector-B , Askari 5 , Malir Cant , Karachi
A78: 74 | B78: HCFM-0608 | C78: SGM MUHAMMAD YAQOOB | D78: yaqoob.awan@btkarachi.com | E78: 3002033090 | F78: Quaid Villa # 551 , Road -2 , Precicnt # 2 , Bahria Town Karachi
A79: 75 | B79: HCFM-0609 | C79: DR.NASEEM MUNSHI | D79: naseemmunshi@hotmail.com | E79: 3009278599
A80: 76 | B80: HCFM-0638 | C80: RIAZ FAZAL | D80: ibadexportsolution@gmail.com | E80: 3460272783
A81: 77 | B81: HCFM-0639 | C81: HUSSAIN WAJID | D81: hussain@fmcbrake.com.pk | E81: 3002241181
A82: 78 | B82: HCFM-0640 | C82: MUKHTIAR AHMED SHAR | D82: mukhtarshar@gmail.com | E82: 3003944127
A83: 79 | B83: HCFM-0641 | C83: AAMIR RASOOL | D83: alkarimmotors@hotmail.com | E83: 3452088967 | F83: 550000 party amount135000
A84: 80 | B84: HCFM-0642 | C84: ASIF ASHFAQ | D84: asiftextile@hotmail.com | E84: 3219275943
A85: 81 | B85: HCFM-0644 | C85: SABA AHSAN | D85: aleenaahsan@hotmail.com | E85: 3333777803
A86: 82 | B86: HCFM-0645 | C86: MUNEER AHMED | D86: engr.muneerkhan@gmail.com | E86: 3327296921
A87: 83 | B87: HCFM-0646 | C87: BAHRIA INTERNATIONAL HOSPITAL | D87: muhammad.ibrahim@btkhospital.com | E87: 3243461988
A88: 84 | B88: HCFM-0647 | C88: IMRAN AHMED | D88: imail.1999@gmail.com | E88: 3323394004
A89: 85 | B89: HCFM-0648 | C89: AYSM MIRZA | D89: asym1480@gmail.com | E89: 3333211480
A90: 86 | B90: HCFM-0649 | C90: IFTIKHAR SHAH | D90: iftikharshah54@yahoo.com | E90: 1(301)370-4286
A91: 87 | B91: HCFM-0650 | C91: KHURRAM FIRDOUS | D91: Khurramchandiwala@gmail.com
A92: 88 | B92: HCFM-0651 | C92: ALI LEGHARI | D92: alileghari1994@gmail.com
A93: 89 | B93: HCFM-0652 | C93: Dr. AZAD ALI | D93: azadlashari.09@gmail.com
A94: 90 | B94: HCFM-0653 | C94: AMEER MUHAMMAD | D94: ameer.mohammad@gbtrader.org
A95: 91 | B95: HCFM-0654 | C95: SYED JIBRAN MUSHTAQ | D95: jibrangilani@gmail.com
A96: 92 | B96: HCFM-0655 | C96: SADDAM HUSSAIN | D96: schandio1624@gmail.com
A97: 93 | B97: HCFM-0656 | C97: ZAIB UR REHMAN | D97: abumousa701@gmail.com
A98: 94 | B98: HCFM-0657 | C98: NASIR ABBAS | D98: nasir.abbas@nbp.com.pk
A99: 95 | B99: HCFM-0658 | C99: MUSHTAQ AHMED MEMON | D99: a.amemon@yahoo.com
A100: 96 | B100: HCFM-0659 | C100: Heritage club
A101: 97 | B101: HCFM-0661 | C101: ARSLAN KHAN ABRO | D101: abroarslan69@gmail.com
A102: 98 | B102: HCFM-0663 | C102: JAM FEROZ | D102: jamferoz@gmail.com
A103: 99 | B103: HCFM-0664 | C103: SHAHBAZ AHMED | D103: shahbazahmedijaz88@gmail.com
A104: 100 | B104: HCFM-0665 | C104: KAZI NAZEER AHMED | D104: kznayz@gmail.com
A105: 101 | B105: HCFM-0666 | C105: MR FAHAD MUMTAZ
A106: 102 | B106: HCFM-0667 | C106: MR. FAYAZ ALI SOOMRO | D106: falisoomro@secmc.com.pk
...

Sheet data base 
A1: S.NO | B1: MBR ID | C1: MBR NAME | D1: BOWLING ALLEY | E1: GYM | F1: FAMILY POOL | G1: SQUASH COURT | H1: LADIES POOL | I1: CHILDERN PLAY AREA | J1: CINEMA | K1: Cigar Lounge | L1: Pool Lockers | M1: SPA | N1: Padel Court | O1: Ladies Saloon | P1: HC Chambers | Q1: Gym Sub | R1: PARTY | S1: VANU CHARGES | T1: FOOD & BEVERAGES | U1: (SST) | V1: MONTHLY SUBSCRIPTION | W1: TOTAL | X1: AREARS | Y1: ADVANCED | Z1: MANDATORY CHARGES | AA1: TOTAL BILLED AMOUNT | AB1: LATE PAYMENT SURCHARGE | AC1: DUE DATE | AD1: AMOUNT AFTER DUE DATE
A2: 1 | B2: HCFM-AH001 | C2: ADMIRAL AHMED HAYAT | D2: =SUMIFS(FACILITIES!E:E,FACILITIES!$B:$B,B2) -> 0 | E2: =SUMIFS(FACILITIES!F:F,FACILITIES!$B:$B,$B2) -> 0 | F2: =SUMIFS(FACILITIES!G:G,FACILITIES!$B:$B,B2) -> 0 | G2: =SUMIFS(FACILITIES!H:H,FACILITIES!$B:$B,B2) -> 0 | H2: =SUMIFS(FACILITIES!I:I,FACILITIES!$B:$B,B2) -> 0 | I2: =SUMIFS(FACILITIES!J:J,FACILITIES!$B:$B,B2) -> 0 | J2: =SUMIFS(FACILITIES!K:K,FACILITIES!$B:$B,B2) -> 0 | K2: =SUMIFS(FACILITIES!L:L,FACILITIES!$B:$B,B2) -> 0 | L2: =SUMIFS(FACILITIES!M:M,FACILITIES!$B:$B,B2) -> 0 | M2: =SUMIFS(FACILITIES!N:N,FACILITIES!$B:$B,B2) -> 0 | N2: =SUMIFS(FACILITIES!O:O,FACILITIES!$B:$B,B2) -> 0 | O2: =SUMIFS(FACILITIES!P:P,FACILITIES!$B:$B,B2) -> 0 | P2: =SUMIFS(FACILITIES!Q:Q,FACILITIES!$B:$B,B2) -> 0 | Q2: =SUMIFS(FACILITIES!R:R,FACILITIES!$B:$B,B2) -> 0 | R2: =SUMIFS(FACILITIES!T:T,FACILITIES!B:B,B2) -> 0 | S2: =SUMIFS(FACILITIES!S:S,FACILITIES!B:B,B2) -> 0 | T2: =SUMIFS('F & B'!G:G,'F & B'!B:B,B2) -> 24550 | U2: =T2*0.15 -> 3682.5 | V2: =SUMIFS('FIXED AMOUNT'!G:G,'FIXED AMOUNT'!B:B,B2) -> 7000 | W2: =SUM(D2:V2) -> 35232.5 | X2: =SUMIFS('FIXED AMOUNT'!E:E,'FIXED AMOUNT'!B:B,'data base '!B:B) -> 0 | Y2: =SUMIFS('FIXED AMOUNT'!F:F,'FIXED AMOUNT'!B:B,'data base '!B:B) -> 0 | Z2: =SUMIFS('FIXED AMOUNT'!V:V,'FIXED AMOUNT'!B:B,B:B) -> 0 | AA2: =W2+X2-Y2+Z2 -> 35232.5 | AB2: =W2*0.1 -> 3523.25 | AC2: 45945 | AD2: =AA2+AB2 -> 38755.75
A3: 2 | B3: HCFM-0502 | C3: MR. JABIR SHAHZAD | D3: =SUMIFS(FACILITIES!E:E,FACILITIES!$B:$B,B3) -> 0 | E3: =SUMIFS(FACILITIES!F:F,FACILITIES!$B:$B,$B3) -> 750 | F3: =SUMIFS(FACILITIES!G:G,FACILITIES!$B:$B,B3) -> 0 | G3: =SUMIFS(FACILITIES!H:H,FACILITIES!$B:$B,B3) -> 0 | H3: =SUMIFS(FACILITIES!I:I,FACILITIES!$B:$B,B3) -> 0 | I3: =SUMIFS(FACILITIES!J:J,FACILITIES!$B:$B,B3) -> 1100 | J3: =SUMIFS(FACILITIES!K:K,FACILITIES!$B:$B,B3) -> 0 | K3: =SUMIFS(FACILITIES!L:L,FACILITIES!$B:$B,B3) -> 0 | L3: =SUMIFS(FACILITIES!M:M,FACILITIES!$B:$B,B3) -> 0 | M3: =SUMIFS(FACILITIES!N:N,FACILITIES!$B:$B,B3) -> 0 | N3: =SUMIFS(FACILITIES!O:O,FACILITIES!$B:$B,B3) -> 0 | O3: =SUMIFS(FACILITIES!P:P,FACILITIES!$B:$B,B3) -> 0 | P3: =SUMIFS(FACILITIES!Q:Q,FACILITIES!$B:$B,B3) -> 0 | Q3: =SUMIFS(FACILITIES!R:R,FACILITIES!$B:$B,B3) -> 0 | R3: =SUMIFS(FACILITIES!T:T,FACILITIES!B:B,B3) -> 0 | S3: =SUMIFS(FACILITIES!S:S,FACILITIES!B:B,B3) -> 0 | T3: =SUMIFS('F & B'!G:G,'F & B'!B:B,B3) -> 12950 | U3: =T3*0.15 -> 1942.5 | V3: =SUMIFS('FIXED AMOUNT'!G:G,'FIXED AMOUNT'!B:B,B3) -> 7000 | W3: =SUM(D3:V3) -> 23742.5 | X3: =SUMIFS('FIXED AMOUNT'!E:E,'FIXED AMOUNT'!B:B,'data base '!B:B) -> 0 | Y3: =SUMIFS('FIXED AMOUNT'!F:F,'FIXED AMOUNT'!B:B,'data base '!B:B) -> 0 | Z3: =SUMIFS('FIXED AMOUNT'!V:V,'FIXED AMOUNT'!B:B,B:B) -> 0 | AA3: =W3+X3-Y3+Z3 -> 23742.5 | AB3: =W3*0.1 -> 2374.25 | AC3: 45945 | AD3: =AA3+AB3 -> 26116.75
A4: 3 | B4: HCFM-0503 | C4: MR.GHULAM NABI OTHI | D4: =SUMIFS(FACILITIES!E:E,FACILITIES!$B:$B,B4) -> 0 | E4: =SUMIFS(FACILITIES!F:F,FACILITIES!$B:$B,$B4) -> 0 | F4: =SUMIFS(FACILITIES!G:G,FACILITIES!$B:$B,B4) -> 0 | G4: =SUMIFS(FACILITIES!H:H,FACILITIES!$B:$B,B4) -> 0 | H4: =SUMIFS(FACILITIES!I:I,FACILITIES!$B:$B,B4) -> 0 | I4: =SUMIFS(FACILITIES!J:J,FACILITIES!$B:$B,B4) -> 0 | J4: =SUMIFS(FACILITIES!K:K,FACILITIES!$B:$B,B4) -> 0 | K4: =SUMIFS(FACILITIES!L:L,FACILITIES!$B:$B,B4) -> 0 | L4: =SUMIFS(FACILITIES!M:M,FACILITIES!$B:$B,B4) -> 0 | M4: =SUMIFS(FACILITIES!N:N,FACILITIES!$B:$B,B4) -> 0 | N4: =SUMIFS(FACILITIES!O:O,FACILITIES!$B:$B,B4) -> 0 | O4: =SUMIFS(FACILITIES!P:P,FACILITIES!$B:$B,B4) -> 0 | P4: =SUMIFS(FACILITIES!Q:Q,FACILITIES!$B:$B,B4) -> 0 | Q4: =SUMIFS(FACILITIES!R:R,FACILITIES!$B:$B,B4) -> 0 | R4: =SUMIFS(FACILITIES!T:T,FACILITIES!B:B,B4) -> 0 | S4: =SUMIFS(FACILITIES!S:S,FACILITIES!B:B,B4) -> 5000 | T4: =SUMIFS('F & B'!G:G,'F & B'!B:B,B4) -> 52578 | U4: =T4*0.15 -> 7886.7 | V4: =SUMIFS('FIXED AMOUNT'!G:G,'FIXED AMOUNT'!B:B,B4) -> 7000 | W4: =SUM(D4:V4) -> 72464.7 | X4: =SUMIFS('FIXED AMOUNT'!E:E,'FIXED AMOUNT'!B:B,'data base '!B:B) -> 0 | Y4: =SUMIFS('FIXED AMOUNT'!F:F,'FIXED AMOUNT'!B:B,'data base '!B:B) -> 0 | Z4: =SUMIFS('FIXED AMOUNT'!V:V,'FIXED AMOUNT'!B:B,B:B) -> 0 | AA4: =W4+X4-Y4+Z4 -> 72464.7 | AB4: =W4*0.1 -> 7246.47 | AC4: 45945 | AD4: =AA4+AB4 -> 79711.17
A5: 4 | B5: HCFM-0504 | C5: MR.BILAL AHMED | D5: =SUMIFS(FACILITIES!E:E,FACILITIES!$B:$B,B5) -> 0 | E5: =SUMIFS(FACILITIES!F:F,FACILITIES!$B:$B,$B5) -> 0 | F5: =SUMIFS(FACILITIES!G:G,FACILITIES!$B:$B,B5) -> 0 | G5: =SUMIFS(FACILITIES!H:H,FACILITIES!$B:$B,B5) -> 0 | H5: =SUMIFS(FACILITIES!I:I,FACILITIES!$B:$B,B5) -> 0 | I5: =SUMIFS(FACILITIES!J:J,FACILITIES!$B:$B,B5) -> 500 | J5: =SUMIFS(FACILITIES!K:K,FACILITIES!$B:$B,B5) -> 0 | K5: =SUMIFS(FACILITIES!L:L,FACILITIES!$B:$B,B5) -> 0 | L5: =SUMIFS(FACILITIES!M:M,FACILITIES!$B:$B,B5) -> 0 | M5: =SUMIFS(FACILITIES!N:N,FACILITIES!$B:$B,B5) -> 0 | N5: =SUMIFS(FACILITIES!O:O,FACILITIES!$B:$B,B5) -> 0 | O5: =SUMIFS(FACILITIES!P:P,FACILITIES!$B:$B,B5) -> 0 | P5: =SUMIFS(FACILITIES!Q:Q,FACILITIES!$B:$B,B5) -> 0 | Q5: =SUMIFS(FACILITIES!R:R,FACILITIES!$B:$B,B5) -> 0 | R5: =SUMIFS(FACILITIES!T:T,FACILITIES!B:B,B5) -> 0 | S5: =SUMIFS(FACILITIES!S:S,FACILITIES!B:B,B5) -> 0 | T5: =SUMIFS('F & B'!G:G,'F & B'!B:B,B5) -> 6550 | U5: =T5*0.15 -> 982.5 | V5: =SUMIFS('FIXED AMOUNT'!G:G,'FIXED AMOUNT'!B:B,B5) -> 7000 | W5: =SUM(D5:V5) -> 15032.5 | X5: =SUMIFS('FIXED AMOUNT'!E:E,'FIXED AMOUNT'!B:B,'data base '!B:B) -> 0 | Y5: =SUMIFS('FIXED AMOUNT'!F:F,'FIXED AMOUNT'!B:B,'data base '!B:B) -> 0 | Z5: =SUMIFS('FIXED AMOUNT'!V:V,'FIXED AMOUNT'!B:B,B:B) -> 0 | AA5: =W5+X5-Y5+Z5 -> 15032.5 | AB5: =W5*0.1 -> 1503.25 | AC5: 45945 | AD5: =AA5+AB5 -> 16535.75
A6: 5 | B6: HCFM-0506 | C6: MR.MUHAMMAD ARIF | D6: =SUMIFS(FACILITIES!E:E,FACILITIES!$B:$B,B6) -> 2700 | E6: =SUMIFS(FACILITIES!F:F,FACILITIES!$B:$B,$B6) -> 0 | F6: =SUMIFS(FACILITIES!G:G,FACILITIES!$B:$B,B6) -> 0 | G6: =SUMIFS(FACILITIES!H:H,FACILITIES!$B:$B,B6) -> 0 | H6: =SUMIFS(FACILITIES!I:I,FACILITIES!$B:$B,B6) -> 0 | I6: =SUMIFS(FACILITIES!J:J,FACILITIES!$B:$B,B6) -> 600 | J6: =SUMIFS(FACILITIES!K:K,FACILITIES!$B:$B,B6) -> 0 | K6: =SUMIFS(FACILITIES!L:L,FACILITIES!$B:$B,B6) -> 0 | L6: =SUMIFS(FACILITIES!M:M,FACILITIES!$B:$B,B6) -> 0 | M6: =SUMIFS(FACILITIES!N:N,FACILITIES!$B:$B,B6) -> 0 | N6: =SUMIFS(FACILITIES!O:O,FACILITIES!$B:$B,B6) -> 0 | O6: =SUMIFS(FACILITIES!P:P,FACILITIES!$B:$B,B6) -> 0 | P6: =SUMIFS(FACILITIES!Q:Q,FACILITIES!$B:$B,B6) -> 0 | Q6: =SUMIFS(FACILITIES!R:R,FACILITIES!$B:$B,B6) -> 0 | R6: =SUMIFS(FACILITIES!T:T,FACILITIES!B:B,B6) -> 0 | S6: =SUMIFS(FACILITIES!S:S,FACILITIES!B:B,B6) -> 0 | T6: =SUMIFS('F & B'!G:G,'F & B'!B:B,B6) -> 22657 | U6: =T6*0.15 -> 3398.55 | V6: =SUMIFS('FIXED AMOUNT'!G:G,'FIXED AMOUNT'!B:B,B6) -> 7000 | W6: =SUM(D6:V6) -> 36355.55 | X6: =SUMIFS('FIXED AMOUNT'!E:E,'FIXED AMOUNT'!B:B,'data base '!B:B) -> 0 | Y6: =SUMIFS('FIXED AMOUNT'!F:F,'FIXED AMOUNT'!B:B,'data base '!B:B) -> 0 | Z6: =SUMIFS('FIXED AMOUNT'!V:V,'FIXED AMOUNT'!B:B,B:B) -> 8474 | AA6: =W6+X6-Y6+Z6 -> 44829.55 | AB6: =W6*0.1 -> 3635.555 | AC6: 45945 | AD6: =AA6+AB6 -> 48465.105
A7: 6 | B7: HCFM-0507 | C7: MR.SYED TAHIR ABBAS | D7: =SUMIFS(FACILITIES!E:E,FACILITIES!$B:$B,B7) -> 0 | E7: =SUMIFS(FACILITIES!F:F,FACILITIES!$B:$B,$B7) -> 0 | F7: =SUMIFS(FACILITIES!G:G,FACILITIES!$B:$B,B7) -> 0 | G7: =SUMIFS(FACILITIES!H:H,FACILITIES!$B:$B,B7) -> 0 | H7: =SUMIFS(FACILITIES!I:I,FACILITIES!$B:$B,B7) -> 0 | I7: =SUMIFS(FACILITIES!J:J,FACILITIES!$B:$B,B7) -> 0 | J7: =SUMIFS(FACILITIES!K:K,FACILITIES!$B:$B,B7) -> 0 | K7: =SUMIFS(FACILITIES!L:L,FACILITIES!$B:$B,B7) -> 0 | L7: =SUMIFS(FACILITIES!M:M,FACILITIES!$B:$B,B7) -> 0 | M7: =SUMIFS(FACILITIES!N:N,FACILITIES!$B:$B,B7) -> 0 | N7: =SUMIFS(FACILITIES!O:O,FACILITIES!$B:$B,B7) -> 0 | O7: =SUMIFS(FACILITIES!P:P,FACILITIES!$B:$B,B7) -> 0 | P7: =SUMIFS(FACILITIES!Q:Q,FACILITIES!$B:$B,B7) -> 0 | Q7: =SUMIFS(FACILITIES!R:R,FACILITIES!$B:$B,B7) -> 0 | R7: =SUMIFS(FACILITIES!T:T,FACILITIES!B:B,B7) -> 0 | S7: =SUMIFS(FACILITIES!S:S,FACILITIES!B:B,B7) -> 0 | T7: =SUMIFS('F & B'!G:G,'F & B'!B:B,B7) -> 3200 | U7: =T7*0.15 -> 480 | V7: =SUMIFS('FIXED AMOUNT'!G:G,'FIXED AMOUNT'!B:B,B7) -> 7000 | W7: =SUM(D7:V7) -> 10680 | X7: =SUMIFS('FIXED AMOUNT'!E:E,'FIXED AMOUNT'!B:B,'data base '!B:B) -> 0 | Y7: =SUMIFS('FIXED AMOUNT'!F:F,'FIXED AMOUNT'!B:B,'data base '!B:B) -> 0 | Z7: =SUMIFS('FIXED AMOUNT'!V:V,'FIXED AMOUNT'!B:B,B:B) -> 44350 | AA7: =W7+X7-Y7+Z7 -> 55030 | AB7: =W7*0.1 -> 1068 | AC7: 45945 | AD7: =AA7+AB7 -> 56098
A8: 7 | B8: HCFM-0508 | C8: MR.SHIRAZ AHMED | D8: =SUMIFS(FACILITIES!E:E,FACILITIES!$B:$B,B8) -> 2400 | E8: =SUMIFS(FACILITIES!F:F,FACILITIES!$B:$B,$B8) -> 0 | F8: =SUMIFS(FACILITIES!G:G,FACILITIES!$B:$B,B8) -> 0 | G8: =SUMIFS(FACILITIES!H:H,FACILITIES!$B:$B,B8) -> 0 | H8: =SUMIFS(FACILITIES!I:I,FACILITIES!$B:$B,B8) -> 0 | I8: =SUMIFS(FACILITIES!J:J,FACILITIES!$B:$B,B8) -> 1100 | J8: =SUMIFS(FACILITIES!K:K,FACILITIES!$B:$B,B8) -> 0 | K8: =SUMIFS(FACILITIES!L:L,FACILITIES!$B:$B,B8) -> 0 | L8: =SUMIFS(FACILITIES!M:M,FACILITIES!$B:$B,B8) -> 0 | M8: =SUMIFS(FACILITIES!N:N,FACILITIES!$B:$B,B8) -> 0 | N8: =SUMIFS(FACILITIES!O:O,FACILITIES!$B:$B,B8) -> 0 | O8: =SUMIFS(FACILITIES!P:P,FACILITIES!$B:$B,B8) -> 0 | P8: =SUMIFS(FACILITIES!Q:Q,FACILITIES!$B:$B,B8) -> 0 | Q8: =SUMIFS(FACILITIES!R:R,FACILITIES!$B:$B,B8) -> 0 | R8: =SUMIFS(FACILITIES!T:T,FACILITIES!B:B,B8) -> 0 | S8: =SUMIFS(FACILITIES!S:S,FACILITIES!B:B,B8) -> 0 | T8: =SUMIFS('F & B'!G:G,'F & B'!B:B,B8) -> 0 | U8: =T8*0.15 -> 0 | V8: =SUMIFS('FIXED AMOUNT'!G:G,'FIXED AMOUNT'!B:B,B8) -> 7000 | W8: =SUM(D8:V8) -> 10500 | X8: =SUMIFS('FIXED AMOUNT'!E:E,'FIXED AMOUNT'!B:B,'data base '!B:B) -> 0 | Y8: =SUMIFS('FIXED AMOUNT'!F:F,'FIXED AMOUNT'!B:B,'data base '!B:B) -> 0 | Z8: =SUMIFS('FIXED AMOUNT'!V:V,'FIXED AMOUNT'!B:B,B:B) -> 0 | AA8: =W8+X8-Y8+Z8 -> 10500 | AB8: =W8*0.1 -> 1050 | AC8: 45945 | AD8: =AA8+AB8 -> 11550
A9: 8 | B9: HCFM-0509 | C9: MR.SYED ABDULLAH ALI | D9: =SUMIFS(FACILITIES!E:E,FACILITIES!$B:$B,B9) -> 0 | E9: =SUMIFS(FACILITIES!F:F,FACILITIES!$B:$B,$B9) -> 600 | F9: =SUMIFS(FACILITIES!G:G,FACILITIES!$B:$B,B9) -> 0 | G9: =SUMIFS(FACILITIES!H:H,FACILITIES!$B:$B,B9) -> 0 | H9: =SUMIFS(FACILITIES!I:I,FACILITIES!$B:$B,B9) -> 0 | I9: =SUMIFS(FACILITIES!J:J,FACILITIES!$B:$B,B9) -> 0 | J9: =SUMIFS(FACILITIES!K:K,FACILITIES!$B:$B,B9) -> 0 | K9: =SUMIFS(FACILITIES!L:L,FACILITIES!$B:$B,B9) -> 0 | L9: =SUMIFS(FACILITIES!M:M,FACILITIES!$B:$B,B9) -> 0 | M9: =SUMIFS(FACILITIES!N:N,FACILITIES!$B:$B,B9) -> 0 | N9: =SUMIFS(FACILITIES!O:O,FACILITIES!$B:$B,B9) -> 0 | O9: =SUMIFS(FACILITIES!P:P,FACILITIES!$B:$B,B9) -> 0 | P9: =SUMIFS(FACILITIES!Q:Q,FACILITIES!$B:$B,B9) -> 0 | Q9: =SUMIFS(FACILITIES!R:R,FACILITIES!$B:$B,B9) -> 0 | R9: =SUMIFS(FACILITIES!T:T,FACILITIES!B:B,B9) -> 0 | S9: =SUMIFS(FACILITIES!S:S,FACILITIES!B:B,B9) -> 0 | T9: =SUMIFS('F & B'!G:G,'F & B'!B:B,B9) -> 1300 | U9: =T9*0.15 -> 195 | V9: =SUMIFS('FIXED AMOUNT'!G:G,'FIXED AMOUNT'!B:B,B9) -> 7000 | W9: =SUM(D9:V9) -> 9095 | X9: =SUMIFS('FIXED AMOUNT'!E:E,'FIXED AMOUNT'!B:B,'data base '!B:B) -> 0 | Y9: =SUMIFS('FIXED AMOUNT'!F:F,'FIXED AMOUNT'!B:B,'data base '!B:B) -> 0 | Z9: =SUMIFS('FIXED AMOUNT'!V:V,'FIXED AMOUNT'!B:B,B:B) -> 0 | AA9: =W9+X9-Y9+Z9 -> 9095 | AB9: =W9*0.1 -> 909.5 | AC9: 45945 | AD9: =AA9+AB9 -> 10004.5
A10: 9 | B10: HCFM-0510 | C10: MR.MUHAMMAD RIZWAN | D10: =SUMIFS(FACILITIES!E:E,FACILITIES!$B:$B,B10) -> 1800 | E10: =SUMIFS(FACILITIES!F:F,FACILITIES!$B:$B,$B10) -> 750 | F10: =SUMIFS(FACILITIES!G:G,FACILITIES!$B:$B,B10) -> 0 | G10: =SUMIFS(FACILITIES!H:H,FACILITIES!$B:$B,B10) -> 0 | H10: =SUMIFS(FACILITIES!I:I,FACILITIES!$B:$B,B10) -> 0 | I10: =SUMIFS(FACILITIES!J:J,FACILITIES!$B:$B,B10) -> 0 | J10: =SUMIFS(FACILITIES!K:K,FACILITIES!$B:$B,B10) -> 0 | K10: =SUMIFS(FACILITIES!L:L,FACILITIES!$B:$B,B10) -> 0 | L10: =SUMIFS(FACILITIES!M:M,FACILITIES!$B:$B,B10) -> 0 | M10: =SUMIFS(FACILITIES!N:N,FACILITIES!$B:$B,B10) -> 0 | N10: =SUMIFS(FACILITIES!O:O,FACILITIES!$B:$B,B10) -> 0 | O10: =SUMIFS(FACILITIES!P:P,FACILITIES!$B:$B,B10) -> 0 | P10: =SUMIFS(FACILITIES!Q:Q,FACILITIES!$B:$B,B10) -> 0 | Q10: =SUMIFS(FACILITIES!R:R,FACILITIES!$B:$B,B10) -> 0 | R10: =SUMIFS(FACILITIES!T:T,FACILITIES!B:B,B10) -> 0 | S10: =SUMIFS(FACILITIES!S:S,FACILITIES!B:B,B10) -> 0 | T10: =SUMIFS('F & B'!G:G,'F & B'!B:B,B10) -> 500 | U10: =T10*0.15 -> 75 | V10: =SUMIFS('FIXED AMOUNT'!G:G,'FIXED AMOUNT'!B:B,B10) -> 7000 | W10: =SUM(D10:V10) -> 10125 | X10: =SUMIFS('FIXED AMOUNT'!E:E,'FIXED AMOUNT'!B:B,'data base '!B:B) -> 0 | Y10: =SUMIFS('FIXED AMOUNT'!F:F,'FIXED AMOUNT'!B:B,'data base '!B:B) -> 0 | Z10: =SUMIFS('FIXED AMOUNT'!V:V,'FIXED AMOUNT'!B:B,B:B) -> 17926 | AA10: =W10+X10-Y10+Z10 -> 28051 | AB10: =W10*0.1 -> 1012.5 | AC10: 45945 | AD10: =AA10+AB10 -> 29063.5
A11: 10 | B11: HCFM-0511 | C11: MR.TALHAR AHMED | D11: =SUMIFS(FACILITIES!E:E,FACILITIES!$B:$B,B11) -> 0 | E11: =SUMIFS(FACILITIES!F:F,FACILITIES!$B:$B,$B11) -> 0 | F11: =SUMIFS(FACILITIES!G:G,FACILITIES!$B:$B,B11) -> 0 | G11: =SUMIFS(FACILITIES!H:H,FACILITIES!$B:$B,B11) -> 0 | H11: =SUMIFS(FACILITIES!I:I,FACILITIES!$B:$B,B11) -> 0 | I11: =SUMIFS(FACILITIES!J:J,FACILITIES!$B:$B,B11) -> 0 | J11: =SUMIFS(FACILITIES!K:K,FACILITIES!$B:$B,B11) -> 0 | K11: =SUMIFS(FACILITIES!L:L,FACILITIES!$B:$B,B11) -> 0 | L11: =SUMIFS(FACILITIES!M:M,FACILITIES!$B:$B,B11) -> 0 | M11: =SUMIFS(FACILITIES!N:N,FACILITIES!$B:$B,B11) -> 0 | N11: =SUMIFS(FACILITIES!O:O,FACILITIES!$B:$B,B11) -> 0 | O11: =SUMIFS(FACILITIES!P:P,FACILITIES!$B:$B,B11) -> 0 | P11: =SUMIFS(FACILITIES!Q:Q,FACILITIES!$B:$B,B11) -> 0 | Q11: =SUMIFS(FACILITIES!R:R,FACILITIES!$B:$B,B11) -> 0 | R11: =SUMIFS(FACILITIES!T:T,FACILITIES!B:B,B11) -> 0 | S11: =SUMIFS(FACILITIES!S:S,FACILITIES!B:B,B11) -> 0 | T11: =SUMIFS('F & B'!G:G,'F & B'!B:B,B11) -> 0 | U11: =T11*0.15 -> 0 | V11: =SUMIFS('FIXED AMOUNT'!G:G,'FIXED AMOUNT'!B:B,B11) -> 7000 | W11: =SUM(D11:V11) -> 7000 | X11: =SUMIFS('FIXED AMOUNT'!E:E,'FIXED AMOUNT'!B:B,'data base '!B:B) -> 0 | Y11: =SUMIFS('FIXED AMOUNT'!F:F,'FIXED AMOUNT'!B:B,'data base '!B:B) -> 0 | Z11: =SUMIFS('FIXED AMOUNT'!V:V,'FIXED AMOUNT'!B:B,B:B) -> 0 | AA11: =W11+X11-Y11+Z11 -> 7000 | AB11: =W11*0.1 -> 700 | AC11: 45945 | AD11: =AA11+AB11 -> 7700
A12: 11 | B12: HCFM-0512 | C12: MR.ZEESHAN IQBAL | D12: =SUMIFS(FACILITIES!E:E,FACILITIES!$B:$B,B12) -> 0 | E12: =SUMIFS(FACILITIES!F:F,FACILITIES!$B:$B,$B12) -> 6150 | F12: =SUMIFS(FACILITIES!G:G,FACILITIES!$B:$B,B12) -> 0 | G12: =SUMIFS(FACILITIES!H:H,FACILITIES!$B:$B,B12) -> 0 | H12: =SUMIFS(FACILITIES!I:I,FACILITIES!$B:$B,B12) -> 0 | I12: =SUMIFS(FACILITIES!J:J,FACILITIES!$B:$B,B12) -> 3100 | J12: =SUMIFS(FACILITIES!K:K,FACILITIES!$B:$B,B12) -> 0 | K12: =SUMIFS(FACILITIES!L:L,FACILITIES!$B:$B,B12) -> 0 | L12: =SUMIFS(FACILITIES!M:M,FACILITIES!$B:$B,B12) -> 0 | M12: =SUMIFS(FACILITIES!N:N,FACILITIES!$B:$B,B12) -> 0 | N12: =SUMIFS(FACILITIES!O:O,FACILITIES!$B:$B,B12) -> 0 | O12: =SUMIFS(FACILITIES!P:P,FACILITIES!$B:$B,B12) -> 0 | P12: =SUMIFS(FACILITIES!Q:Q,FACILITIES!$B:$B,B12) -> 0 | Q12: =SUMIFS(FACILITIES!R:R,FACILITIES!$B:$B,B12) -> 0 | R12: =SUMIFS(FACILITIES!T:T,FACILITIES!B:B,B12) -> 4000 | S12: =SUMIFS(FACILITIES!S:S,FACILITIES!B:B,B12) -> 0 | T12: =SUMIFS('F & B'!G:G,'F & B'!B:B,B12) -> 6150 | U12: =T12*0.15 -> 922.5 | V12: =SUMIFS('FIXED AMOUNT'!G:G,'FIXED AMOUNT'!B:B,B12) -> 7000 | W12: =SUM(D12:V12) -> 27322.5 | X12: =SUMIFS('FIXED AMOUNT'!E:E,'FIXED AMOUNT'!B:B,'data base '!B:B) -> 0 | Y12: =SUMIFS('FIXED AMOUNT'!F:F,'FIXED AMOUNT'!B:B,'data base '!B:B) -> 0 | Z12: =SUMIFS('FIXED AMOUNT'!V:V,'FIXED AMOUNT'!B:B,B:B) -> 3176 | AA12: =W12+X12-Y12+Z12 -> 30498.5 | AB12: =W12*0.1 -> 2732.25 | AC12: 45945 | AD12: =AA12+AB12 -> 33230.75
A13: 12 | B13: HCFM-0513 | C13: MR.SAJJAD ALI | D13: =SUMIFS(FACILITIES!E:E,FACILITIES!$B:$B,B13) -> 0 | E13: =SUMIFS(FACILITIES!F:F,FACILITIES!$B:$B,$B13) -> 0 | F13: =SUMIFS(FACILITIES!G:G,FACILITIES!$B:$B,B13) -> 0 | G13: =SUMIFS(FACILITIES!H:H,FACILITIES!$B:$B,B13) -> 0 | H13: =SUMIFS(FACILITIES!I:I,FACILITIES!$B:$B,B13) -> 0 | I13: =SUMIFS(FACILITIES!J:J,FACILITIES!$B:$B,B13) -> 0 | J13: =SUMIFS(FACILITIES!K:K,FACILITIES!$B:$B,B13) -> 0 | K13: =SUMIFS(FACILITIES!L:L,FACILITIES!$B:$B,B13) -> 0 | L13: =SUMIFS(FACILITIES!M:M,FACILITIES!$B:$B,B13) -> 0 | M13: =SUMIFS(FACILITIES!N:N,FACILITIES!$B:$B,B13) -> 0 | N13: =SUMIFS(FACILITIES!O:O,FACILITIES!$B:$B,B13) -> 0 | O13: =SUMIFS(FACILITIES!P:P,FACILITIES!$B:$B,B13) -> 12000 | P13: =SUMIFS(FACILITIES!Q:Q,FACILITIES!$B:$B,B13) -> 0 | Q13: =SUMIFS(FACILITIES!R:R,FACILITIES!$B:$B,B13) -> 0 | R13: =SUMIFS(FACILITIES!T:T,FACILITIES!B:B,B13) -> 0 | S13: =SUMIFS(FACILITIES!S:S,FACILITIES!B:B,B13) -> 0 | T13: =SUMIFS('F & B'!G:G,'F & B'!B:B,B13) -> 23647 | U13: =T13*0.15 -> 3547.05 | V13: =SUMIFS('FIXED AMOUNT'!G:G,'FIXED AMOUNT'!B:B,B13) -> 7000 | W13: =SUM(D13:V13) -> 46194.05 | X13: =SUMIFS('FIXED AMOUNT'!E:E,'FIXED AMOUNT'!B:B,'data base '!B:B) -> 0 | Y13: =SUMIFS('FIXED AMOUNT'!F:F,'FIXED AMOUNT'!B:B,'data base '!B:B) -> 0 | Z13: =SUMIFS('FIXED AMOUNT'!V:V,'FIXED AMOUNT'!B:B,B:B) -> 0 | AA13: =W13+X13-Y13+Z13 -> 46194.05 | AB13: =W13*0.1 -> 4619.405 | AC13: 45945 | AD13: =AA13+AB13 -> 50813.455
A14: 13 | B14: HCFM-0514 | C14: MR.DILEEP KUMAR | D14: =SUMIFS(FACILITIES!E:E,FACILITIES!$B:$B,B14) -> 0 | E14: =SUMIFS(FACILITIES!F:F,FACILITIES!$B:$B,$B14) -> 0 | F14: =SUMIFS(FACILITIES!G:G,FACILITIES!$B:$B,B14) -> 0 | G14: =SUMIFS(FACILITIES!H:H,FACILITIES!$B:$B,B14) -> 0 | H14: =SUMIFS(FACILITIES!I:I,FACILITIES!$B:$B,B14) -> 0 | I14: =SUMIFS(FACILITIES!J:J,FACILITIES!$B:$B,B14) -> 0 | J14: =SUMIFS(FACILITIES!K:K,FACILITIES!$B:$B,B14) -> 0 | K14: =SUMIFS(FACILITIES!L:L,FACILITIES!$B:$B,B14) -> 0 | L14: =SUMIFS(FACILITIES!M:M,FACILITIES!$B:$B,B14) -> 0 | M14: =SUMIFS(FACILITIES!N:N,FACILITIES!$B:$B,B14) -> 0 | N14: =SUMIFS(FACILITIES!O:O,FACILITIES!$B:$B,B14) -> 0 | O14: =SUMIFS(FACILITIES!P:P,FACILITIES!$B:$B,B14) -> 0 | P14: =SUMIFS(FACILITIES!Q:Q,FACILITIES!$B:$B,B14) -> 0 | Q14: =SUMIFS(FACILITIES!R:R,FACILITIES!$B:$B,B14) -> 0 | R14: =SUMIFS(FACILITIES!T:T,FACILITIES!B:B,B14) -> 0 | S14: =SUMIFS(FACILITIES!S:S,FACILITIES!B:B,B14) -> 0 | T14: =SUMIFS('F & B'!G:G,'F & B'!B:B,B14) -> 39050 | U14: =T14*0.15 -> 5857.5 | V14: =SUMIFS('FIXED AMOUNT'!G:G,'FIXED AMOUNT'!B:B,B14) -> 7000 | W14: =SUM(D14:V14) -> 51907.5 | X14: =SUMIFS('FIXED AMOUNT'!E:E,'FIXED AMOUNT'!B:B,'data base '!B:B) -> 0 | Y14: =SUMIFS('FIXED AMOUNT'!F:F,'FIXED AMOUNT'!B:B,'data base '!B:B) -> 0 | Z14: =SUMIFS('FIXED AMOUNT'!V:V,'FIXED AMOUNT'!B:B,B:B) -> 12030 | AA14: =W14+X14-Y14+Z14 -> 63937.5 | AB14: =W14*0.1 -> 5190.75 | AC14: 45945 | AD14: =AA14+AB14 -> 69128.25
A15: 14 | B15: HCFM-0515 | C15: MR.TARIQUE ZUBAIR | D15: =SUMIFS(FACILITIES!E:E,FACILITIES!$B:$B,B15) -> 0 | E15: =SUMIFS(FACILITIES!F:F,FACILITIES!$B:$B,$B15) -> 1050 | F15: =SUMIFS(FACILITIES!G:G,FACILITIES!$B:$B,B15) -> 0 | G15: =SUMIFS(FACILITIES!H:H,FACILITIES!$B:$B,B15) -> 0 | H15: =SUMIFS(FACILITIES!I:I,FACILITIES!$B:$B,B15) -> 0 | I15: =SUMIFS(FACILITIES!J:J,FACILITIES!$B:$B,B15) -> 1500 | J15: =SUMIFS(FACILITIES!K:K,FACILITIES!$B:$B,B15) -> 0 | K15: =SUMIFS(FACILITIES!L:L,FACILITIES!$B:$B,B15) -> 0 | L15: =SUMIFS(FACILITIES!M:M,FACILITIES!$B:$B,B15) -> 0 | M15: =SUMIFS(FACILITIES!N:N,FACILITIES!$B:$B,B15) -> 0 | N15: =SUMIFS(FACILITIES!O:O,FACILITIES!$B:$B,B15) -> 0 | O15: =SUMIFS(FACILITIES!P:P,FACILITIES!$B:$B,B15) -> 0 | P15: =SUMIFS(FACILITIES!Q:Q,FACILITIES!$B:$B,B15) -> 0 | Q15: =SUMIFS(FACILITIES!R:R,FACILITIES!$B:$B,B15) -> 0 | R15: =SUMIFS(FACILITIES!T:T,FACILITIES!B:B,B15) -> 0 | S15: =SUMIFS(FACILITIES!S:S,FACILITIES!B:B,B15) -> 0 | T15: =SUMIFS('F & B'!G:G,'F & B'!B:B,B15) -> 25360 | U15: =T15*0.15 -> 3804 | V15: =SUMIFS('FIXED AMOUNT'!G:G,'FIXED AMOUNT'!B:B,B15) -> 7000 | W15: =SUM(D15:V15) -> 38714 | X15: =SUMIFS('FIXED AMOUNT'!E:E,'FIXED AMOUNT'!B:B,'data base '!B:B) -> 0 | Y15: =SUMIFS('FIXED AMOUNT'!F:F,'FIXED AMOUNT'!B:B,'data base '!B:B) -> 0 | Z15: =SUMIFS('FIXED AMOUNT'!V:V,'FIXED AMOUNT'!B:B,B:B) -> 0 | AA15: =W15+X15-Y15+Z15 -> 38714 | AB15: =W15*0.1 -> 3871.4 | AC15: 45945 | AD15: 0
A16: 15 | B16: HCFM-0516 | C16: MR.ATIF SHAFQAT | D16: =SUMIFS(FACILITIES!E:E,FACILITIES!$B:$B,B16) -> 0 | E16: =SUMIFS(FACILITIES!F:F,FACILITIES!$B:$B,$B16) -> 0 | F16: =SUMIFS(FACILITIES!G:G,FACILITIES!$B:$B,B16) -> 0 | G16: =SUMIFS(FACILITIES!H:H,FACILITIES!$B:$B,B16) -> 0 | H16: =SUMIFS(FACILITIES!I:I,FACILITIES!$B:$B,B16) -> 0 | I16: =SUMIFS(FACILITIES!J:J,FACILITIES!$B:$B,B16) -> 600 | J16: =SUMIFS(FACILITIES!K:K,FACILITIES!$B:$B,B16) -> 0 | K16: =SUMIFS(FACILITIES!L:L,FACILITIES!$B:$B,B16) -> 0 | L16: =SUMIFS(FACILITIES!M:M,FACILITIES!$B:$B,B16) -> 0 | M16: =SUMIFS(FACILITIES!N:N,FACILITIES!$B:$B,B16) -> 0 | N16: =SUMIFS(FACILITIES!O:O,FACILITIES!$B:$B,B16) -> 0 | O16: =SUMIFS(FACILITIES!P:P,FACILITIES!$B:$B,B16) -> 0 | P16: =SUMIFS(FACILITIES!Q:Q,FACILITIES!$B:$B,B16) -> 0 | Q16: =SUMIFS(FACILITIES!R:R,FACILITIES!$B:$B,B16) -> 0 | R16: =SUMIFS(FACILITIES!T:T,FACILITIES!B:B,B16) -> 0 | S16: =SUMIFS(FACILITIES!S:S,FACILITIES!B:B,B16) -> 0 | T16: =SUMIFS('F & B'!G:G,'F & B'!B:B,B16) -> 3970 | U16: =T16*0.15 -> 595.5 | V16: =SUMIFS('FIXED AMOUNT'!G:G,'FIXED AMOUNT'!B:B,B16) -> 7000 | W16: =SUM(D16:V16) -> 12165.5 | X16: =SUMIFS('FIXED AMOUNT'!E:E,'FIXED AMOUNT'!B:B,'data base '!B:B) -> 0 | Y16: =SUMIFS('FIXED AMOUNT'!F:F,'FIXED AMOUNT'!B:B,'data base '!B:B) -> 0 | Z16: =SUMIFS('FIXED AMOUNT'!V:V,'FIXED AMOUNT'!B:B,B:B) -> 47155 | AA16: =W16+X16-Y16+Z16 -> 59320.5 | AB16: =W16*0.1 -> 1216.55 | AC16: 45945 | AD16: =AA16+AB16 -> 60537.05
A17: 16 | B17: HCFM-0517 | C17: DR.ATHESHAM UL HAQ RANA | D17: =SUMIFS(FACILITIES!E:E,FACILITIES!$B:$B,B17) -> 0 | E17: =SUMIFS(FACILITIES!F:F,FACILITIES!$B:$B,$B17) -> 0 | F17: =SUMIFS(FACILITIES!G:G,FACILITIES!$B:$B,B17) -> 0 | G17: =SUMIFS(FACILITIES!H:H,FACILITIES!$B:$B,B17) -> 0 | H17: =SUMIFS(FACILITIES!I:I,FACILITIES!$B:$B,B17) -> 0 | I17: =SUMIFS(FACILITIES!J:J,FACILITIES!$B:$B,B17) -> 0 | J17: =SUMIFS(FACILITIES!K:K,FACILITIES!$B:$B,B17) -> 0 | K17: =SUMIFS(FACILITIES!L:L,FACILITIES!$B:$B,B17) -> 0 | L17: =SUMIFS(FACILITIES!M:M,FACILITIES!$B:$B,B17) -> 0 | M17: =SUMIFS(FACILITIES!N:N,FACILITIES!$B:$B,B17) -> 0 | N17: =SUMIFS(FACILITIES!O:O,FACILITIES!$B:$B,B17) -> 0 | O17: =SUMIFS(FACILITIES!P:P,FACILITIES!$B:$B,B17) -> 0 | P17: =SUMIFS(FACILITIES!Q:Q,FACILITIES!$B:$B,B17) -> 0 | Q17: =SUMIFS(FACILITIES!R:R,FACILITIES!$B:$B,B17) -> 0 | R17: =SUMIFS(FACILITIES!T:T,FACILITIES!B:B,B17) -> 0 | S17: =SUMIFS(FACILITIES!S:S,FACILITIES!B:B,B17) -> 0 | T17: =SUMIFS('F & B'!G:G,'F & B'!B:B,B17) -> 0 | U17: =T17*0.15 -> 0 | V17: =SUMIFS('FIXED AMOUNT'!G:G,'FIXED AMOUNT'!B:B,B17) -> 7000 | W17: =SUM(D17:V17) -> 7000 | X17: =SUMIFS('FIXED AMOUNT'!E:E,'FIXED AMOUNT'!B:B,'data base '!B:B) -> 0 | Y17: =SUMIFS('FIXED AMOUNT'!F:F,'FIXED AMOUNT'!B:B,'data base '!B:B) -> 0 | Z17: =SUMIFS('FIXED AMOUNT'!V:V,'FIXED AMOUNT'!B:B,B:B) -> 37300 | AA17: =W17+X17-Y17+Z17 -> 44300 | AB17: =W17*0.1 -> 700 | AC17: 45945 | AD17: =AA17+AB17 -> 45000
A18: 17 | B18: HCFM-0518 | C18: DR.SANTOSH KUMAR | D18: =SUMIFS(FACILITIES!E:E,FACILITIES!$B:$B,B18) -> 0 | E18: =SUMIFS(FACILITIES!F:F,FACILITIES!$B:$B,$B18) -> 1200 | F18: =SUMIFS(FACILITIES!G:G,FACILITIES!$B:$B,B18) -> 0 | G18: =SUMIFS(FACILITIES!H:H,FACILITIES!$B:$B,B18) -> 0 | H18: =SUMIFS(FACILITIES!I:I,FACILITIES!$B:$B,B18) -> 0 | I18: =SUMIFS(FACILITIES!J:J,FACILITIES!$B:$B,B18) -> 0 | J18: =SUMIFS(FACILITIES!K:K,FACILITIES!$B:$B,B18) -> 0 | K18: =SUMIFS(FACILITIES!L:L,FACILITIES!$B:$B,B18) -> 0 | L18: =SUMIFS(FACILITIES!M:M,FACILITIES!$B:$B,B18) -> 0 | M18: =SUMIFS(FACILITIES!N:N,FACILITIES!$B:$B,B18) -> 0 | N18: =SUMIFS(FACILITIES!O:O,FACILITIES!$B:$B,B18) -> 0 | O18: =SUMIFS(FACILITIES!P:P,FACILITIES!$B:$B,B18) -> 0 | P18: =SUMIFS(FACILITIES!Q:Q,FACILITIES!$B:$B,B18) -> 0 | Q18: =SUMIFS(FACILITIES!R:R,FACILITIES!$B:$B,B18) -> 0 | R18: =SUMIFS(FACILITIES!T:T,FACILITIES!B:B,B18) -> 0 | S18: =SUMIFS(FACILITIES!S:S,FACILITIES!B:B,B18) -> 0 | T18: =SUMIFS('F & B'!G:G,'F & B'!B:B,B18) -> 0 | U18: =T18*0.15 -> 0 | V18: =SUMIFS('FIXED AMOUNT'!G:G,'FIXED AMOUNT'!B:B,B18) -> 7000 | W18: =SUM(D18:V18) -> 8200 | X18: =SUMIFS('FIXED AMOUNT'!E:E,'FIXED AMOUNT'!B:B,'data base '!B:B) -> 0 | Y18: =SUMIFS('FIXED AMOUNT'!F:F,'FIXED AMOUNT'!B:B,'data base '!B:B) -> 0 | Z18: =SUMIFS('FIXED AMOUNT'!V:V,'FIXED AMOUNT'!B:B,B:B) -> 1076 | AA18: =W18+X18-Y18+Z18 -> 9276 | AB18: =W18*0.1 -> 820 | AC18: 45945 | AD18: =AA18+AB18 -> 10096
A19: 18 | B19: HCFM-0519 | C19: DR.NAZEER HUSSAIN KALHORO | D19: =SUMIFS(FACILITIES!E:E,FACILITIES!$B:$B,B19) -> 0 | E19: =SUMIFS(FACILITIES!F:F,FACILITIES!$B:$B,$B19) -> 0 | F19: =SUMIFS(FACILITIES!G:G,FACILITIES!$B:$B,B19) -> 0 | G19: =SUMIFS(FACILITIES!H:H,FACILITIES!$B:$B,B19) -> 0 | H19: =SUMIFS(FACILITIES!I:I,FACILITIES!$B:$B,B19) -> 0 | I19: =SUMIFS(FACILITIES!J:J,FACILITIES!$B:$B,B19) -> 4000 | J19: =SUMIFS(FACILITIES!K:K,FACILITIES!$B:$B,B19) -> 0 | K19: =SUMIFS(FACILITIES!L:L,FACILITIES!$B:$B,B19) -> 0 | L19: =SUMIFS(FACILITIES!M:M,FACILITIES!$B:$B,B19) -> 0 | M19: =SUMIFS(FACILITIES!N:N,FACILITIES!$B:$B,B19) -> 0 | N19: =SUMIFS(FACILITIES!O:O,FACILITIES!$B:$B,B19) -> 0 | O19: =SUMIFS(FACILITIES!P:P,FACILITIES!$B:$B,B19) -> 0 | P19: =SUMIFS(FACILITIES!Q:Q,FACILITIES!$B:$B,B19) -> 0 | Q19: =SUMIFS(FACILITIES!R:R,FACILITIES!$B:$B,B19) -> 0 | R19: =SUMIFS(FACILITIES!T:T,FACILITIES!B:B,B19) -> 4500 | S19: =SUMIFS(FACILITIES!S:S,FACILITIES!B:B,B19) -> 0 | T19: =SUMIFS('F & B'!G:G,'F & B'!B:B,B19) -> 34425 | U19: =T19*0.15 -> 5163.75 | V19: =SUMIFS('FIXED AMOUNT'!G:G,'FIXED AMOUNT'!B:B,B19) -> 7000 | W19: =SUM(D19:V19) -> 55088.75 | X19: =SUMIFS('FIXED AMOUNT'!E:E,'FIXED AMOUNT'!B:B,'data base '!B:B) -> 0 | Y19: =SUMIFS('FIXED AMOUNT'!F:F,'FIXED AMOUNT'!B:B,'data base '!B:B) -> 0 | Z19: =SUMIFS('FIXED AMOUNT'!V:V,'FIXED AMOUNT'!B:B,B:B) -> 0 | AA19: =W19+X19-Y19+Z19 -> 55088.75 | AB19: =W19*0.1 -> 5508.875 | AC19: 45945 | AD19: =AA19+AB19 -> 60597.625
A20: 19 | B20: HCFM-0520 | C20: MR.NIZAM UDDIN NIZAMANI | D20: =SUMIFS(FACILITIES!E:E,FACILITIES!$B:$B,B20) -> 0 | E20: =SUMIFS(FACILITIES!F:F,FACILITIES!$B:$B,$B20) -> 0 | F20: =SUMIFS(FACILITIES!G:G,FACILITIES!$B:$B,B20) -> 0 | G20: =SUMIFS(FACILITIES!H:H,FACILITIES!$B:$B,B20) -> 0 | H20: =SUMIFS(FACILITIES!I:I,FACILITIES!$B:$B,B20) -> 0 | I20: =SUMIFS(FACILITIES!J:J,FACILITIES!$B:$B,B20) -> 0 | J20: =SUMIFS(FACILITIES!K:K,FACILITIES!$B:$B,B20) -> 0 | K20: =SUMIFS(FACILITIES!L:L,FACILITIES!$B:$B,B20) -> 0 | L20: =SUMIFS(FACILITIES!M:M,FACILITIES!$B:$B,B20) -> 0 | M20: =SUMIFS(FACILITIES!N:N,FACILITIES!$B:$B,B20) -> 0 | N20: =SUMIFS(FACILITIES!O:O,FACILITIES!$B:$B,B20) -> 0 | O20: =SUMIFS(FACILITIES!P:P,FACILITIES!$B:$B,B20) -> 0 | P20: =SUMIFS(FACILITIES!Q:Q,FACILITIES!$B:$B,B20) -> 0 | Q20: =SUMIFS(FACILITIES!R:R,FACILITIES!$B:$B,B20) -> 0 | R20: =SUMIFS(FACILITIES!T:T,FACILITIES!B:B,B20) -> 0 | S20: =SUMIFS(FACILITIES!S:S,FACILITIES!B:B,B20) -> 0 | T20: =SUMIFS('F & B'!G:G,'F & B'!B:B,B20) -> 98060 | U20: =T20*0.15 -> 14709 | V20: =SUMIFS('FIXED AMOUNT'!G:G,'FIXED AMOUNT'!B:B,B20) -> 7000 | W20: =SUM(D20:V20) -> 119769 | X20: =SUMIFS('FIXED AMOUNT'!E:E,'FIXED AMOUNT'!B:B,'data base '!B:B) -> 0 | Y20: =SUMIFS('FIXED AMOUNT'!F:F,'FIXED AMOUNT'!B:B,'data base '!B:B) -> 0 | Z20: =SUMIFS('FIXED AMOUNT'!V:V,'FIXED AMOUNT'!B:B,B:B) -> 0 | AA20: =W20+X20-Y20+Z20 -> 119769 | AB20: =W20*0.1 -> 11976.9 | AC20: 45945 | AD20: =AA20+AB20 -> 131745.9
A21: 20 | B21: HCFM-0521 | C21: MR.HAFEEZ AHMED SIYAL | D21: =SUMIFS(FACILITIES!E:E,FACILITIES!$B:$B,B21) -> 0 | E21: =SUMIFS(FACILITIES!F:F,FACILITIES!$B:$B,$B21) -> 1200 | F21: =SUMIFS(FACILITIES!G:G,FACILITIES!$B:$B,B21) -> 0 | G21: =SUMIFS(FACILITIES!H:H,FACILITIES!$B:$B,B21) -> 0 | H21: =SUMIFS(FACILITIES!I:I,FACILITIES!$B:$B,B21) -> 0 | I21: =SUMIFS(FACILITIES!J:J,FACILITIES!$B:$B,B21) -> 2800 | J21: =SUMIFS(FACILITIES!K:K,FACILITIES!$B:$B,B21) -> 0 | K21: =SUMIFS(FACILITIES!L:L,FACILITIES!$B:$B,B21) -> 0 | L21: =SUMIFS(FACILITIES!M:M,FACILITIES!$B:$B,B21) -> 0 | M21: =SUMIFS(FACILITIES!N:N,FACILITIES!$B:$B,B21) -> 0 | N21: =SUMIFS(FACILITIES!O:O,FACILITIES!$B:$B,B21) -> 0 | O21: =SUMIFS(FACILITIES!P:P,FACILITIES!$B:$B,B21) -> 0 | P21: =SUMIFS(FACILITIES!Q:Q,FACILITIES!$B:$B,B21) -> 0 | Q21: =SUMIFS(FACILITIES!R:R,FACILITIES!$B:$B,B21) -> 0 | R21: =SUMIFS(FACILITIES!T:T,FACILITIES!B:B,B21) -> 4000 | S21: =SUMIFS(FACILITIES!S:S,FACILITIES!B:B,B21) -> 0 | T21: =SUMIFS('F & B'!G:G,'F & B'!B:B,B21) -> 11185 | U21: =T21*0.15 -> 1677.75 | V21: =SUMIFS('FIXED AMOUNT'!G:G,'FIXED AMOUNT'!B:B,B21) -> 7000 | W21: =SUM(D21:V21) -> 27862.75 | X21: =SUMIFS('FIXED AMOUNT'!E:E,'FIXED AMOUNT'!B:B,'data base '!B:B) -> 0 | Y21: =SUMIFS('FIXED AMOUNT'!F:F,'FIXED AMOUNT'!B:B,'data base '!B:B) -> 0 | Z21: =SUMIFS('FIXED AMOUNT'!V:V,'FIXED AMOUNT'!B:B,B:B) -> 0 | AA21: =W21+X21-Y21+Z21 -> 27862.75 | AB21: =W21*0.1 -> 2786.275 | AC21: 45945 | AD21: =AA21+AB21 -> 30649.025
A22: 21 | B22: HCFM-0522 | C22: MR.IQBAL AHMED MALLAH | D22: =SUMIFS(FACILITIES!E:E,FACILITIES!$B:$B,B22) -> 0 | E22: =SUMIFS(FACILITIES!F:F,FACILITIES!$B:$B,$B22) -> 0 | F22: =SUMIFS(FACILITIES!G:G,FACILITIES!$B:$B,B22) -> 0 | G22: =SUMIFS(FACILITIES!H:H,FACILITIES!$B:$B,B22) -> 0 | H22: =SUMIFS(FACILITIES!I:I,FACILITIES!$B:$B,B22) -> 0 | I22: =SUMIFS(FACILITIES!J:J,FACILITIES!$B:$B,B22) -> 3200 | J22: =SUMIFS(FACILITIES!K:K,FACILITIES!$B:$B,B22) -> 0 | K22: =SUMIFS(FACILITIES!L:L,FACILITIES!$B:$B,B22) -> 0 | L22: =SUMIFS(FACILITIES!M:M,FACILITIES!$B:$B,B22) -> 0 | M22: =SUMIFS(FACILITIES!N:N,FACILITIES!$B:$B,B22) -> 0 | N22: =SUMIFS(FACILITIES!O:O,FACILITIES!$B:$B,B22) -> 0 | O22: =SUMIFS(FACILITIES!P:P,FACILITIES!$B:$B,B22) -> 0 | P22: =SUMIFS(FACILITIES!Q:Q,FACILITIES!$B:$B,B22) -> 0 | Q22: =SUMIFS(FACILITIES!R:R,FACILITIES!$B:$B,B22) -> 0 | R22: =SUMIFS(FACILITIES!T:T,FACILITIES!B:B,B22) -> 0 | S22: =SUMIFS(FACILITIES!S:S,FACILITIES!B:B,B22) -> 0 | T22: =SUMIFS('F & B'!G:G,'F & B'!B:B,B22) -> 22474 | U22: =T22*0.15 -> 3371.1 | V22: =SUMIFS('FIXED AMOUNT'!G:G,'FIXED AMOUNT'!B:B,B22) -> 7000 | W22: =SUM(D22:V22) -> 36045.1 | X22: =SUMIFS('FIXED AMOUNT'!E:E,'FIXED AMOUNT'!B:B,'data base '!B:B) -> 0 | Y22: =SUMIFS('FIXED AMOUNT'!F:F,'FIXED AMOUNT'!B:B,'data base '!B:B) -> 0 | Z22: =SUMIFS('FIXED AMOUNT'!V:V,'FIXED AMOUNT'!B:B,B:B) -> 0 | AA22: =W22+X22-Y22+Z22 -> 36045.1 | AB22: =W22*0.1 -> 3604.51 | AC22: 45945 | AD22: =AA22+AB22 -> 39649.61
A23: 22 | B23: HCFM-0523 | C23: MR.KANYO LAL | D23: =SUMIFS(FACILITIES!E:E,FACILITIES!$B:$B,B23) -> 0 | E23: =SUMIFS(FACILITIES!F:F,FACILITIES!$B:$B,$B23) -> 0 | F23: =SUMIFS(FACILITIES!G:G,FACILITIES!$B:$B,B23) -> 0 | G23: =SUMIFS(FACILITIES!H:H,FACILITIES!$B:$B,B23) -> 0 | H23: =SUMIFS(FACILITIES!I:I,FACILITIES!$B:$B,B23) -> 0 | I23: =SUMIFS(FACILITIES!J:J,FACILITIES!$B:$B,B23) -> 0 | J23: =SUMIFS(FACILITIES!K:K,FACILITIES!$B:$B,B23) -> 0 | K23: =SUMIFS(FACILITIES!L:L,FACILITIES!$B:$B,B23) -> 0 | L23: =SUMIFS(FACILITIES!M:M,FACILITIES!$B:$B,B23) -> 0 | M23: =SUMIFS(FACILITIES!N:N,FACILITIES!$B:$B,B23) -> 0 | N23: =SUMIFS(FACILITIES!O:O,FACILITIES!$B:$B,B23) -> 0 | O23: =SUMIFS(FACILITIES!P:P,FACILITIES!$B:$B,B23) -> 0 | P23: =SUMIFS(FACILITIES!Q:Q,FACILITIES!$B:$B,B23) -> 0 | Q23: =SUMIFS(FACILITIES!R:R,FACILITIES!$B:$B,B23) -> 0 | R23: =SUMIFS(FACILITIES!T:T,FACILITIES!B:B,B23) -> 0 | S23: =SUMIFS(FACILITIES!S:S,FACILITIES!B:B,B23) -> 0 | T23: =SUMIFS('F & B'!G:G,'F & B'!B:B,B23) -> 6600 | U23: =T23*0.15 -> 990 | V23: =SUMIFS('FIXED AMOUNT'!G:G,'FIXED AMOUNT'!B:B,B23) -> 7000 | W23: =SUM(D23:V23) -> 14590 | X23: =SUMIFS('FIXED AMOUNT'!E:E,'FIXED AMOUNT'!B:B,'data base '!B:B) -> 0 | Y23: =SUMIFS('FIXED AMOUNT'!F:F,'FIXED AMOUNT'!B:B,'data base '!B:B) -> 0 | Z23: =SUMIFS('FIXED AMOUNT'!V:V,'FIXED AMOUNT'!B:B,B:B) -> 14290 | AA23: =W23+X23-Y23+Z23 -> 28880 | AB23: =W23*0.1 -> 1459 | AC23: 45945 | AD23: =AA23+AB23 -> 30339
A24: 23 | B24: HCFM-0524 | C24: MR.MANOJ KUMAR | D24: =SUMIFS(FACILITIES!E:E,FACILITIES!$B:$B,B24) -> 3000 | E24: =SUMIFS(FACILITIES!F:F,FACILITIES!$B:$B,$B24) -> 0 | F24: =SUMIFS(FACILITIES!G:G,FACILITIES!$B:$B,B24) -> 0 | G24: =SUMIFS(FACILITIES!H:H,FACILITIES!$B:$B,B24) -> 0 | H24: =SUMIFS(FACILITIES!I:I,FACILITIES!$B:$B,B24) -> 0 | I24: =SUMIFS(FACILITIES!J:J,FACILITIES!$B:$B,B24) -> 2900 | J24: =SUMIFS(FACILITIES!K:K,FACILITIES!$B:$B,B24) -> 0 | K24: =SUMIFS(FACILITIES!L:L,FACILITIES!$B:$B,B24) -> 0 | L24: =SUMIFS(FACILITIES!M:M,FACILITIES!$B:$B,B24) -> 0 | M24: =SUMIFS(FACILITIES!N:N,FACILITIES!$B:$B,B24) -> 0 | N24: =SUMIFS(FACILITIES!O:O,FACILITIES!$B:$B,B24) -> 0 | O24: =SUMIFS(FACILITIES!P:P,FACILITIES!$B:$B,B24) -> 0 | P24: =SUMIFS(FACILITIES!Q:Q,FACILITIES!$B:$B,B24) -> 0 | Q24: =SUMIFS(FACILITIES!R:R,FACILITIES!$B:$B,B24) -> 0 | R24: =SUMIFS(FACILITIES!T:T,FACILITIES!B:B,B24) -> 0 | S24: =SUMIFS(FACILITIES!S:S,FACILITIES!B:B,B24) -> 0 | T24: =SUMIFS('F & B'!G:G,'F & B'!B:B,B24) -> 25730 | U24: =T24*0.15 -> 3859.5 | V24: =SUMIFS('FIXED AMOUNT'!G:G,'FIXED AMOUNT'!B:B,B24) -> 7000 | W24: =SUM(D24:V24) -> 42489.5 | X24: =SUMIFS('FIXED AMOUNT'!E:E,'FIXED AMOUNT'!B:B,'data base '!B:B) -> 0 | Y24: =SUMIFS('FIXED AMOUNT'!F:F,'FIXED AMOUNT'!B:B,'data base '!B:B) -> 0 | Z24: =SUMIFS('FIXED AMOUNT'!V:V,'FIXED AMOUNT'!B:B,B:B) -> 0 | AA24: =W24+X24-Y24+Z24 -> 42489.5 | AB24: =W24*0.1 -> 4248.95 | AC24: 45945 | AD24: =AA24+AB24 -> 46738.45
A25: 24 | B25: HCFM-0525 | C25: DR.SAJJAD AHMED SOLANGI | D25: =SUMIFS(FACILITIES!E:E,FACILITIES!$B:$B,B25) -> 0 | E25: =SUMIFS(FACILITIES!F:F,FACILITIES!$B:$B,$B25) -> 0 | F25: =SUMIFS(FACILITIES!G:G,FACILITIES!$B:$B,B25) -> 0 | G25: =SUMIFS(FACILITIES!H:H,FACILITIES!$B:$B,B25) -> 0 | H25: =SUMIFS(FACILITIES!I:I,FACILITIES!$B:$B,B25) -> 0 | I25: =SUMIFS(FACILITIES!J:J,FACILITIES!$B:$B,B25) -> 0 | J25: =SUMIFS(FACILITIES!K:K,FACILITIES!$B:$B,B25) -> 0 | K25: =SUMIFS(FACILITIES!L:L,FACILITIES!$B:$B,B25) -> 0 | L25: =SUMIFS(FACILITIES!M:M,FACILITIES!$B:$B,B25) -> 0 | M25: =SUMIFS(FACILITIES!N:N,FACILITIES!$B:$B,B25) -> 0 | N25: =SUMIFS(FACILITIES!O:O,FACILITIES!$B:$B,B25) -> 0 | O25: =SUMIFS(FACILITIES!P:P,FACILITIES!$B:$B,B25) -> 0 | P25: =SUMIFS(FACILITIES!Q:Q,FACILITIES!$B:$B,B25) -> 0 | Q25: =SUMIFS(FACILITIES!R:R,FACILITIES!$B:$B,B25) -> 0 | R25: =SUMIFS(FACILITIES!T:T,FACILITIES!B:B,B25) -> 0 | S25: =SUMIFS(FACILITIES!S:S,FACILITIES!B:B,B25) -> 0 | T25: =SUMIFS('F & B'!G:G,'F & B'!B:B,B25) -> 6170 | U25: =T25*0.15 -> 925.5 | V25: =SUMIFS('FIXED AMOUNT'!G:G,'FIXED AMOUNT'!B:B,B25) -> 7000 | W25: =SUM(D25:V25) -> 14095.5 | X25: =SUMIFS('FIXED AMOUNT'!E:E,'FIXED AMOUNT'!B:B,'data base '!B:B) -> 0 | Y25: =SUMIFS('FIXED AMOUNT'!F:F,'FIXED AMOUNT'!B:B,'data base '!B:B) -> 0 | Z25: =SUMIFS('FIXED AMOUNT'!V:V,'FIXED AMOUNT'!B:B,B:B) -> 0 | AA25: =W25+X25-Y25+Z25 -> 14095.5 | AB25: =W25*0.1 -> 1409.55 | AC25: 45945 | AD25: =AA25+AB25 -> 15505.05
A26: 25 | B26: HCFM-0526 | C26: MR.MUIED AHMED DURRANI | D26: =SUMIFS(FACILITIES!E:E,FACILITIES!$B:$B,B26) -> 1800 | E26: =SUMIFS(FACILITIES!F:F,FACILITIES!$B:$B,$B26) -> 0 | F26: =SUMIFS(FACILITIES!G:G,FACILITIES!$B:$B,B26) -> 0 | G26: =SUMIFS(FACILITIES!H:H,FACILITIES!$B:$B,B26) -> 0 | H26: =SUMIFS(FACILITIES!I:I,FACILITIES!$B:$B,B26) -> 0 | I26: =SUMIFS(FACILITIES!J:J,FACILITIES!$B:$B,B26) -> 900 | J26: =SUMIFS(FACILITIES!K:K,FACILITIES!$B:$B,B26) -> 0 | K26: =SUMIFS(FACILITIES!L:L,FACILITIES!$B:$B,B26) -> 0 | L26: =SUMIFS(FACILITIES!M:M,FACILITIES!$B:$B,B26) -> 0 | M26: =SUMIFS(FACILITIES!N:N,FACILITIES!$B:$B,B26) -> 0 | N26: =SUMIFS(FACILITIES!O:O,FACILITIES!$B:$B,B26) -> 0 | O26: =SUMIFS(FACILITIES!P:P,FACILITIES!$B:$B,B26) -> 0 | P26: =SUMIFS(FACILITIES!Q:Q,FACILITIES!$B:$B,B26) -> 0 | Q26: =SUMIFS(FACILITIES!R:R,FACILITIES!$B:$B,B26) -> 0 | R26: =SUMIFS(FACILITIES!T:T,FACILITIES!B:B,B26) -> 7000 | S26: =SUMIFS(FACILITIES!S:S,FACILITIES!B:B,B26) -> 0 | T26: =SUMIFS('F & B'!G:G,'F & B'!B:B,B26) -> 2975 | U26: =T26*0.15 -> 446.25 | V26: =SUMIFS('FIXED AMOUNT'!G:G,'FIXED AMOUNT'!B:B,B26) -> 7000 | W26: =SUM(D26:V26) -> 20121.25 | X26: =SUMIFS('FIXED AMOUNT'!E:E,'FIXED AMOUNT'!B:B,'data base '!B:B) -> 0 | Y26: =SUMIFS('FIXED AMOUNT'!F:F,'FIXED AMOUNT'!B:B,'data base '!B:B) -> 0 | Z26: =SUMIFS('FIXED AMOUNT'!V:V,'FIXED AMOUNT'!B:B,B:B) -> 0 | AA26: =W26+X26-Y26+Z26 -> 20121.25 | AB26: =W26*0.1 -> 2012.125 | AC26: 45945 | AD26: =AA26+AB26 -> 22133.375
A27: 26 | B27: HCFM-0527 | C27: MR.SAEED AHMED | D27: =SUMIFS(FACILITIES!E:E,FACILITIES!$B:$B,B27) -> 0 | E27: =SUMIFS(FACILITIES!F:F,FACILITIES!$B:$B,$B27) -> 0 | F27: =SUMIFS(FACILITIES!G:G,FACILITIES!$B:$B,B27) -> 0 | G27: =SUMIFS(FACILITIES!H:H,FACILITIES!$B:$B,B27) -> 0 | H27: =SUMIFS(FACILITIES!I:I,FACILITIES!$B:$B,B27) -> 0 | I27: =SUMIFS(FACILITIES!J:J,FACILITIES!$B:$B,B27) -> 0 | J27: =SUMIFS(FACILITIES!K:K,FACILITIES!$B:$B,B27) -> 0 | K27: =SUMIFS(FACILITIES!L:L,FACILITIES!$B:$B,B27) -> 0 | L27: =SUMIFS(FACILITIES!M:M,FACILITIES!$B:$B,B27) -> 0 | M27: =SUMIFS(FACILITIES!N:N,FACILITIES!$B:$B,B27) -> 0 | N27: =SUMIFS(FACILITIES!O:O,FACILITIES!$B:$B,B27) -> 0 | O27: =SUMIFS(FACILITIES!P:P,FACILITIES!$B:$B,B27) -> 0 | P27: =SUMIFS(FACILITIES!Q:Q,FACILITIES!$B:$B,B27) -> 0 | Q27: =SUMIFS(FACILITIES!R:R,FACILITIES!$B:$B,B27) -> 0 | R27: =SUMIFS(FACILITIES!T:T,FACILITIES!B:B,B27) -> 0 | S27: =SUMIFS(FACILITIES!S:S,FACILITIES!B:B,B27) -> 0 | T27: =SUMIFS('F & B'!G:G,'F & B'!B:B,B27) -> 0 | U27: =T27*0.15 -> 0 | V27: =SUMIFS('FIXED AMOUNT'!G:G,'FIXED AMOUNT'!B:B,B27) -> 7000 | W27: =SUM(D27:V27) -> 7000 | X27: =SUMIFS('FIXED AMOUNT'!E:E,'FIXED AMOUNT'!B:B,'data base '!B:B) -> 0 | Y27: =SUMIFS('FIXED AMOUNT'!F:F,'FIXED AMOUNT'!B:B,'data base '!B:B) -> 0 | Z27: =SUMIFS('FIXED AMOUNT'!V:V,'FIXED AMOUNT'!B:B,B:B) -> 8847 | AA27: =W27+X27-Y27+Z27 -> 15847 | AB27: =W27*0.1 -> 700 | AC27: 45945 | AD27: =AA27+AB27 -> 16547
... A83: 82 | B83: HCFM-0645 | C83: MUNEER AHMED | D83: =SUMIFS(FACILITIES!E:E,FACILITIES!$B:$B,B83) -> 0 | E83: =SUMIFS(FACILITIES!F:F,FACILITIES!$B:$B,$B83) -> 0 | F83: =SUMIFS(FACILITIES!G:G,FACILITIES!$B:$B,B83) -> 0 | G83: =SUMIFS(FACILITIES!H:H,FACILITIES!$B:$B,B83) -> 0 | H83: =SUMIFS(FACILITIES!I:I,FACILITIES!$B:$B,B83) -> 0 | I83: =SUMIFS(FACILITIES!J:J,FACILITIES!$B:$B,B83) -> 0 | J83: =SUMIFS(FACILITIES!K:K,FACILITIES!$B:$B,B83) -> 0 | K83: =SUMIFS(FACILITIES!L:L,FACILITIES!$B:$B,B83) -> 0 | L83: =SUMIFS(FACILITIES!M:M,FACILITIES!$B:$B,B83) -> 0 | M83: =SUMIFS(FACILITIES!N:N,FACILITIES!$B:$B,B83) -> 0 | N83: =SUMIFS(FACILITIES!O:O,FACILITIES!$B:$B,B83) -> 0 | O83: =SUMIFS(FACILITIES!P:P,FACILITIES!$B:$B,B83) -> 0 | P83: =SUMIFS(FACILITIES!Q:Q,FACILITIES!$B:$B,B83) -> 0 | Q83: =SUMIFS(FACILITIES!R:R,FACILITIES!$B:$B,B83) -> 0 | R83: =SUMIFS(FACILITIES!T:T,FACILITIES!B:B,B83) -> 0 | S83: =SUMIFS(FACILITIES!S:S,FACILITIES!B:B,B83) -> 0 | T83: =SUMIFS('F & B'!G:G,'F & B'!B:B,B83) -> 0 | U83: =T83*0.15 -> 0 | V83: =SUMIFS('FIXED AMOUNT'!G:G,'FIXED AMOUNT'!B:B,B83) -> 7000 | W83: =SUM(D83:V83) -> 7000 | X83: =SUMIFS('FIXED AMOUNT'!E:E,'FIXED AMOUNT'!B:B,'data base '!B:B) -> 0 | Y83: =SUMIFS('FIXED AMOUNT'!F:F,'FIXED AMOUNT'!B:B,'data base '!B:B) -> 0 | Z83: =SUMIFS('FIXED AMOUNT'!V:V,'FIXED AMOUNT'!B:B,B:B) -> 0 | AA83: =W83+X83-Y83+Z83 -> 7000 | AB83: =W83*0.1 -> 700 | AC83: 45945 | AD83: =AA83+AB83 -> 7700
A84: 83 | B84: HCFM-0646 | C84: BAHRIA INTERNATIONAL HOSPITAL | D84: =SUMIFS(FACILITIES!E:E,FACILITIES!$B:$B,B84) -> 0 | E84: =SUMIFS(FACILITIES!F:F,FACILITIES!$B:$B,$B84) -> 0 | F84: =SUMIFS(FACILITIES!G:G,FACILITIES!$B:$B,B84) -> 0 | G84: =SUMIFS(FACILITIES!H:H,FACILITIES!$B:$B,B84) -> 0 | H84: =SUMIFS(FACILITIES!I:I,FACILITIES!$B:$B,B84) -> 0 | I84: =SUMIFS(FACILITIES!J:J,FACILITIES!$B:$B,B84) -> 0 | J84: =SUMIFS(FACILITIES!K:K,FACILITIES!$B:$B,B84) -> 0 | K84: =SUMIFS(FACILITIES!L:L,FACILITIES!$B:$B,B84) -> 0 | L84: =SUMIFS(FACILITIES!M:M,FACILITIES!$B:$B,B84) -> 0 | M84: =SUMIFS(FACILITIES!N:N,FACILITIES!$B:$B,B84) -> 0 | N84: =SUMIFS(FACILITIES!O:O,FACILITIES!$B:$B,B84) -> 0 | O84: =SUMIFS(FACILITIES!P:P,FACILITIES!$B:$B,B84) -> 0 | P84: =SUMIFS(FACILITIES!Q:Q,FACILITIES!$B:$B,B84) -> 0 | Q84: =SUMIFS(FACILITIES!R:R,FACILITIES!$B:$B,B84) -> 0 | R84: =SUMIFS(FACILITIES!T:T,FACILITIES!B:B,B84) -> 0 | S84: =SUMIFS(FACILITIES!S:S,FACILITIES!B:B,B84) -> 0 | T84: =SUMIFS('F & B'!G:G,'F & B'!B:B,B84) -> 94400 | V84: =SUMIFS('FIXED AMOUNT'!G:G,'FIXED AMOUNT'!B:B,B84) -> 0 | W84: =SUM(D84:V84) -> 94400 | X84: =SUMIFS('FIXED AMOUNT'!E:E,'FIXED AMOUNT'!B:B,'data base '!B:B) -> 0 | Y84: =SUMIFS('FIXED AMOUNT'!F:F,'FIXED AMOUNT'!B:B,'data base '!B:B) -> 0 | Z84: =SUMIFS('FIXED AMOUNT'!V:V,'FIXED AMOUNT'!B:B,B:B) -> 0 | AA84: =W84+X84-Y84+Z84 -> 94400 | AB84: =W84*0.1 -> 9440 | AC84: 45945 | AD84: =AA84+AB84 -> 103840
A85: 84 | B85: HCFM-0647 | C85: IMRAN AHMED | D85: =SUMIFS(FACILITIES!E:E,FACILITIES!$B:$B,B85) -> 0 | E85: =SUMIFS(FACILITIES!F:F,FACILITIES!$B:$B,$B85) -> 0 | F85: =SUMIFS(FACILITIES!G:G,FACILITIES!$B:$B,B85) -> 0 | G85: =SUMIFS(FACILITIES!H:H,FACILITIES!$B:$B,B85) -> 0 | H85: =SUMIFS(FACILITIES!I:I,FACILITIES!$B:$B,B85) -> 0 | I85: =SUMIFS(FACILITIES!J:J,FACILITIES!$B:$B,B85) -> 0 | J85: =SUMIFS(FACILITIES!K:K,FACILITIES!$B:$B,B85) -> 0 | K85: =SUMIFS(FACILITIES!L:L,FACILITIES!$B:$B,B85) -> 0 | L85: =SUMIFS(FACILITIES!M:M,FACILITIES!$B:$B,B85) -> 0 | M85: =SUMIFS(FACILITIES!N:N,FACILITIES!$B:$B,B85) -> 0 | N85: =SUMIFS(FACILITIES!O:O,FACILITIES!$B:$B,B85) -> 0 | O85: =SUMIFS(FACILITIES!P:P,FACILITIES!$B:$B,B85) -> 0 | P85: =SUMIFS(FACILITIES!Q:Q,FACILITIES!$B:$B,B85) -> 0 | Q85: =SUMIFS(FACILITIES!R:R,FACILITIES!$B:$B,B85) -> 0 | R85: =SUMIFS(FACILITIES!T:T,FACILITIES!B:B,B85) -> 0 | S85: =SUMIFS(FACILITIES!S:S,FACILITIES!B:B,B85) -> 0 | T85: =SUMIFS('F & B'!G:G,'F & B'!B:B,B85) -> 0 | U85: =T85*0.15 -> 0 | V85: =SUMIFS('FIXED AMOUNT'!G:G,'FIXED AMOUNT'!B:B,B85) -> 7000 | W85: =SUM(D85:V85) -> 7000 | X85: =SUMIFS('FIXED AMOUNT'!E:E,'FIXED AMOUNT'!B:B,'data base '!B:B) -> 0 | Y85: =SUMIFS('FIXED AMOUNT'!F:F,'FIXED AMOUNT'!B:B,'data base '!B:B) -> 0 | Z85: =SUMIFS('FIXED AMOUNT'!V:V,'FIXED AMOUNT'!B:B,B:B) -> 15225 | AA85: =W85+X85-Y85+Z85 -> 22225 | AB85: =W85*0.1 -> 700 | AC85: 45945 | AD85: =AA85+AB85 -> 22925
A86: 85 | B86: HCFM-0648 | C86: AYSM MIRZA | D86: =SUMIFS(FACILITIES!E:E,FACILITIES!$B:$B,B86) -> 0 | E86: =SUMIFS(FACILITIES!F:F,FACILITIES!$B:$B,$B86) -> 750 | F86: =SUMIFS(FACILITIES!G:G,FACILITIES!$B:$B,B86) -> 0 | G86: =SUMIFS(FACILITIES!H:H,FACILITIES!$B:$B,B86) -> 0 | H86: =SUMIFS(FACILITIES!I:I,FACILITIES!$B:$B,B86) -> 0 | I86: =SUMIFS(FACILITIES!J:J,FACILITIES!$B:$B,B86) -> 1600 | J86: =SUMIFS(FACILITIES!K:K,FACILITIES!$B:$B,B86) -> 1500 | K86: =SUMIFS(FACILITIES!L:L,FACILITIES!$B:$B,B86) -> 0 | L86: =SUMIFS(FACILITIES!M:M,FACILITIES!$B:$B,B86) -> 0 | M86: =SUMIFS(FACILITIES!N:N,FACILITIES!$B:$B,B86) -> 0 | N86: =SUMIFS(FACILITIES!O:O,FACILITIES!$B:$B,B86) -> 0 | O86: =SUMIFS(FACILITIES!P:P,FACILITIES!$B:$B,B86) -> 0 | P86: =SUMIFS(FACILITIES!Q:Q,FACILITIES!$B:$B,B86) -> 0 | Q86: =SUMIFS(FACILITIES!R:R,FACILITIES!$B:$B,B86) -> 0 | R86: =SUMIFS(FACILITIES!T:T,FACILITIES!B:B,B86) -> 0 | S86: =SUMIFS(FACILITIES!S:S,FACILITIES!B:B,B86) -> 0 | T86: =SUMIFS('F & B'!G:G,'F & B'!B:B,B86) -> 21714 | U86: =T86*0.15 -> 3257.1 | V86: =SUMIFS('FIXED AMOUNT'!G:G,'FIXED AMOUNT'!B:B,B86) -> 7000 | W86: =SUM(D86:V86) -> 35821.1 | X86: =SUMIFS('FIXED AMOUNT'!E:E,'FIXED AMOUNT'!B:B,'data base '!B:B) -> 0 | Y86: =SUMIFS('FIXED AMOUNT'!F:F,'FIXED AMOUNT'!B:B,'data base '!B:B) -> 0 | Z86: =SUMIFS('FIXED AMOUNT'!V:V,'FIXED AMOUNT'!B:B,B:B) -> 7926 | AA86: =W86+X86-Y86+Z86 -> 43747.1 | AB86: =W86*0.1 -> 3582.11 | AC86: 45945 | AD86: =AA86+AB86 -> 47329.21
A87: 86 | B87: HCFM-0649 | C87: IFTIKHAR SHAH | D87: =SUMIFS(FACILITIES!E:E,FACILITIES!$B:$B,B87) -> 0 | E87: =SUMIFS(FACILITIES!F:F,FACILITIES!$B:$B,$B87) -> 0 | F87: =SUMIFS(FACILITIES!G:G,FACILITIES!$B:$B,B87) -> 0 | G87: =SUMIFS(FACILITIES!H:H,FACILITIES!$B:$B,B87) -> 0 | H87: =SUMIFS(FACILITIES!I:I,FACILITIES!$B:$B,B87) -> 0 | I87: =SUMIFS(FACILITIES!J:J,FACILITIES!$B:$B,B87) -> 0 | J87: =SUMIFS(FACILITIES!K:K,FACILITIES!$B:$B,B87) -> 0 | K87: =SUMIFS(FACILITIES!L:L,FACILITIES!$B:$B,B87) -> 0 | L87: =SUMIFS(FACILITIES!M:M,FACILITIES!$B:$B,B87) -> 0 | M87: =SUMIFS(FACILITIES!N:N,FACILITIES!$B:$B,B87) -> 0 | N87: =SUMIFS(FACILITIES!O:O,FACILITIES!$B:$B,B87) -> 0 | O87: =SUMIFS(FACILITIES!P:P,FACILITIES!$B:$B,B87) -> 0 | P87: =SUMIFS(FACILITIES!Q:Q,FACILITIES!$B:$B,B87) -> 0 | Q87: =SUMIFS(FACILITIES!R:R,FACILITIES!$B:$B,B87) -> 0 | R87: =SUMIFS(FACILITIES!T:T,FACILITIES!B:B,B87) -> 0 | S87: =SUMIFS(FACILITIES!S:S,FACILITIES!B:B,B87) -> 0 | T87: =SUMIFS('F & B'!G:G,'F & B'!B:B,B87) -> 76200 | U87: =T87*0.15 -> 11430 | V87: =SUMIFS('FIXED AMOUNT'!G:G,'FIXED AMOUNT'!B:B,B87) -> 7000 | W87: =SUM(D87:V87) -> 94630 | X87: =SUMIFS('FIXED AMOUNT'!E:E,'FIXED AMOUNT'!B:B,'data base '!B:B) -> 0 | Y87: =SUMIFS('FIXED AMOUNT'!F:F,'FIXED AMOUNT'!B:B,'data base '!B:B) -> 0 | Z87: =SUMIFS('FIXED AMOUNT'!V:V,'FIXED AMOUNT'!B:B,B:B) -> 0 | AA87: =W87+X87-Y87+Z87 -> 94630 | AB87: =W87*0.1 -> 9463 | AC87: 45945 | AD87: =AA87+AB87 -> 104093
A88: 87 | B88: HCFM-0650 | C88: KHURRAM FIRDOUS | D88: =SUMIFS(FACILITIES!E:E,FACILITIES!$B:$B,B88) -> 0 | E88: =SUMIFS(FACILITIES!F:F,FACILITIES!$B:$B,$B88) -> 0 | F88: =SUMIFS(FACILITIES!G:G,FACILITIES!$B:$B,B88) -> 0 | G88: =SUMIFS(FACILITIES!H:H,FACILITIES!$B:$B,B88) -> 0 | H88: =SUMIFS(FACILITIES!I:I,FACILITIES!$B:$B,B88) -> 0 | I88: =SUMIFS(FACILITIES!J:J,FACILITIES!$B:$B,B88) -> 2800 | J88: =SUMIFS(FACILITIES!K:K,FACILITIES!$B:$B,B88) -> 0 | K88: =SUMIFS(FACILITIES!L:L,FACILITIES!$B:$B,B88) -> 0 | L88: =SUMIFS(FACILITIES!M:M,FACILITIES!$B:$B,B88) -> 0 | M88: =SUMIFS(FACILITIES!N:N,FACILITIES!$B:$B,B88) -> 0 | N88: =SUMIFS(FACILITIES!O:O,FACILITIES!$B:$B,B88) -> 5500 | O88: =SUMIFS(FACILITIES!P:P,FACILITIES!$B:$B,B88) -> 0 | P88: =SUMIFS(FACILITIES!Q:Q,FACILITIES!$B:$B,B88) -> 0 | Q88: =SUMIFS(FACILITIES!R:R,FACILITIES!$B:$B,B88) -> 0 | R88: =SUMIFS(FACILITIES!T:T,FACILITIES!B:B,B88) -> 0 | S88: =SUMIFS(FACILITIES!S:S,FACILITIES!B:B,B88) -> 0 | T88: =SUMIFS('F & B'!G:G,'F & B'!B:B,B88) -> 16250 | U88: =T88*0.15 -> 2437.5 | V88: =SUMIFS('FIXED AMOUNT'!G:G,'FIXED AMOUNT'!B:B,B88) -> 7000 | W88: =SUM(D88:V88) -> 33987.5 | X88: =SUMIFS('FIXED AMOUNT'!E:E,'FIXED AMOUNT'!B:B,'data base '!B:B) -> 0 | Y88: =SUMIFS('FIXED AMOUNT'!F:F,'FIXED AMOUNT'!B:B,'data base '!B:B) -> 0 | Z88: =SUMIFS('FIXED AMOUNT'!V:V,'FIXED AMOUNT'!B:B,B:B) -> 2085 | AA88: =W88+X88-Y88+Z88 -> 36072.5 | AB88: =W88*0.1 -> 3398.75 | AC88: 45945 | AD88: =AA88+AB88 -> 39471.25
A89: 88 | B89: HCFM-0651 | C89: ALI LEGHARI | D89: =SUMIFS(FACILITIES!E:E,FACILITIES!$B:$B,B89) -> 0 | E89: =SUMIFS(FACILITIES!F:F,FACILITIES!$B:$B,$B89) -> 0 | F89: =SUMIFS(FACILITIES!G:G,FACILITIES!$B:$B,B89) -> 0 | G89: =SUMIFS(FACILITIES!H:H,FACILITIES!$B:$B,B89) -> 0 | H89: =SUMIFS(FACILITIES!I:I,FACILITIES!$B:$B,B89) -> 0 | I89: =SUMIFS(FACILITIES!J:J,FACILITIES!$B:$B,B89) -> 0 | J89: =SUMIFS(FACILITIES!K:K,FACILITIES!$B:$B,B89) -> 0 | K89: =SUMIFS(FACILITIES!L:L,FACILITIES!$B:$B,B89) -> 0 | L89: =SUMIFS(FACILITIES!M:M,FACILITIES!$B:$B,B89) -> 0 | M89: =SUMIFS(FACILITIES!N:N,FACILITIES!$B:$B,B89) -> 0 | N89: =SUMIFS(FACILITIES!O:O,FACILITIES!$B:$B,B89) -> 0 | O89: =SUMIFS(FACILITIES!P:P,FACILITIES!$B:$B,B89) -> 0 | P89: =SUMIFS(FACILITIES!Q:Q,FACILITIES!$B:$B,B89) -> 0 | Q89: =SUMIFS(FACILITIES!R:R,FACILITIES!$B:$B,B89) -> 0 | R89: =SUMIFS(FACILITIES!T:T,FACILITIES!B:B,B89) -> 365000 | S89: =SUMIFS(FACILITIES!S:S,FACILITIES!B:B,B89) -> 100000 | T89: =SUMIFS('F & B'!G:G,'F & B'!B:B,B89) -> 80050 | U89: =T89*0.15 -> 12007.5 | V89: =SUMIFS('FIXED AMOUNT'!G:G,'FIXED AMOUNT'!B:B,B89) -> 7000 | W89: =SUM(D89:V89) -> 564057.5 | X89: =SUMIFS('FIXED AMOUNT'!E:E,'FIXED AMOUNT'!B:B,'data base '!B:B) -> 0 | Y89: =SUMIFS('FIXED AMOUNT'!F:F,'FIXED AMOUNT'!B:B,'data base '!B:B) -> 0 | Z89: =SUMIFS('FIXED AMOUNT'!V:V,'FIXED AMOUNT'!B:B,B:B) -> 0 | AA89: =W89+X89-Y89+Z89 -> 564057.5 | AB89: =W89*0.1 -> 56405.75 | AC89: 45945 | AD89: =AA89+AB89 -> 620463.25
A90: 89 | B90: HCFM-0652 | C90: Dr. AZAD ALI | D90: =SUMIFS(FACILITIES!E:E,FACILITIES!$B:$B,B90) -> 0 | E90: =SUMIFS(FACILITIES!F:F,FACILITIES!$B:$B,$B90) -> 0 | F90: =SUMIFS(FACILITIES!G:G,FACILITIES!$B:$B,B90) -> 0 | G90: =SUMIFS(FACILITIES!H:H,FACILITIES!$B:$B,B90) -> 0 | H90: =SUMIFS(FACILITIES!I:I,FACILITIES!$B:$B,B90) -> 0 | I90: =SUMIFS(FACILITIES!J:J,FACILITIES!$B:$B,B90) -> 0 | J90: =SUMIFS(FACILITIES!K:K,FACILITIES!$B:$B,B90) -> 0 | K90: =SUMIFS(FACILITIES!L:L,FACILITIES!$B:$B,B90) -> 0 | L90: =SUMIFS(FACILITIES!M:M,FACILITIES!$B:$B,B90) -> 0 | M90: =SUMIFS(FACILITIES!N:N,FACILITIES!$B:$B,B90) -> 0 | N90: =SUMIFS(FACILITIES!O:O,FACILITIES!$B:$B,B90) -> 0 | O90: =SUMIFS(FACILITIES!P:P,FACILITIES!$B:$B,B90) -> 0 | P90: =SUMIFS(FACILITIES!Q:Q,FACILITIES!$B:$B,B90) -> 0 | Q90: =SUMIFS(FACILITIES!R:R,FACILITIES!$B:$B,B90) -> 0 | R90: =SUMIFS(FACILITIES!T:T,FACILITIES!B:B,B90) -> 0 | S90: =SUMIFS(FACILITIES!S:S,FACILITIES!B:B,B90) -> 0 | T90: =SUMIFS('F & B'!G:G,'F & B'!B:B,B90) -> 0 | U90: =T90*0.15 -> 0 | V90: =SUMIFS('FIXED AMOUNT'!G:G,'FIXED AMOUNT'!B:B,B90) -> 7000 | W90: =SUM(D90:V90) -> 7000 | X90: =SUMIFS('FIXED AMOUNT'!E:E,'FIXED AMOUNT'!B:B,'data base '!B:B) -> 0 | Y90: =SUMIFS('FIXED AMOUNT'!F:F,'FIXED AMOUNT'!B:B,'data base '!B:B) -> 0 | Z90: =SUMIFS('FIXED AMOUNT'!V:V,'FIXED AMOUNT'!B:B,B:B) -> 31471 | AA90: =W90+X90-Y90+Z90 -> 38471 | AB90: =W90*0.1 -> 700 | AC90: 45945 | AD90: =AA90+AB90 -> 39171
A91: 90 | B91: HCFM-0653 | C91: AMEER MUHAMMAD | D91: =SUMIFS(FACILITIES!E:E,FACILITIES!$B:$B,B91) -> 0 | E91: =SUMIFS(FACILITIES!F:F,FACILITIES!$B:$B,$B91) -> 0 | F91: =SUMIFS(FACILITIES!G:G,FACILITIES!$B:$B,B91) -> 0 | G91: =SUMIFS(FACILITIES!H:H,FACILITIES!$B:$B,B91) -> 0 | H91: =SUMIFS(FACILITIES!I:I,FACILITIES!$B:$B,B91) -> 0 | I91: =SUMIFS(FACILITIES!J:J,FACILITIES!$B:$B,B91) -> 0 | J91: =SUMIFS(FACILITIES!K:K,FACILITIES!$B:$B,B91) -> 0 | K91: =SUMIFS(FACILITIES!L:L,FACILITIES!$B:$B,B91) -> 0 | L91: =SUMIFS(FACILITIES!M:M,FACILITIES!$B:$B,B91) -> 0 | M91: =SUMIFS(FACILITIES!N:N,FACILITIES!$B:$B,B91) -> 0 | N91: =SUMIFS(FACILITIES!O:O,FACILITIES!$B:$B,B91) -> 0 | O91: =SUMIFS(FACILITIES!P:P,FACILITIES!$B:$B,B91) -> 0 | P91: =SUMIFS(FACILITIES!Q:Q,FACILITIES!$B:$B,B91) -> 0 | Q91: =SUMIFS(FACILITIES!R:R,FACILITIES!$B:$B,B91) -> 0 | R91: =SUMIFS(FACILITIES!T:T,FACILITIES!B:B,B91) -> 0 | S91: =SUMIFS(FACILITIES!S:S,FACILITIES!B:B,B91) -> 0 | T91: =SUMIFS('F & B'!G:G,'F & B'!B:B,B91) -> 0 | U91: =T91*0.15 -> 0 | V91: =SUMIFS('FIXED AMOUNT'!G:G,'FIXED AMOUNT'!B:B,B91) -> 7000 | W91: =SUM(D91:V91) -> 7000 | X91: =SUMIFS('FIXED AMOUNT'!E:E,'FIXED AMOUNT'!B:B,'data base '!B:B) -> 0 | Y91: =SUMIFS('FIXED AMOUNT'!F:F,'FIXED AMOUNT'!B:B,'data base '!B:B) -> 0 | Z91: =SUMIFS('FIXED AMOUNT'!V:V,'FIXED AMOUNT'!B:B,B:B) -> 0 | AA91: =W91+X91-Y91+Z91 -> 7000 | AB91: =W91*0.1 -> 700 | AC91: 45945 | AD91: =AA91+AB91 -> 7700
A92: 91 | B92: HCFM-0654 | C92: SYED JIBRAN MUSHTAQ | D92: =SUMIFS(FACILITIES!E:E,FACILITIES!$B:$B,B92) -> 1200 | E92: =SUMIFS(FACILITIES!F:F,FACILITIES!$B:$B,$B92) -> 0 | F92: =SUMIFS(FACILITIES!G:G,FACILITIES!$B:$B,B92) -> 0 | G92: =SUMIFS(FACILITIES!H:H,FACILITIES!$B:$B,B92) -> 0 | H92: =SUMIFS(FACILITIES!I:I,FACILITIES!$B:$B,B92) -> 0 | I92: =SUMIFS(FACILITIES!J:J,FACILITIES!$B:$B,B92) -> 5400 | J92: =SUMIFS(FACILITIES!K:K,FACILITIES!$B:$B,B92) -> 0 | K92: =SUMIFS(FACILITIES!L:L,FACILITIES!$B:$B,B92) -> 0 | L92: =SUMIFS(FACILITIES!M:M,FACILITIES!$B:$B,B92) -> 0 | M92: =SUMIFS(FACILITIES!N:N,FACILITIES!$B:$B,B92) -> 1500 | N92: =SUMIFS(FACILITIES!O:O,FACILITIES!$B:$B,B92) -> 0 | O92: =SUMIFS(FACILITIES!P:P,FACILITIES!$B:$B,B92) -> 11500 | P92: =SUMIFS(FACILITIES!Q:Q,FACILITIES!$B:$B,B92) -> 0 | Q92: =SUMIFS(FACILITIES!R:R,FACILITIES!$B:$B,B92) -> 0 | R92: =SUMIFS(FACILITIES!T:T,FACILITIES!B:B,B92) -> 0 | S92: =SUMIFS(FACILITIES!S:S,FACILITIES!B:B,B92) -> 0 | T92: =SUMIFS('F & B'!G:G,'F & B'!B:B,B92) -> 29370 | U92: =T92*0.15 -> 4405.5 | V92: =SUMIFS('FIXED AMOUNT'!G:G,'FIXED AMOUNT'!B:B,B92) -> 7000 | W92: =SUM(D92:V92) -> 60375.5 | X92: =SUMIFS('FIXED AMOUNT'!E:E,'FIXED AMOUNT'!B:B,'data base '!B:B) -> 0 | Y92: =SUMIFS('FIXED AMOUNT'!F:F,'FIXED AMOUNT'!B:B,'data base '!B:B) -> 0 | Z92: =SUMIFS('FIXED AMOUNT'!V:V,'FIXED AMOUNT'!B:B,B:B) -> 0 | AA92: =W92+X92-Y92+Z92 -> 60375.5 | AB92: =W92*0.1 -> 6037.55 | AC92: 45945 | AD92: =AA92+AB92 -> 66413.05
A93: 92 | B93: HCFM-0655 | C93: SADDAM HUSSAIN | D93: =SUMIFS(FACILITIES!E:E,FACILITIES!$B:$B,B93) -> 0 | E93: =SUMIFS(FACILITIES!F:F,FACILITIES!$B:$B,$B93) -> 0 | F93: =SUMIFS(FACILITIES!G:G,FACILITIES!$B:$B,B93) -> 0 | G93: =SUMIFS(FACILITIES!H:H,FACILITIES!$B:$B,B93) -> 0 | H93: =SUMIFS(FACILITIES!I:I,FACILITIES!$B:$B,B93) -> 0 | I93: =SUMIFS(FACILITIES!J:J,FACILITIES!$B:$B,B93) -> 300 | J93: =SUMIFS(FACILITIES!K:K,FACILITIES!$B:$B,B93) -> 0 | K93: =SUMIFS(FACILITIES!L:L,FACILITIES!$B:$B,B93) -> 0 | L93: =SUMIFS(FACILITIES!M:M,FACILITIES!$B:$B,B93) -> 0 | M93: =SUMIFS(FACILITIES!N:N,FACILITIES!$B:$B,B93) -> 0 | N93: =SUMIFS(FACILITIES!O:O,FACILITIES!$B:$B,B93) -> 0 | O93: =SUMIFS(FACILITIES!P:P,FACILITIES!$B:$B,B93) -> 0 | P93: =SUMIFS(FACILITIES!Q:Q,FACILITIES!$B:$B,B93) -> 0 | Q93: =SUMIFS(FACILITIES!R:R,FACILITIES!$B:$B,B93) -> 0 | R93: =SUMIFS(FACILITIES!T:T,FACILITIES!B:B,B93) -> 0 | S93: =SUMIFS(FACILITIES!S:S,FACILITIES!B:B,B93) -> 0 | T93: =SUMIFS('F & B'!G:G,'F & B'!B:B,B93) -> 4100 | U93: =T93*0.15 -> 615 | V93: =SUMIFS('FIXED AMOUNT'!G:G,'FIXED AMOUNT'!B:B,B93) -> 7000 | W93: =SUM(D93:V93) -> 12015 | X93: =SUMIFS('FIXED AMOUNT'!E:E,'FIXED AMOUNT'!B:B,'data base '!B:B) -> 0 | Y93: =SUMIFS('FIXED AMOUNT'!F:F,'FIXED AMOUNT'!B:B,'data base '!B:B) -> 0 | Z93: =SUMIFS('FIXED AMOUNT'!V:V,'FIXED AMOUNT'!B:B,B:B) -> 0 | AA93: =W93+X93-Y93+Z93 -> 12015 | AB93: =W93*0.1 -> 1201.5 | AC93: 45945 | AD93: =AA93+AB93 -> 13216.5
A94: 93 | B94: HCFM-0656 | C94: ZAIB UR REHMAN | D94: =SUMIFS(FACILITIES!E:E,FACILITIES!$B:$B,B94) -> 1500 | E94: =SUMIFS(FACILITIES!F:F,FACILITIES!$B:$B,$B94) -> 0 | F94: =SUMIFS(FACILITIES!G:G,FACILITIES!$B:$B,B94) -> 0 | G94: =SUMIFS(FACILITIES!H:H,FACILITIES!$B:$B,B94) -> 0 | H94: =SUMIFS(FACILITIES!I:I,FACILITIES!$B:$B,B94) -> 0 | I94: =SUMIFS(FACILITIES!J:J,FACILITIES!$B:$B,B94) -> 3100 | J94: =SUMIFS(FACILITIES!K:K,FACILITIES!$B:$B,B94) -> 0 | K94: =SUMIFS(FACILITIES!L:L,FACILITIES!$B:$B,B94) -> 0 | L94: =SUMIFS(FACILITIES!M:M,FACILITIES!$B:$B,B94) -> 0 | M94: =SUMIFS(FACILITIES!N:N,FACILITIES!$B:$B,B94) -> 0 | N94: =SUMIFS(FACILITIES!O:O,FACILITIES!$B:$B,B94) -> 0 | O94: =SUMIFS(FACILITIES!P:P,FACILITIES!$B:$B,B94) -> 0 | P94: =SUMIFS(FACILITIES!Q:Q,FACILITIES!$B:$B,B94) -> 0 | Q94: =SUMIFS(FACILITIES!R:R,FACILITIES!$B:$B,B94) -> 0 | R94: =SUMIFS(FACILITIES!T:T,FACILITIES!B:B,B94) -> 0 | S94: =SUMIFS(FACILITIES!S:S,FACILITIES!B:B,B94) -> 0 | T94: =SUMIFS('F & B'!G:G,'F & B'!B:B,B94) -> 5370 | U94: =T94*0.15 -> 805.5 | V94: =SUMIFS('FIXED AMOUNT'!G:G,'FIXED AMOUNT'!B:B,B94) -> 7000 | W94: =SUM(D94:V94) -> 17775.5 | X94: =SUMIFS('FIXED AMOUNT'!E:E,'FIXED AMOUNT'!B:B,'data base '!B:B) -> 0 | Y94: =SUMIFS('FIXED AMOUNT'!F:F,'FIXED AMOUNT'!B:B,'data base '!B:B) -> 0 | Z94: =SUMIFS('FIXED AMOUNT'!V:V,'FIXED AMOUNT'!B:B,B:B) -> 0 | AA94: =W94+X94-Y94+Z94 -> 17775.5 | AB94: =W94*0.1 -> 1777.55 | AC94: 45945 | AD94: =AA94+AB94 -> 19553.05
A95: 94 | B95: HCFM-0657 | C95: NASIR ABBAS | D95: =SUMIFS(FACILITIES!E:E,FACILITIES!$B:$B,B95) -> 0 | E95: =SUMIFS(FACILITIES!F:F,FACILITIES!$B:$B,$B95) -> 1200 | F95: =SUMIFS(FACILITIES!G:G,FACILITIES!$B:$B,B95) -> 0 | G95: =SUMIFS(FACILITIES!H:H,FACILITIES!$B:$B,B95) -> 0 | H95: =SUMIFS(FACILITIES!I:I,FACILITIES!$B:$B,B95) -> 0 | I95: =SUMIFS(FACILITIES!J:J,FACILITIES!$B:$B,B95) -> 0 | J95: =SUMIFS(FACILITIES!K:K,FACILITIES!$B:$B,B95) -> 0 | K95: =SUMIFS(FACILITIES!L:L,FACILITIES!$B:$B,B95) -> 0 | L95: =SUMIFS(FACILITIES!M:M,FACILITIES!$B:$B,B95) -> 0 | M95: =SUMIFS(FACILITIES!N:N,FACILITIES!$B:$B,B95) -> 0 | N95: =SUMIFS(FACILITIES!O:O,FACILITIES!$B:$B,B95) -> 0 | O95: =SUMIFS(FACILITIES!P:P,FACILITIES!$B:$B,B95) -> 0 | P95: =SUMIFS(FACILITIES!Q:Q,FACILITIES!$B:$B,B95) -> 0 | Q95: =SUMIFS(FACILITIES!R:R,FACILITIES!$B:$B,B95) -> 0 | R95: =SUMIFS(FACILITIES!T:T,FACILITIES!B:B,B95) -> 0 | S95: =SUMIFS(FACILITIES!S:S,FACILITIES!B:B,B95) -> 0 | T95: =SUMIFS('F & B'!G:G,'F & B'!B:B,B95) -> 59650 | U95: =T95*0.15 -> 8947.5 | V95: =SUMIFS('FIXED AMOUNT'!G:G,'FIXED AMOUNT'!B:B,B95) -> 7000 | W95: =SUM(D95:V95) -> 76797.5 | X95: =SUMIFS('FIXED AMOUNT'!E:E,'FIXED AMOUNT'!B:B,'data base '!B:B) -> 0 | Y95: =SUMIFS('FIXED AMOUNT'!F:F,'FIXED AMOUNT'!B:B,'data base '!B:B) -> 0 | Z95: =SUMIFS('FIXED AMOUNT'!V:V,'FIXED AMOUNT'!B:B,B:B) -> 0 | AA95: =W95+X95-Y95+Z95 -> 76797.5 | AB95: =W95*0.1 -> 7679.75 | AC95: 45945 | AD95: =AA95+AB95 -> 84477.25
A96: 95 | B96: HCFM-0658 | C96: MUSHTAQ AHMED MEMON | D96: =SUMIFS(FACILITIES!E:E,FACILITIES!$B:$B,B96) -> 0 | E96: =SUMIFS(FACILITIES!F:F,FACILITIES!$B:$B,$B96) -> 0 | F96: =SUMIFS(FACILITIES!G:G,FACILITIES!$B:$B,B96) -> 0 | G96: =SUMIFS(FACILITIES!H:H,FACILITIES!$B:$B,B96) -> 0 | H96: =SUMIFS(FACILITIES!I:I,FACILITIES!$B:$B,B96) -> 0 | I96: =SUMIFS(FACILITIES!J:J,FACILITIES!$B:$B,B96) -> 0 | J96: =SUMIFS(FACILITIES!K:K,FACILITIES!$B:$B,B96) -> 0 | K96: =SUMIFS(FACILITIES!L:L,FACILITIES!$B:$B,B96) -> 0 | L96: =SUMIFS(FACILITIES!M:M,FACILITIES!$B:$B,B96) -> 0 | M96: =SUMIFS(FACILITIES!N:N,FACILITIES!$B:$B,B96) -> 0 | N96: =SUMIFS(FACILITIES!O:O,FACILITIES!$B:$B,B96) -> 0 | O96: =SUMIFS(FACILITIES!P:P,FACILITIES!$B:$B,B96) -> 0 | P96: =SUMIFS(FACILITIES!Q:Q,FACILITIES!$B:$B,B96) -> 0 | Q96: =SUMIFS(FACILITIES!R:R,FACILITIES!$B:$B,B96) -> 0 | R96: =SUMIFS(FACILITIES!T:T,FACILITIES!B:B,B96) -> 0 | S96: =SUMIFS(FACILITIES!S:S,FACILITIES!B:B,B96) -> 0 | T96: =SUMIFS('F & B'!G:G,'F & B'!B:B,B96) -> 0 | U96: =T96*0.15 -> 0 | V96: =SUMIFS('FIXED AMOUNT'!G:G,'FIXED AMOUNT'!B:B,B96) -> 7000 | W96: =SUM(D96:V96) -> 7000 | X96: =SUMIFS('FIXED AMOUNT'!E:E,'FIXED AMOUNT'!B:B,'data base '!B:B) -> 0 | Y96: =SUMIFS('FIXED AMOUNT'!F:F,'FIXED AMOUNT'!B:B,'data base '!B:B) -> 0 | Z96: =SUMIFS('FIXED AMOUNT'!V:V,'FIXED AMOUNT'!B:B,B:B) -> 60000 | AA96: =W96+X96-Y96+Z96 -> 67000 | AB96: =W96*0.1 -> 700 | AC96: 45945 | AD96: =AA96+AB96 -> 67700
... A106: 105 | B106: HCFM-0670 | C106: MR. TEHSEEN FAIZ | D106: =SUMIFS(FACILITIES!E:E,FACILITIES!$B:$B,B106) -> 2400 | E106: =SUMIFS(FACILITIES!F:F,FACILITIES!$B:$B,$B106) -> 150 | F106: =SUMIFS(FACILITIES!G:G,FACILITIES!$B:$B,B106) -> 0 | G106: =SUMIFS(FACILITIES!H:H,FACILITIES!$B:$B,B106) -> 0 | H106: =SUMIFS(FACILITIES!I:I,FACILITIES!$B:$B,B106) -> 0 | I106: =SUMIFS(FACILITIES!J:J,FACILITIES!$B:$B,B106) -> 1500 | J106: =SUMIFS(FACILITIES!K:K,FACILITIES!$B:$B,B106) -> 900 | K106: =SUMIFS(FACILITIES!L:L,FACILITIES!$B:$B,B106) -> 0 | L106: =SUMIFS(FACILITIES!M:M,FACILITIES!$B:$B,B106) -> 0 | M106: =SUMIFS(FACILITIES!N:N,FACILITIES!$B:$B,B106) -> 0 | N106: =SUMIFS(FACILITIES!O:O,FACILITIES!$B:$B,B106) -> 0 | O106: =SUMIFS(FACILITIES!P:P,FACILITIES!$B:$B,B106) -> 0 | P106: =SUMIFS(FACILITIES!Q:Q,FACILITIES!$B:$B,B106) -> 0 | Q106: =SUMIFS(FACILITIES!R:R,FACILITIES!$B:$B,B106) -> 0 | R106: =SUMIFS(FACILITIES!T:T,FACILITIES!B:B,B106) -> 0 | S106: =SUMIFS(FACILITIES!S:S,FACILITIES!B:B,B106) -> 0 | T106: =SUMIFS('F & B'!G:G,'F & B'!B:B,B106) -> 17379 | U106: =T106*0.15 -> 2606.85 | V106: =SUMIFS('FIXED AMOUNT'!G:G,'FIXED AMOUNT'!B:B,B106) -> 7000 | W106: =SUM(D106:V106) -> 31935.85 | X106: =SUMIFS('FIXED AMOUNT'!E:E,'FIXED AMOUNT'!B:B,'data base '!B:B) -> 0 | Y106: =SUMIFS('FIXED AMOUNT'!F:F,'FIXED AMOUNT'!B:B,'data base '!B:B) -> 0 | Z106: =SUMIFS('FIXED AMOUNT'!V:V,'FIXED AMOUNT'!B:B,B:B) -> 22606 | AA106: =W106+X106-Y106+Z106 -> 54541.85 | AB106: =W106*0.1 -> 3193.585 | AC106: 45945 | AD106: =AA106+AB106 -> 57735.435
A107: 106 | B107: HCFM-0671 | C107: MRS. HASSAN RAFI | D107: =SUMIFS(FACILITIES!E:E,FACILITIES!$B:$B,B107) -> 0 | E107: =SUMIFS(FACILITIES!F:F,FACILITIES!$B:$B,$B107) -> 0 | F107: =SUMIFS(FACILITIES!G:G,FACILITIES!$B:$B,B107) -> 0 | G107: =SUMIFS(FACILITIES!H:H,FACILITIES!$B:$B,B107) -> 0 | H107: =SUMIFS(FACILITIES!I:I,FACILITIES!$B:$B,B107) -> 0 | I107: =SUMIFS(FACILITIES!J:J,FACILITIES!$B:$B,B107) -> 0 | J107: =SUMIFS(FACILITIES!K:K,FACILITIES!$B:$B,B107) -> 0 | K107: =SUMIFS(FACILITIES!L:L,FACILITIES!$B:$B,B107) -> 0 | L107: =SUMIFS(FACILITIES!M:M,FACILITIES!$B:$B,B107) -> 0 | M107: =SUMIFS(FACILITIES!N:N,FACILITIES!$B:$B,B107) -> 0 | N107: =SUMIFS(FACILITIES!O:O,FACILITIES!$B:$B,B107) -> 0 | O107: =SUMIFS(FACILITIES!P:P,FACILITIES!$B:$B,B107) -> 0 | P107: =SUMIFS(FACILITIES!Q:Q,FACILITIES!$B:$B,B107) -> 0 | Q107: =SUMIFS(FACILITIES!R:R,FACILITIES!$B:$B,B107) -> 0 | R107: =SUMIFS(FACILITIES!T:T,FACILITIES!B:B,B107) -> 0 | S107: =SUMIFS(FACILITIES!S:S,FACILITIES!B:B,B107) -> 0 | T107: =SUMIFS('F & B'!G:G,'F & B'!B:B,B107) -> 0 | U107: 0 | V107: =SUMIFS('FIXED AMOUNT'!G:G,'FIXED AMOUNT'!B:B,B107) -> 0 | W107: =SUM(D107:V107) -> 0 | X107: =SUMIFS('FIXED AMOUNT'!E:E,'FIXED AMOUNT'!B:B,'data base '!B:B) -> 0 | Y107: =SUMIFS('FIXED AMOUNT'!F:F,'FIXED AMOUNT'!B:B,'data base '!B:B) -> 0 | Z107: =SUMIFS('FIXED AMOUNT'!V:V,'FIXED AMOUNT'!B:B,B:B) -> 0 | AA107: =W107+X107-Y107+Z107 -> 0 | AB107: =W107*0.1 -> 0 | AC107: 45945 | AD107: =AA107+AB107 -> 0
A108: 107 | B108: HCFM-0672 | C108: MRS RIFFAT ZULFIQAR | D108: =SUMIFS(FACILITIES!E:E,FACILITIES!$B:$B,B108) -> 4200 | E108: =SUMIFS(FACILITIES!F:F,FACILITIES!$B:$B,$B108) -> 450 | F108: =SUMIFS(FACILITIES!G:G,FACILITIES!$B:$B,B108) -> 0 | G108: =SUMIFS(FACILITIES!H:H,FACILITIES!$B:$B,B108) -> 0 | H108: =SUMIFS(FACILITIES!I:I,FACILITIES!$B:$B,B108) -> 0 | I108: =SUMIFS(FACILITIES!J:J,FACILITIES!$B:$B,B108) -> 0 | J108: =SUMIFS(FACILITIES!K:K,FACILITIES!$B:$B,B108) -> 0 | K108: =SUMIFS(FACILITIES!L:L,FACILITIES!$B:$B,B108) -> 0 | L108: =SUMIFS(FACILITIES!M:M,FACILITIES!$B:$B,B108) -> 0 | M108: =SUMIFS(FACILITIES!N:N,FACILITIES!$B:$B,B108) -> 0 | N108: =SUMIFS(FACILITIES!O:O,FACILITIES!$B:$B,B108) -> 0 | O108: =SUMIFS(FACILITIES!P:P,FACILITIES!$B:$B,B108) -> 0 | P108: =SUMIFS(FACILITIES!Q:Q,FACILITIES!$B:$B,B108) -> 0 | Q108: =SUMIFS(FACILITIES!R:R,FACILITIES!$B:$B,B108) -> 0 | R108: =SUMIFS(FACILITIES!T:T,FACILITIES!B:B,B108) -> 40000 | S108: =SUMIFS(FACILITIES!S:S,FACILITIES!B:B,B108) -> 0 | T108: =SUMIFS('F & B'!G:G,'F & B'!B:B,B108) -> 38280 | U108: =T108*0.15 -> 5742 | V108: =SUMIFS('FIXED AMOUNT'!G:G,'FIXED AMOUNT'!B:B,B108) -> 7000 | W108: =SUM(D108:V108) -> 95672 | X108: =SUMIFS('FIXED AMOUNT'!E:E,'FIXED AMOUNT'!B:B,'data base '!B:B) -> 0 | Y108: =SUMIFS('FIXED AMOUNT'!F:F,'FIXED AMOUNT'!B:B,'data base '!B:B) -> 0 | Z108: =SUMIFS('FIXED AMOUNT'!V:V,'FIXED AMOUNT'!B:B,B:B) -> 0 | AA108: =W108+X108-Y108+Z108 -> 95672 | AB108: =W108*0.1 -> 9567.2 | AC108: 45945 | AD108: =AA108+AB108 -> 105239.2
A109: 108 | B109: HCFM-0673 | C109: MR. AKSHAY RAJ | D109: =SUMIFS(FACILITIES!E:E,FACILITIES!$B:$B,B109) -> 0 | E109: =SUMIFS(FACILITIES!F:F,FACILITIES!$B:$B,$B109) -> 0 | F109: =SUMIFS(FACILITIES!G:G,FACILITIES!$B:$B,B109) -> 0 | G109: =SUMIFS(FACILITIES!H:H,FACILITIES!$B:$B,B109) -> 0 | H109: =SUMIFS(FACILITIES!I:I,FACILITIES!$B:$B,B109) -> 0 | I109: =SUMIFS(FACILITIES!J:J,FACILITIES!$B:$B,B109) -> 0 | J109: =SUMIFS(FACILITIES!K:K,FACILITIES!$B:$B,B109) -> 0 | K109: =SUMIFS(FACILITIES!L:L,FACILITIES!$B:$B,B109) -> 0 | L109: =SUMIFS(FACILITIES!M:M,FACILITIES!$B:$B,B109) -> 0 | M109: =SUMIFS(FACILITIES!N:N,FACILITIES!$B:$B,B109) -> 0 | N109: =SUMIFS(FACILITIES!O:O,FACILITIES!$B:$B,B109) -> 0 | O109: =SUMIFS(FACILITIES!P:P,FACILITIES!$B:$B,B109) -> 0 | P109: =SUMIFS(FACILITIES!Q:Q,FACILITIES!$B:$B,B109) -> 0 | Q109: =SUMIFS(FACILITIES!R:R,FACILITIES!$B:$B,B109) -> 0 | R109: =SUMIFS(FACILITIES!T:T,FACILITIES!B:B,B109) -> 0 | S109: =SUMIFS(FACILITIES!S:S,FACILITIES!B:B,B109) -> 0 | T109: =SUMIFS('F & B'!G:G,'F & B'!B:B,B109) -> 4550 | U109: =T109*0.15 -> 682.5 | V109: =SUMIFS('FIXED AMOUNT'!G:G,'FIXED AMOUNT'!B:B,B109) -> 7000 | W109: =SUM(D109:V109) -> 12232.5 | X109: =SUMIFS('FIXED AMOUNT'!E:E,'FIXED AMOUNT'!B:B,'data base '!B:B) -> 0 | Y109: =SUMIFS('FIXED AMOUNT'!F:F,'FIXED AMOUNT'!B:B,'data base '!B:B) -> 0 | Z109: =SUMIFS('FIXED AMOUNT'!V:V,'FIXED AMOUNT'!B:B,B:B) -> 55450 | AA109: =W109+X109-Y109+Z109 -> 67682.5 | AB109: =W109*0.1 -> 1223.25 | AC109: 45945 | AD109: =AA109+AB109 -> 68905.75
A110: 109 | B110: HCFM-0674 | C110: MR. RAJESH KUMAR CHAWLA | D110: =SUMIFS(FACILITIES!E:E,FACILITIES!$B:$B,B110) -> 0 | E110: =SUMIFS(FACILITIES!F:F,FACILITIES!$B:$B,$B110) -> 0 | F110: =SUMIFS(FACILITIES!G:G,FACILITIES!$B:$B,B110) -> 0 | G110: =SUMIFS(FACILITIES!H:H,FACILITIES!$B:$B,B110) -> 0 | H110: =SUMIFS(FACILITIES!I:I,FACILITIES!$B:$B,B110) -> 0 | I110: =SUMIFS(FACILITIES!J:J,FACILITIES!$B:$B,B110) -> 0 | J110: =SUMIFS(FACILITIES!K:K,FACILITIES!$B:$B,B110) -> 0 | K110: =SUMIFS(FACILITIES!L:L,FACILITIES!$B:$B,B110) -> 0 | L110: =SUMIFS(FACILITIES!M:M,FACILITIES!$B:$B,B110) -> 0 | M110: =SUMIFS(FACILITIES!N:N,FACILITIES!$B:$B,B110) -> 0 | N110: =SUMIFS(FACILITIES!O:O,FACILITIES!$B:$B,B110) -> 0 | O110: =SUMIFS(FACILITIES!P:P,FACILITIES!$B:$B,B110) -> 0 | P110: =SUMIFS(FACILITIES!Q:Q,FACILITIES!$B:$B,B110) -> 0 | Q110: =SUMIFS(FACILITIES!R:R,FACILITIES!$B:$B,B110) -> 0 | R110: =SUMIFS(FACILITIES!T:T,FACILITIES!B:B,B110) -> 0 | S110: =SUMIFS(FACILITIES!S:S,FACILITIES!B:B,B110) -> 0 | T110: =SUMIFS('F & B'!G:G,'F & B'!B:B,B110) -> 1200 | U110: =T110*0.15 -> 180 | V110: =SUMIFS('FIXED AMOUNT'!G:G,'FIXED AMOUNT'!B:B,B110) -> 7000 | W110: =SUM(D110:V110) -> 8380 | X110: =SUMIFS('FIXED AMOUNT'!E:E,'FIXED AMOUNT'!B:B,'data base '!B:B) -> 0 | Y110: =SUMIFS('FIXED AMOUNT'!F:F,'FIXED AMOUNT'!B:B,'data base '!B:B) -> 0 | Z110: =SUMIFS('FIXED AMOUNT'!V:V,'FIXED AMOUNT'!B:B,B:B) -> 13571 | AA110: =W110+X110-Y110+Z110 -> 21951 | AB110: =W110*0.1 -> 838 | AC110: 45945 | AD110: =AA110+AB110 -> 22789
A111: 110 | B111: HCFM-0676 | C111: MR. SAMEER MALIK | D111: =SUMIFS(FACILITIES!E:E,FACILITIES!$B:$B,B111) -> 0 | E111: =SUMIFS(FACILITIES!F:F,FACILITIES!$B:$B,$B111) -> 0 | F111: =SUMIFS(FACILITIES!G:G,FACILITIES!$B:$B,B111) -> 0 | G111: =SUMIFS(FACILITIES!H:H,FACILITIES!$B:$B,B111) -> 0 | H111: =SUMIFS(FACILITIES!I:I,FACILITIES!$B:$B,B111) -> 0 | I111: =SUMIFS(FACILITIES!J:J,FACILITIES!$B:$B,B111) -> 0 | J111: =SUMIFS(FACILITIES!K:K,FACILITIES!$B:$B,B111) -> 0 | K111: =SUMIFS(FACILITIES!L:L,FACILITIES!$B:$B,B111) -> 0 | L111: =SUMIFS(FACILITIES!M:M,FACILITIES!$B:$B,B111) -> 0 | M111: =SUMIFS(FACILITIES!N:N,FACILITIES!$B:$B,B111) -> 0 | N111: =SUMIFS(FACILITIES!O:O,FACILITIES!$B:$B,B111) -> 0 | O111: =SUMIFS(FACILITIES!P:P,FACILITIES!$B:$B,B111) -> 0 | P111: =SUMIFS(FACILITIES!Q:Q,FACILITIES!$B:$B,B111) -> 0 | Q111: =SUMIFS(FACILITIES!R:R,FACILITIES!$B:$B,B111) -> 0 | R111: =SUMIFS(FACILITIES!T:T,FACILITIES!B:B,B111) -> 0 | S111: =SUMIFS(FACILITIES!S:S,FACILITIES!B:B,B111) -> 0 | T111: =SUMIFS('F & B'!G:G,'F & B'!B:B,B111) -> 0 | U111: =T111*0.15 -> 0 | V111: =SUMIFS('FIXED AMOUNT'!G:G,'FIXED AMOUNT'!B:B,B111) -> 7000 | W111: =SUM(D111:V111) -> 7000 | X111: =SUMIFS('FIXED AMOUNT'!E:E,'FIXED AMOUNT'!B:B,'data base '!B:B) -> 0 | Y111: =SUMIFS('FIXED AMOUNT'!F:F,'FIXED AMOUNT'!B:B,'data base '!B:B) -> 0 | Z111: =SUMIFS('FIXED AMOUNT'!V:V,'FIXED AMOUNT'!B:B,B:B) -> 60000 | AA111: =W111+X111-Y111+Z111 -> 67000 | AB111: =W111*0.1 -> 700 | AC111: 45945 | AD111: =AA111+AB111 -> 67700
A112: 111 | B112: HCFM-0677 | C112: MR. MUNAWAR HUSSAIN | D112: =SUMIFS(FACILITIES!E:E,FACILITIES!$B:$B,B112) -> 1800 | E112: =SUMIFS(FACILITIES!F:F,FACILITIES!$B:$B,$B112) -> 600 | F112: =SUMIFS(FACILITIES!G:G,FACILITIES!$B:$B,B112) -> 0 | G112: =SUMIFS(FACILITIES!H:H,FACILITIES!$B:$B,B112) -> 0 | H112: =SUMIFS(FACILITIES!I:I,FACILITIES!$B:$B,B112) -> 0 | I112: =SUMIFS(FACILITIES!J:J,FACILITIES!$B:$B,B112) -> 0 | J112: =SUMIFS(FACILITIES!K:K,FACILITIES!$B:$B,B112) -> 0 | K112: =SUMIFS(FACILITIES!L:L,FACILITIES!$B:$B,B112) -> 0 | L112: =SUMIFS(FACILITIES!M:M,FACILITIES!$B:$B,B112) -> 0 | M112: =SUMIFS(FACILITIES!N:N,FACILITIES!$B:$B,B112) -> 0 | N112: =SUMIFS(FACILITIES!O:O,FACILITIES!$B:$B,B112) -> 0 | O112: =SUMIFS(FACILITIES!P:P,FACILITIES!$B:$B,B112) -> 0 | P112: =SUMIFS(FACILITIES!Q:Q,FACILITIES!$B:$B,B112) -> 0 | Q112: =SUMIFS(FACILITIES!R:R,FACILITIES!$B:$B,B112) -> 0 | R112: =SUMIFS(FACILITIES!T:T,FACILITIES!B:B,B112) -> 0 | S112: =SUMIFS(FACILITIES!S:S,FACILITIES!B:B,B112) -> 0 | T112: =SUMIFS('F & B'!G:G,'F & B'!B:B,B112) -> 10350 | U112: =T112*0.15 -> 1552.5 | V112: =SUMIFS('FIXED AMOUNT'!G:G,'FIXED AMOUNT'!B:B,B112) -> 7000 | W112: =SUM(D112:V112) -> 21302.5 | X112: =SUMIFS('FIXED AMOUNT'!E:E,'FIXED AMOUNT'!B:B,'data base '!B:B) -> 0 | Y112: =SUMIFS('FIXED AMOUNT'!F:F,'FIXED AMOUNT'!B:B,'data base '!B:B) -> 0 | Z112: =SUMIFS('FIXED AMOUNT'!V:V,'FIXED AMOUNT'!B:B,B:B) -> 0 | AA112: =W112+X112-Y112+Z112 -> 21302.5 | AB112: =W112*0.1 -> 2130.25 | AC112: 45945 | AD112: =AA112+AB112 -> 23432.75
A113: 112 | B113: HCFM-0678 | C113: MR. AIJAZ ALI BALOCH | D113: =SUMIFS(FACILITIES!E:E,FACILITIES!$B:$B,B113) -> 0 | E113: =SUMIFS(FACILITIES!F:F,FACILITIES!$B:$B,$B113) -> 150 | F113: =SUMIFS(FACILITIES!G:G,FACILITIES!$B:$B,B113) -> 0 | G113: =SUMIFS(FACILITIES!H:H,FACILITIES!$B:$B,B113) -> 0 | H113: =SUMIFS(FACILITIES!I:I,FACILITIES!$B:$B,B113) -> 0 | I113: =SUMIFS(FACILITIES!J:J,FACILITIES!$B:$B,B113) -> 6400 | J113: =SUMIFS(FACILITIES!K:K,FACILITIES!$B:$B,B113) -> 0 | K113: =SUMIFS(FACILITIES!L:L,FACILITIES!$B:$B,B113) -> 0 | L113: =SUMIFS(FACILITIES!M:M,FACILITIES!$B:$B,B113) -> 0 | M113: =SUMIFS(FACILITIES!N:N,FACILITIES!$B:$B,B113) -> 0 | N113: =SUMIFS(FACILITIES!O:O,FACILITIES!$B:$B,B113) -> 0 | O113: =SUMIFS(FACILITIES!P:P,FACILITIES!$B:$B,B113) -> 0 | P113: =SUMIFS(FACILITIES!Q:Q,FACILITIES!$B:$B,B113) -> 0 | Q113: =SUMIFS(FACILITIES!R:R,FACILITIES!$B:$B,B113) -> 0 | R113: =SUMIFS(FACILITIES!T:T,FACILITIES!B:B,B113) -> 0 | S113: =SUMIFS(FACILITIES!S:S,FACILITIES!B:B,B113) -> 0 | T113: =SUMIFS('F & B'!G:G,'F & B'!B:B,B113) -> 51687 | U113: =T113*0.15 -> 7753.05 | V113: =SUMIFS('FIXED AMOUNT'!G:G,'FIXED AMOUNT'!B:B,B113) -> 7000 | W113: =SUM(D113:V113) -> 72990.05 | X113: =SUMIFS('FIXED AMOUNT'!E:E,'FIXED AMOUNT'!B:B,'data base '!B:B) -> 0 | Y113: =SUMIFS('FIXED AMOUNT'!F:F,'FIXED AMOUNT'!B:B,'data base '!B:B) -> 0 | Z113: =SUMIFS('FIXED AMOUNT'!V:V,'FIXED AMOUNT'!B:B,B:B) -> 0 | AA113: =W113+X113-Y113+Z113 -> 72990.05 | AB113: =W113*0.1 -> 7299.005 | AC113: 45945 | AD113: =AA113+AB113 -> 80289.055
A114: 113 | B114: HCFM-0679 | C114: MR. ANEEL ZAHOOR | D114: =SUMIFS(FACILITIES!E:E,FACILITIES!$B:$B,B114) -> 0 | E114: =SUMIFS(FACILITIES!F:F,FACILITIES!$B:$B,$B114) -> 0 | F114: =SUMIFS(FACILITIES!G:G,FACILITIES!$B:$B,B114) -> 0 | G114: =SUMIFS(FACILITIES!H:H,FACILITIES!$B:$B,B114) -> 0 | H114: =SUMIFS(FACILITIES!I:I,FACILITIES!$B:$B,B114) -> 0 | I114: =SUMIFS(FACILITIES!J:J,FACILITIES!$B:$B,B114) -> 1600 | J114: =SUMIFS(FACILITIES!K:K,FACILITIES!$B:$B,B114) -> 0 | K114: =SUMIFS(FACILITIES!L:L,FACILITIES!$B:$B,B114) -> 0 | L114: =SUMIFS(FACILITIES!M:M,FACILITIES!$B:$B,B114) -> 0 | M114: =SUMIFS(FACILITIES!N:N,FACILITIES!$B:$B,B114) -> 0 | N114: =SUMIFS(FACILITIES!O:O,FACILITIES!$B:$B,B114) -> 0 | O114: =SUMIFS(FACILITIES!P:P,FACILITIES!$B:$B,B114) -> 57950 | P114: =SUMIFS(FACILITIES!Q:Q,FACILITIES!$B:$B,B114) -> 0 | Q114: =SUMIFS(FACILITIES!R:R,FACILITIES!$B:$B,B114) -> 0 | R114: =SUMIFS(FACILITIES!T:T,FACILITIES!B:B,B114) -> 0 | S114: =SUMIFS(FACILITIES!S:S,FACILITIES!B:B,B114) -> 0 | T114: =SUMIFS('F & B'!G:G,'F & B'!B:B,B114) -> 21629 | U114: =T114*0.15 -> 3244.35 | V114: =SUMIFS('FIXED AMOUNT'!G:G,'FIXED AMOUNT'!B:B,B114) -> 7000 | W114: =SUM(D114:V114) -> 91423.35 | X114: =SUMIFS('FIXED AMOUNT'!E:E,'FIXED AMOUNT'!B:B,'data base '!B:B) -> 0 | Y114: =SUMIFS('FIXED AMOUNT'!F:F,'FIXED AMOUNT'!B:B,'data base '!B:B) -> 0 | Z114: =SUMIFS('FIXED AMOUNT'!V:V,'FIXED AMOUNT'!B:B,B:B) -> 0 | AA114: =W114+X114-Y114+Z114 -> 91423.35 | AB114: =W114*0.1 -> 9142.335 | AC114: 45945 | AD114: =AA114+AB114 -> 100565.69
A115: 114 | B115: HCFM-0680 | C115: MR. AYAZ JAMRO | D115: =SUMIFS(FACILITIES!E:E,FACILITIES!$B:$B,B115) -> 0 | E115: =SUMIFS(FACILITIES!F:F,FACILITIES!$B:$B,$B115) -> 0 | F115: =SUMIFS(FACILITIES!G:G,FACILITIES!$B:$B,B115) -> 0 | G115: =SUMIFS(FACILITIES!H:H,FACILITIES!$B:$B,B115) -> 0 | H115: =SUMIFS(FACILITIES!I:I,FACILITIES!$B:$B,B115) -> 0 | I115: =SUMIFS(FACILITIES!J:J,FACILITIES!$B:$B,B115) -> 1500 | J115: =SUMIFS(FACILITIES!K:K,FACILITIES!$B:$B,B115) -> 0 | K115: =SUMIFS(FACILITIES!L:L,FACILITIES!$B:$B,B115) -> 0 | L115: =SUMIFS(FACILITIES!M:M,FACILITIES!$B:$B,B115) -> 0 | M115: =SUMIFS(FACILITIES!N:N,FACILITIES!$B:$B,B115) -> 0 | N115: =SUMIFS(FACILITIES!O:O,FACILITIES!$B:$B,B115) -> 0 | O115: =SUMIFS(FACILITIES!P:P,FACILITIES!$B:$B,B115) -> 0 | P115: =SUMIFS(FACILITIES!Q:Q,FACILITIES!$B:$B,B115) -> 0 | Q115: =SUMIFS(FACILITIES!R:R,FACILITIES!$B:$B,B115) -> 0 | R115: =SUMIFS(FACILITIES!T:T,FACILITIES!B:B,B115) -> 7000 | S115: =SUMIFS(FACILITIES!S:S,FACILITIES!B:B,B115) -> 0 | T115: =SUMIFS('F & B'!G:G,'F & B'!B:B,B115) -> 5770 | U115: =T115*0.15 -> 865.5 | V115: =SUMIFS('FIXED AMOUNT'!G:G,'FIXED AMOUNT'!B:B,B115) -> 7000 | W115: =SUM(D115:V115) -> 22135.5 | X115: =SUMIFS('FIXED AMOUNT'!E:E,'FIXED AMOUNT'!B:B,'data base '!B:B) -> 0 | Y115: =SUMIFS('FIXED AMOUNT'!F:F,'FIXED AMOUNT'!B:B,'data base '!B:B) -> 0 | Z115: =SUMIFS('FIXED AMOUNT'!V:V,'FIXED AMOUNT'!B:B,B:B) -> 0 | AA115: =W115+X115-Y115+Z115 -> 22135.5 | AB115: =W115*0.1 -> 2213.55 | AC115: 45945 | AD115: =AA115+AB115 -> 24349.05
A116: 115 | B116: HCFM-0681 | C116: BAHRIA ADVENTURE LAND | D116: =SUMIFS(FACILITIES!E:E,FACILITIES!$B:$B,B116) -> 0 | E116: =SUMIFS(FACILITIES!F:F,FACILITIES!$B:$B,$B116) -> 0 | F116: =SUMIFS(FACILITIES!G:G,FACILITIES!$B:$B,B116) -> 0 | G116: =SUMIFS(FACILITIES!H:H,FACILITIES!$B:$B,B116) -> 0 | H116: =SUMIFS(FACILITIES!I:I,FACILITIES!$B:$B,B116) -> 0 | I116: =SUMIFS(FACILITIES!J:J,FACILITIES!$B:$B,B116) -> 0 | J116: =SUMIFS(FACILITIES!K:K,FACILITIES!$B:$B,B116) -> 0 | K116: =SUMIFS(FACILITIES!L:L,FACILITIES!$B:$B,B116) -> 0 | L116: =SUMIFS(FACILITIES!M:M,FACILITIES!$B:$B,B116) -> 0 | M116: =SUMIFS(FACILITIES!N:N,FACILITIES!$B:$B,B116) -> 0 | N116: =SUMIFS(FACILITIES!O:O,FACILITIES!$B:$B,B116) -> 0 | O116: =SUMIFS(FACILITIES!P:P,FACILITIES!$B:$B,B116) -> 0 | P116: =SUMIFS(FACILITIES!Q:Q,FACILITIES!$B:$B,B116) -> 0 | Q116: =SUMIFS(FACILITIES!R:R,FACILITIES!$B:$B,B116) -> 0 | R116: =SUMIFS(FACILITIES!T:T,FACILITIES!B:B,B116) -> 0 | S116: =SUMIFS(FACILITIES!S:S,FACILITIES!B:B,B116) -> 0 | T116: =SUMIFS('F & B'!G:G,'F & B'!B:B,B116) -> 0 | U116: 0 | V116: =SUMIFS('FIXED AMOUNT'!G:G,'FIXED AMOUNT'!B:B,B116) -> 0 | W116: =SUM(D116:V116) -> 0 | Y116: =SUMIFS('FIXED AMOUNT'!F:F,'FIXED AMOUNT'!B:B,'data base '!B:B) -> 0 | Z116: =SUMIFS('FIXED AMOUNT'!V:V,'FIXED AMOUNT'!B:B,B:B) -> 0 | AA116: =W116+X116-Y116+Z116 -> 0 | AB116: =W116*0.1 -> 0 | AC116: 45945 | AD116: =AA116+AB116 -> 0
A117: 116 | B117: HCFM-0682 | C117: MR. ZAHIR REHMAN | D117: =SUMIFS(FACILITIES!E:E,FACILITIES!$B:$B,B117) -> 0 | E117: =SUMIFS(FACILITIES!F:F,FACILITIES!$B:$B,$B117) -> 0 | F117: =SUMIFS(FACILITIES!G:G,FACILITIES!$B:$B,B117) -> 0 | G117: =SUMIFS(FACILITIES!H:H,FACILITIES!$B:$B,B117) -> 0 | H117: =SUMIFS(FACILITIES!I:I,FACILITIES!$B:$B,B117) -> 0 | I117: =SUMIFS(FACILITIES!J:J,FACILITIES!$B:$B,B117) -> 1500 | J117: =SUMIFS(FACILITIES!K:K,FACILITIES!$B:$B,B117) -> 0 | K117: =SUMIFS(FACILITIES!L:L,FACILITIES!$B:$B,B117) -> 0 | L117: =SUMIFS(FACILITIES!M:M,FACILITIES!$B:$B,B117) -> 0 | M117: =SUMIFS(FACILITIES!N:N,FACILITIES!$B:$B,B117) -> 0 | N117: =SUMIFS(FACILITIES!O:O,FACILITIES!$B:$B,B117) -> 0 | O117: =SUMIFS(FACILITIES!P:P,FACILITIES!$B:$B,B117) -> 0 | P117: =SUMIFS(FACILITIES!Q:Q,FACILITIES!$B:$B,B117) -> 0 | Q117: =SUMIFS(FACILITIES!R:R,FACILITIES!$B:$B,B117) -> 0 | R117: =SUMIFS(FACILITIES!T:T,FACILITIES!B:B,B117) -> 0 | S117: =SUMIFS(FACILITIES!S:S,FACILITIES!B:B,B117) -> 0 | T117: =SUMIFS('F & B'!G:G,'F & B'!B:B,B117) -> 24300 | U117: =T117*0.15 -> 3645 | V117: =SUMIFS('FIXED AMOUNT'!G:G,'FIXED AMOUNT'!B:B,B117) -> 7000 | W117: =SUM(D117:V117) -> 36445 | X117: =SUMIFS('FIXED AMOUNT'!E:E,'FIXED AMOUNT'!B:B,B117) -> 0 | Y117: =SUMIFS('FIXED AMOUNT'!F:F,'FIXED AMOUNT'!B:B,'data base '!B:B) -> 0 | Z117: =SUMIFS('FIXED AMOUNT'!V:V,'FIXED AMOUNT'!B:B,B:B) -> 0 | AA117: =W117+X117-Y117+Z117 -> 36445 | AB117: =W117*0.1 -> 3644.5 | AC117: 45945 | AD117: =AA117+AB117 -> 40089.5
A118: 117 | B118: HCFM-0683 | C118: MR. YASIR RASHEED | D118: =SUMIFS(FACILITIES!E:E,FACILITIES!$B:$B,B118) -> 0 | E118: =SUMIFS(FACILITIES!F:F,FACILITIES!$B:$B,$B118) -> 0 | F118: =SUMIFS(FACILITIES!G:G,FACILITIES!$B:$B,B118) -> 0 | G118: =SUMIFS(FACILITIES!H:H,FACILITIES!$B:$B,B118) -> 0 | H118: =SUMIFS(FACILITIES!I:I,FACILITIES!$B:$B,B118) -> 0 | I118: =SUMIFS(FACILITIES!J:J,FACILITIES!$B:$B,B118) -> 600 | J118: =SUMIFS(FACILITIES!K:K,FACILITIES!$B:$B,B118) -> 0 | K118: =SUMIFS(FACILITIES!L:L,FACILITIES!$B:$B,B118) -> 0 | L118: =SUMIFS(FACILITIES!M:M,FACILITIES!$B:$B,B118) -> 0 | M118: =SUMIFS(FACILITIES!N:N,FACILITIES!$B:$B,B118) -> 1500 | N118: =SUMIFS(FACILITIES!O:O,FACILITIES!$B:$B,B118) -> 0 | O118: =SUMIFS(FACILITIES!P:P,FACILITIES!$B:$B,B118) -> 450 | P118: =SUMIFS(FACILITIES!Q:Q,FACILITIES!$B:$B,B118) -> 0 | Q118: =SUMIFS(FACILITIES!R:R,FACILITIES!$B:$B,B118) -> 0 | R118: =SUMIFS(FACILITIES!T:T,FACILITIES!B:B,B118) -> 0 | S118: =SUMIFS(FACILITIES!S:S,FACILITIES!B:B,B118) -> 0 | T118: =SUMIFS('F & B'!G:G,'F & B'!B:B,B118) -> 4650 | U118: =T118*0.15 -> 697.5 | V118: =SUMIFS('FIXED AMOUNT'!G:G,'FIXED AMOUNT'!B:B,B118) -> 7000 | W118: =SUM(D118:V118) -> 14897.5 | X118: =SUMIFS('FIXED AMOUNT'!E:E,'FIXED AMOUNT'!B:B,B118) -> 0 | Y118: =SUMIFS('FIXED AMOUNT'!F:F,'FIXED AMOUNT'!B:B,'data base '!B:B) -> 0 | Z118: =SUMIFS('FIXED AMOUNT'!V:V,'FIXED AMOUNT'!B:B,B:B) -> 0 | AA118: =W118+X118-Y118+Z118 -> 14897.5 | AB118: =W118*0.1 -> 1489.75 | AC118: 45945 | AD118: =AA118+AB118 -> 16387.25
A119: 118 | B119: HCFM-0684 | C119: MR. ZAMIR ALI SHAH | D119: =SUMIFS(FACILITIES!E:E,FACILITIES!$B:$B,B119) -> 14700 | E119: =SUMIFS(FACILITIES!F:F,FACILITIES!$B:$B,$B119) -> 0 | F119: =SUMIFS(FACILITIES!G:G,FACILITIES!$B:$B,B119) -> 0 | G119: =SUMIFS(FACILITIES!H:H,FACILITIES!$B:$B,B119) -> 0 | H119: =SUMIFS(FACILITIES!I:I,FACILITIES!$B:$B,B119) -> 0 | I119: =SUMIFS(FACILITIES!J:J,FACILITIES!$B:$B,B119) -> 12000 | J119: =SUMIFS(FACILITIES!K:K,FACILITIES!$B:$B,B119) -> 0 | K119: =SUMIFS(FACILITIES!L:L,FACILITIES!$B:$B,B119) -> 0 | L119: =SUMIFS(FACILITIES!M:M,FACILITIES!$B:$B,B119) -> 0 | M119: =SUMIFS(FACILITIES!N:N,FACILITIES!$B:$B,B119) -> 0 | N119: =SUMIFS(FACILITIES!O:O,FACILITIES!$B:$B,B119) -> 4000 | O119: =SUMIFS(FACILITIES!P:P,FACILITIES!$B:$B,B119) -> 24200 | P119: =SUMIFS(FACILITIES!Q:Q,FACILITIES!$B:$B,B119) -> 0 | Q119: =SUMIFS(FACILITIES!R:R,FACILITIES!$B:$B,B119) -> 0 | R119: =SUMIFS(FACILITIES!T:T,FACILITIES!B:B,B119) -> 0 | S119: =SUMIFS(FACILITIES!S:S,FACILITIES!B:B,B119) -> 0 | T119: =SUMIFS('F & B'!G:G,'F & B'!B:B,B119) -> 84916 | U119: =T119*0.15 -> 12737.4 | V119: =SUMIFS('FIXED AMOUNT'!G:G,'FIXED AMOUNT'!B:B,B119) -> 7000 | W119: =SUM(D119:V119) -> 159553.4 | X119: =SUMIFS('FIXED AMOUNT'!E:E,'FIXED AMOUNT'!B:B,B119) -> 0 | Y119: =SUMIFS('FIXED AMOUNT'!F:F,'FIXED AMOUNT'!B:B,'data base '!B:B) -> 0 | Z119: =SUMIFS('FIXED AMOUNT'!V:V,'FIXED AMOUNT'!B:B,B:B) -> 0 | AA119: =W119+X119-Y119+Z119 -> 159553.4 | AB119: =W119*0.1 -> 15955.34 | AC119: 45945 | AD119: =AA119+AB119 -> 175508.74
A120: 119 | B120: HCFM-0685 | C120: MR. KHURRAM SHAHZAD MEMON | D120: =SUMIFS(FACILITIES!E:E,FACILITIES!$B:$B,B120) -> 0 | E120: =SUMIFS(FACILITIES!F:F,FACILITIES!$B:$B,$B120) -> 0 | F120: =SUMIFS(FACILITIES!G:G,FACILITIES!$B:$B,B120) -> 0 | G120: =SUMIFS(FACILITIES!H:H,FACILITIES!$B:$B,B120) -> 0 | H120: =SUMIFS(FACILITIES!I:I,FACILITIES!$B:$B,B120) -> 0 | I120: =SUMIFS(FACILITIES!J:J,FACILITIES!$B:$B,B120) -> 0 | J120: =SUMIFS(FACILITIES!K:K,FACILITIES!$B:$B,B120) -> 0 | K120: =SUMIFS(FACILITIES!L:L,FACILITIES!$B:$B,B120) -> 0 | L120: =SUMIFS(FACILITIES!M:M,FACILITIES!$B:$B,B120) -> 0 | M120: =SUMIFS(FACILITIES!N:N,FACILITIES!$B:$B,B120) -> 0 | N120: =SUMIFS(FACILITIES!O:O,FACILITIES!$B:$B,B120) -> 0 | O120: =SUMIFS(FACILITIES!P:P,FACILITIES!$B:$B,B120) -> 0 | P120: =SUMIFS(FACILITIES!Q:Q,FACILITIES!$B:$B,B120) -> 0 | Q120: =SUMIFS(FACILITIES!R:R,FACILITIES!$B:$B,B120) -> 0 | R120: =SUMIFS(FACILITIES!T:T,FACILITIES!B:B,B120) -> 0 | S120: =SUMIFS(FACILITIES!S:S,FACILITIES!B:B,B120) -> 0 | T120: =SUMIFS('F & B'!G:G,'F & B'!B:B,B120) -> 0 | U120: =T120*0.15 -> 0 | V120: =SUMIFS('FIXED AMOUNT'!G:G,'FIXED AMOUNT'!B:B,B120) -> 7000 | W120: =SUM(D120:V120) -> 7000 | X120: =SUMIFS('FIXED AMOUNT'!E:E,'FIXED AMOUNT'!B:B,B120) -> 0 | Y120: =SUMIFS('FIXED AMOUNT'!F:F,'FIXED AMOUNT'!B:B,'data base '!B:B) -> 0 | Z120: =SUMIFS('FIXED AMOUNT'!V:V,'FIXED AMOUNT'!B:B,B:B) -> 30000 | AA120: =W120+X120-Y120+Z120 -> 37000 | AB120: =W120*0.1 -> 700 | AC120: 45945 | AD120: =AA120+AB120 -> 37700
A121: 120 | B121: HCFM-0686 | C121: MR. GHULAM MUSTAFA | D121: =SUMIFS(FACILITIES!E:E,FACILITIES!$B:$B,B121) -> 1800 | E121: =SUMIFS(FACILITIES!F:F,FACILITIES!$B:$B,$B121) -> 0 | F121: =SUMIFS(FACILITIES!G:G,FACILITIES!$B:$B,B121) -> 0 | G121: =SUMIFS(FACILITIES!H:H,FACILITIES!$B:$B,B121) -> 0 | H121: =SUMIFS(FACILITIES!I:I,FACILITIES!$B:$B,B121) -> 0 | I121: =SUMIFS(FACILITIES!J:J,FACILITIES!$B:$B,B121) -> 2000 | J121: =SUMIFS(FACILITIES!K:K,FACILITIES!$B:$B,B121) -> 0 | K121: =SUMIFS(FACILITIES!L:L,FACILITIES!$B:$B,B121) -> 0 | L121: =SUMIFS(FACILITIES!M:M,FACILITIES!$B:$B,B121) -> 0 | M121: =SUMIFS(FACILITIES!N:N,FACILITIES!$B:$B,B121) -> 0 | N121: =SUMIFS(FACILITIES!O:O,FACILITIES!$B:$B,B121) -> 0 | O121: =SUMIFS(FACILITIES!P:P,FACILITIES!$B:$B,B121) -> 0 | P121: =SUMIFS(FACILITIES!Q:Q,FACILITIES!$B:$B,B121) -> 0 | Q121: =SUMIFS(FACILITIES!R:R,FACILITIES!$B:$B,B121) -> 0 | R121: =SUMIFS(FACILITIES!T:T,FACILITIES!B:B,B121) -> 15000 | S121: =SUMIFS(FACILITIES!S:S,FACILITIES!B:B,B121) -> 0 | T121: =SUMIFS('F & B'!G:G,'F & B'!B:B,B121) -> 36529 | U121: =T121*0.15 -> 5479.35 | V121: =SUMIFS('FIXED AMOUNT'!G:G,'FIXED AMOUNT'!B:B,B121) -> 7000 | W121: =SUM(D121:V121) -> 67808.35 | X121: =SUMIFS('FIXED AMOUNT'!E:E,'FIXED AMOUNT'!B:B,B121) -> 0 | Y121: =SUMIFS('FIXED AMOUNT'!F:F,'FIXED AMOUNT'!B:B,'data base '!B:B) -> 0 | Z121: =SUMIFS('FIXED AMOUNT'!V:V,'FIXED AMOUNT'!B:B,B:B) -> 0 | AA121: =W121+X121-Y121+Z121 -> 67808.35 | AB121: =W121*0.1 -> 6780.835 | AC121: 45945 | AD121: =AA121+AB121 -> 74589.185
A122: 121 | B122: HCFM-0687 | C122: MR. IKRAMULLAH | D122: =SUMIFS(FACILITIES!E:E,FACILITIES!$B:$B,B122) -> 0 | E122: =SUMIFS(FACILITIES!F:F,FACILITIES!$B:$B,$B122) -> 0 | F122: =SUMIFS(FACILITIES!G:G,FACILITIES!$B:$B,B122) -> 0 | G122: =SUMIFS(FACILITIES!H:H,FACILITIES!$B:$B,B122) -> 0 | H122: =SUMIFS(FACILITIES!I:I,FACILITIES!$B:$B,B122) -> 0 | I122: =SUMIFS(FACILITIES!J:J,FACILITIES!$B:$B,B122) -> 0 | J122: =SUMIFS(FACILITIES!K:K,FACILITIES!$B:$B,B122) -> 0 | K122: =SUMIFS(FACILITIES!L:L,FACILITIES!$B:$B,B122) -> 0 | L122: =SUMIFS(FACILITIES!M:M,FACILITIES!$B:$B,B122) -> 0 | M122: =SUMIFS(FACILITIES!N:N,FACILITIES!$B:$B,B122) -> 0 | N122: =SUMIFS(FACILITIES!O:O,FACILITIES!$B:$B,B122) -> 0 | O122: =SUMIFS(FACILITIES!P:P,FACILITIES!$B:$B,B122) -> 0 | P122: =SUMIFS(FACILITIES!Q:Q,FACILITIES!$B:$B,B122) -> 0 | Q122: =SUMIFS(FACILITIES!R:R,FACILITIES!$B:$B,B122) -> 0 | R122: =SUMIFS(FACILITIES!T:T,FACILITIES!B:B,B122) -> 0 | S122: =SUMIFS(FACILITIES!S:S,FACILITIES!B:B,B122) -> 0 | T122: =SUMIFS('F & B'!G:G,'F & B'!B:B,B122) -> 0 | U122: =T122*0.15 -> 0 | V122: =SUMIFS('FIXED AMOUNT'!G:G,'FIXED AMOUNT'!B:B,B122) -> 7000 | W122: =SUM(D122:V122) -> 7000 | X122: =SUMIFS('FIXED AMOUNT'!E:E,'FIXED AMOUNT'!B:B,B122) -> 0 | Y122: =SUMIFS('FIXED AMOUNT'!F:F,'FIXED AMOUNT'!B:B,'data base '!B:B) -> 0 | Z122: =SUMIFS('FIXED AMOUNT'!V:V,'FIXED AMOUNT'!B:B,B:B) -> 0 | AA122: =W122+X122-Y122+Z122 -> 7000 | AB122: =W122*0.1 -> 700 | AC122: 45945 | AD122: =AA122+AB122 -> 7700
A123: 122 | B123: HCFM-0 | C123: CASH | D123: =SUMIFS(FACILITIES!E:E,FACILITIES!$B:$B,B123) -> 7500 | E123: =SUMIFS(FACILITIES!F:F,FACILITIES!$B:$B,$B123) -> 150 | F123: =SUMIFS(FACILITIES!G:G,FACILITIES!$B:$B,B123) -> 0 | G123: =SUMIFS(FACILITIES!H:H,FACILITIES!$B:$B,B123) -> 0 | H123: =SUMIFS(FACILITIES!I:I,FACILITIES!$B:$B,B123) -> 0 | I123: =SUMIFS(FACILITIES!J:J,FACILITIES!$B:$B,B123) -> 4000 | J123: =SUMIFS(FACILITIES!K:K,FACILITIES!$B:$B,B123) -> 2600 | K123: =SUMIFS(FACILITIES!L:L,FACILITIES!$B:$B,B123) -> 0 | L123: =SUMIFS(FACILITIES!M:M,FACILITIES!$B:$B,B123) -> 0 | M123: =SUMIFS(FACILITIES!N:N,FACILITIES!$B:$B,B123) -> 0 | N123: =SUMIFS(FACILITIES!O:O,FACILITIES!$B:$B,B123) -> 11200 | O123: =SUMIFS(FACILITIES!P:P,FACILITIES!$B:$B,B123) -> 101250 | P123: =SUMIFS(FACILITIES!Q:Q,FACILITIES!$B:$B,B123) -> 0 | Q123: =SUMIFS(FACILITIES!R:R,FACILITIES!$B:$B,B123) -> 0 | R123: =SUMIFS(FACILITIES!T:T,FACILITIES!B:B,B123) -> 0 | S123: =SUMIFS(FACILITIES!S:S,FACILITIES!B:B,B123) -> 150000 | T123: =SUMIFS('F & B'!G:G,'F & B'!B:B,B123) -> 0 | U123: =T123*0.15 -> 0 | V123: =SUMIFS('FIXED AMOUNT'!G:G,'FIXED AMOUNT'!B:B,B123) -> 0 | W123: =SUM(D123:V123) -> 276700 | X123: =SUMIFS('FIXED AMOUNT'!E:E,'FIXED AMOUNT'!B:B,B123) -> 0 | Y123: =SUMIFS('FIXED AMOUNT'!F:F,'FIXED AMOUNT'!B:B,'data base '!B:B) -> 0 | Z123: =SUMIFS('FIXED AMOUNT'!V:V,'FIXED AMOUNT'!B:B,B:B) -> 0 | AA123: =W123+X123-Y123+Z123 -> 276700 | AB123: =W123*0.1 -> 27670 | AC123: 45945 | AD123: 0
D124: =SUM(D2:D122) -> 81600 | E124: =SUM(E2:E122) -> 33900 | F124: =SUM(F2:F122) -> 1500 | G124: =SUM(G2:G122) -> 7500 | H124: =SUM(H2:H122) -> 300 | I124: =SUM(I2:I122) -> 105100 | J124: =SUM(J2:J122) -> 14400 | K124: =SUM(K2:K122) -> 0 | ... R124: =SUM(R2:R122) -> 508000 | T124: =SUM(T2:T122) -> 5370466 | U124: =SUM(U2:U122) -> 791409.9 | V124: =SUM(V2:V122) -> 819000 | W124: =SUM(W2:W123) -> 8825475.9 | X124: =SUM(X2:X123) -> 0 | Y124: =SUM(Y2:Y123) -> 0 | Z124: =SUM(Z2:Z123) -> 1153996 | AA124: =SUM(AA2:AA123) -> 9979471.9 | AB124: =SUM(AB2:AB123) -> 882547.59 | AD124: =SUM(AD2:AD123) -> 10515064 | AE124: =AD124-AA124 -> 535592.19

Sheet FIXED AMOUNT
A1: S.no | B1: Membership number | C1: Name | D1: Date | E1: AREARS | F1: ADVANCD PAID | G1: Monthly sub | H1: TOTAL DININ | I1: Party Charges nov | J1: Party Charges july | K1: Party Charges Aug | L1: Party Charges sep | M1: Party Charges OCT | N1: Party Charges NOV | O1: DECEMBER | P1: JULY | Q1: AUGUST | R1: SEPTEMBER | S1: OCTUBER | T1: NOVEMBER | U1: Mandatory Charges | V1: REMAINING
A2: 1 | B2: HCFM-AH001 | C2: ADMIRAL AHMED HAYAT | D2: 45992 | E2: 0 | F2: 0 | G2: 7000 | H2: =SUM(I2:T2) -> 65600 | I2: =SUMIFS(FACILITIES!T:T,FACILITIES!B:B,B2) -> 0 | J2: 0 | K2: 0 | L2: 0 | M2: - | N2: 0 | O2: =SUMIFS('F & B'!G:G,'F & B'!B:B,B2) -> 24550 | P2: 0 | Q2: 11350 | R2: 11100 | S2: 18600 | T2: 0 | U2: 60000 | V2: =IF(U2-H2>0, U2-H2, "")
A3: 2 | B3: HCFM-0502 | C3: MR. JABIR SHAHZAD | D3: 45992 | E3: 0 | F3: 0 | G3: 7000 | H3: =SUM(I3:T3) -> 61790 | I3: =SUMIFS(FACILITIES!T:T,FACILITIES!B:B,B3) -> 0 | J3: 0 | K3: 0 | L3: 0 | M3: - | N3: 4500 | O3: =SUMIFS('F & B'!G:G,'F & B'!B:B,B3) -> 12950 | P3: 13200 | Q3: 5210 | R3: 15080 | S3: 8950 | T3: 1900 | U3: 60000 | V3: =IF(U3-H3>0, U3-H3, "")
A4: 3 | B4: HCFM-0503 | C4: MR.GHULAM NABI OTHI | D4: 45992 | E4: 0 | F4: 0 | G4: 7000 | H4: =SUM(I4:T4) -> 168251 | I4: =SUMIFS(FACILITIES!T:T,FACILITIES!B:B,B4) -> 0 | J4: 0 | K4: 0 | L4: 0 | M4: - | N4: 2000 | O4: =SUMIFS('F & B'!G:G,'F & B'!B:B,B4) -> 52578 | P4: 17820 | Q4: 19924 | R4: 30270 | S4: 11600 | T4: 34059 | U4: 60000 | V4: =IF(U4-H4>0, U4-H4, "")
A5: 4 | B5: HCFM-0504 | C5: MR.BILAL AHMED | D5: 45992 | E5: 0 | F5: 0 | G5: 7000 | H5: =SUM(I5:T5) -> 105105 | I5: =SUMIFS(FACILITIES!T:T,FACILITIES!B:B,B5) -> 0 | J5: 0 | K5: 0 | L5: 0 | M5: - | N5: 0 | O5: =SUMIFS('F & B'!G:G,'F & B'!B:B,B5) -> 6550 | P5: 25167 | Q5: 34700 | R5: 9150 | S5: 22388 | T5: 7150 | U5: 60000 | V5: =IF(U5-H5>0, U5-H5, "")
A6: 5 | B6: HCFM-0506 | C6: MR.MUHAMMAD ARIF | D6: 45992 | E6: 0 | F6: 0 | G6: 7000 | H6: =SUM(I6:T6) -> 51526 | I6: =SUMIFS(FACILITIES!T:T,FACILITIES!B:B,B6) -> 0 | J6: 0 | K6: 0 | L6: 0 | M6: - | N6: 0 | O6: =SUMIFS('F & B'!G:G,'F & B'!B:B,B6) -> 22657 | P6: 7325 | Q6: 9974 | R6: 1200 | S6: 10370 | T6: 0 | U6: 60000 | V6: =IF(U6-H6>0, U6-H6, "") -> 8474
A7: 6 | B7: HCFM-0507 | C7: MR.SYED TAHIR ABBAS | D7: 45992 | E7: 0 | F7: 0 | G7: 7000 | H7: =SUM(I7:T7) -> 15650 | I7: =SUMIFS(FACILITIES!T:T,FACILITIES!B:B,B7) -> 0 | J7: 0 | K7: 0 | L7: 0 | M7: - | N7: 0 | O7: =SUMIFS('F & B'!G:G,'F & B'!B:B,B7) -> 3200 | P7: 4420 | Q7: 3850 | R7: 4180 | S7: 0 | T7: 0 | U7: 60000 | V7: =IF(U7-H7>0, U7-H7, "") -> 44350
A8: 7 | B8: HCFM-0508 | C8: MR.SHIRAZ AHMED | D8: 45992 | E8: 0 | F8: 0 | G8: 7000 | H8: =SUM(I8:T8) -> 721159 | I8: =SUMIFS(FACILITIES!T:T,FACILITIES!B:B,B8) -> 0 | J8: 0 | K8: 180000 | L8: 0 | M8: - | N8: 270000 | O8: =SUMIFS('F & B'!G:G,'F & B'!B:B,B8) -> 0 | P8: 3550 | Q8: 236849 | R8: 6160 | S8: 0 | T8: 24600 | U8: 60000 | V8: =IF(U8-H8>0, U8-H8, "")
A9: 8 | B9: HCFM-0509 | C9: MR.SYED ABDULLAH ALI | D9: 45992 | E9: 0 | F9: 0 | G9: 7000 | H9: =SUM(I9:T9) -> 70453 | I9: =SUMIFS(FACILITIES!T:T,FACILITIES!B:B,B9) -> 0 | J9: 0 | K9: 0 | L9: 0 | M9: - | N9: 0 | O9: =SUMIFS('F & B'!G:G,'F & B'!B:B,B9) -> 1300 | P9: 19930 | Q9: 25949 | R9: 14474 | S9: 3625 | T9: 5175 | U9: 60000 | V9: =IF(U9-H9>0, U9-H9, "")
A10: 9 | B10: HCFM-0510 | C10: MR.MUHAMMAD RIZWAN | D10: 45992 | E10: 0 | F10: 0 | G10: 7000 | H10: =SUM(I10:T10) -> 42074 | I10: =SUMIFS(FACILITIES!T:T,FACILITIES!B:B,B10) -> 0 | J10: 0 | K10: 0 | L10: 0 | M10: - | N10: 0 | O10: =SUMIFS('F & B'!G:G,'F & B'!B:B,B10) -> 500 | P10: 6789 | Q10: 0 | R10: 28257 | S10: 0 | T10: 6528 | U10: 60000 | V10: =IF(U10-H10>0, U10-H10, "") -> 17926
A11: 10 | B11: HCFM-0511 | C11: MR.TALHAR AHMED | D11: 45992 | E11: 0 | F11: 0 | G11: 7000 | H11: =SUM(I11:T11) -> 74215 | I11: =SUMIFS(FACILITIES!T:T,FACILITIES!B:B,B11) -> 0 | J11: 0 | K11: 0 | L11: 0 | M11: - | N11: 0 | O11: =SUMIFS('F & B'!G:G,'F & B'!B:B,B11) -> 0 | P11: 54066 | Q11: 0 | R11: 5349 | S11: 10000 | T11: 4800 | U11: 60000 | V11: =IF(U11-H11>0, U11-H11, "")
A12: 11 | B12: HCFM-0512 | C12: MR.ZEESHAN IQBAL | D12: 45992 | E12: 0 | F12: 0 | G12: 7000 | H12: =SUM(I12:T12) -> 56824 | I12: =SUMIFS(FACILITIES!T:T,FACILITIES!B:B,B12) -> 4000 | J12: 0 | K12: 0 | L12: 0 | M12: - | N12: 0 | O12: =SUMIFS('F & B'!G:G,'F & B'!B:B,B12) -> 6150 | P12: 19849 | Q12: 18375 | R12: 1300 | S12: 5700 | T12: 1450 | U12: 60000 | V12: =IF(U12-H12>0, U12-H12, "") -> 3176
A13: 12 | B13: HCFM-0513 | C13: MR.SAJJAD ALI | D13: 45992 | E13: 0 | F13: 0 | G13: 7000 | H13: =SUM(I13:T13) -> 119581 | I13: =SUMIFS(FACILITIES!T:T,FACILITIES!B:B,B13) -> 0 | J13: 0 | K13: 0 | L13: 0 | M13: - | N13: 0 | O13: =SUMIFS('F & B'!G:G,'F & B'!B:B,B13) -> 23647 | P13: 26185 | Q13: 38396 | R13: 2000 | S13: 23603 | T13: 5750 | U13: 60000 | V13: =IF(U13-H13>0, U13-H13, "")
... A102: 101 | B102: HCFM-0666 | C102: MR FAHAD MUMTAZ | D102: 45992 | E102: 0 | F102: 0 | G102: 7000 | H102: =SUM(I102:T102) -> 24635 | I102: =SUMIFS(FACILITIES!T:T,FACILITIES!B:B,B102) -> 0 | J102: 0 | K102: 0 | L102: 0 | M102: - | N102: 0 | O102: =SUMIFS('F & B'!G:G,'F & B'!B:B,B102) -> 0 | P102: 0 | Q102: 14635 | R102: 10000 | S102: 0 | T102: 0 | U102: 10000 | V102: =IF(U102-H102>0, U102-H102, "")
A103: 102 | B103: HCFM-0667 | C103: =VLOOKUP(B103,MEMBERS!B:C,2, ) -> MR. FAYAZ ALI SOOMRO | D103: 45992 | E103: 0 | F103: 0 | G103: 7000 | H103: =SUM(I103:T103) -> 77300 | I103: =SUMIFS(FACILITIES!T:T,FACILITIES!B:B,B103) -> 0 | J103: 0 | K103: 0 | L103: 0 | M103: - | N103: 0 | O103: =SUMIFS('F & B'!G:G,'F & B'!B:B,B103) -> 8949 | P103: 38005 | Q103: 19799 | R103: 9350 | S103: 1197 | T103: 0 | U103: 60000 | V103: =IF(U103-H103>0, U103-H103, "")
A104: 103 | B104: HCFM-0668 | C104: =VLOOKUP(B104,MEMBERS!B:C,2, ) -> MR. KASHIF SAEED | D104: 45992 | E104: 0 | F104: 0 | G104: 7000 | H104: =SUM(I104:T104) -> 84098 | I104: =SUMIFS(FACILITIES!T:T,FACILITIES!B:B,B104) -> 0 | J104: 0 | K104: 0 | L104: 0 | M104: - | N104: 0 | O104: =SUMIFS('F & B'!G:G,'F & B'!B:B,B104) -> 26400 | P104: 0 | Q104: 9300 | R104: 18420 | S104: 19888 | T104: 10090 | U104: 60000 | V104: =IF(U104-H104>0, U104-H104, "")
A105: 104 | B105: HCFM-0669 | C105: =VLOOKUP(B105,MEMBERS!B:C,2, ) -> MR . SYED RAHAT HUSSAIN ZAIDI | D105: 45992 | E105: 0 | F105: 0 | G105: 7000 | H105: =SUM(I105:T105) -> 82810 | I105: =SUMIFS(FACILITIES!T:T,FACILITIES!B:B,B105) -> 0 | J105: 0 | K105: 0 | L105: 0 | M105: - | N105: 0 | O105: =SUMIFS('F & B'!G:G,'F & B'!B:B,B105) -> 63250 | P105: 5200 | Q105: 6100 | R105: 8260 | S105: 0 | T105: 0 | U105: 60000 | V105: =IF(U105-H105>0, U105-H105, "")
A106: 105 | B106: HCFM-0670 | C106: =VLOOKUP(B106,MEMBERS!B:C,2, ) -> MR. TEHSEEN FAIZ | D106: 45992 | E106: 0 | F106: 0 | G106: 7000 | H106: =SUM(I106:T106) -> 37394 | I106: =SUMIFS(FACILITIES!T:T,FACILITIES!B:B,B106) -> 0 | J106: 0 | K106: 0 | L106: 0 | M106: - | N106: 0 | O106: =SUMIFS('F & B'!G:G,'F & B'!B:B,B106) -> 17379 | P106: 0 | Q106: 10420 | R106: 5405 | S106: 4090 | T106: 100 | U106: 60000 | V106: =IF(U106-H106>0, U106-H106, "") -> 22606
A107: 106 | B107: HCFM-0671 | C107: =VLOOKUP(B107,MEMBERS!B:C,2, ) -> MRS. HASSAN RAFI | D107: 45992 | E107: 0 | F107: 0 | G107: 0 | H107: =SUM(I107:T107) -> 0 | I107: =SUMIFS(FACILITIES!T:T,FACILITIES!B:B,B107) -> 0 | J107: 0 | K107: 0 | L107: 0 | M107: - | N107: 0 | O107: =SUMIFS('F & B'!G:G,'F & B'!B:B,B107) -> 0 | P107: 0 | Q107: 0 | R107: 0 | S107: 0 | T107: 0 | U107: 0 | V107: =IF(U107-H107>0, U107-H107, "")
A108: 107 | B108: HCFM-0672 | C108: MRS RIFFAT ZULFIQAR | D108: 45992 | E108: 0 | F108: 0 | G108: 7000 | H108: =SUM(I108:T108) -> 111805 | I108: =SUMIFS(FACILITIES!T:T,FACILITIES!B:B,B108) -> 40000 | J108: 0 | K108: 0 | L108: 0 | M108: - | N108: 0 | O108: =SUMIFS('F & B'!G:G,'F & B'!B:B,B108) -> 38280 | P108: 7360 | Q108: 22965 | R108: 0 | S108: 3200 | T108: 0 | U108: 60000 | V108: =IF(U108-H108>0, U108-H108, "")
A109: 108 | B109: HCFM-0673 | C109: MR. AKSHAY RAJ | D109: 45992 | E109: 0 | F109: 0 | G109: 7000 | H109: =SUM(I109:T109) -> 4550 | I109: =SUMIFS(FACILITIES!T:T,FACILITIES!B:B,B109) -> 0 | J109: 0 | K109: 0 | L109: 0 | M109: - | N109: 0 | O109: =SUMIFS('F & B'!G:G,'F & B'!B:B,B109) -> 4550 | P109: 0 | Q109: 0 | R109: 0 | S109: 0 | T109: 0 | U109: 60000 | V109: =IF(U109-H109>0, U109-H109, "") -> 55450
A110: 109 | B110: HCFM-0674 | C110: MR. RAJESH KUMAR CHAWLA | D110: 45992 | E110: 0 | F110: 0 | G110: 7000 | H110: =SUM(I110:T110) -> 46429 | I110: =SUMIFS(FACILITIES!T:T,FACILITIES!B:B,B110) -> 0 | J110: 0 | K110: 0 | L110: 0 | M110: - | N110: 2000 | O110: =SUMIFS('F & B'!G:G,'F & B'!B:B,B110) -> 1200 | P110: 5550 | Q110: 6949 | R110: 12230 | S110: 11450 | T110: 7050 | U110: 60000 | V110: =IF(U110-H110>0, U110-H110, "") -> 13571
A111: 110 | B111: HCFM-0676 | C111: MR. SAMEER MALIK | D111: 45992 | E111: 0 | F111: 0 | G111: 7000 | H111: =SUM(I111:T111) -> 0 | I111: =SUMIFS(FACILITIES!T:T,FACILITIES!B:B,B111) -> 0 | J111: 0 | K111: 0 | L111: 0 | M111: - | N111: 0 | O111: =SUMIFS('F & B'!G:G,'F & B'!B:B,B111) -> 0 | P111: 0 | Q111: 0 | R111: 0 | S111: 0 | T111: 0 | U111: 60000 | V111: =IF(U111-H111>0, U111-H111, "") -> 60000
A112: 111 | B112: HCFM-0677 | C112: MR. MUNAWAR HUSSAIN | D112: 45992 | E112: 0 | F112: 0 | G112: 7000 | H112: =SUM(I112:T112) -> 98751 | I112: =SUMIFS(FACILITIES!T:T,FACILITIES!B:B,B112) -> 0 | J112: 0 | K112: 0 | L112: 0 | M112: - | N112: 0 | O112: =SUMIFS('F & B'!G:G,'F & B'!B:B,B112) -> 10350 | P112: 0 | Q112: 24049 | R112: 33587 | S112: 6475 | T112: 24290 | U112: 60000 | V112: =IF(U112-H112>0, U112-H112, "")
A113: 112 | B113: HCFM-0678 | C113: MR. AIJAZ ALI BALOCH | D113: 45992 | E113: 0 | F113: 0 | G113: 7000 | H113: =SUM(I113:T113) -> 124615 | I113: =SUMIFS(FACILITIES!T:T,FACILITIES!B:B,B113) -> 0 | J113: 0 | K113: 0 | L113: 0 | M113: - | N113: 0 | O113: =SUMIFS('F & B'!G:G,'F & B'!B:B,B113) -> 51687 | P113: 0 | Q113: 8550 | R113: 21099 | S113: 10319 | T113: 32960 | U113: 60000 | V113: =IF(U113-H113>0, U113-H113, "")
A114: 113 | B114: HCFM-0679 | C114: MR. ANEEL ZAHOOR | D114: 45992 | E114: 0 | F114: 0 | G114: 7000 | H114: =SUM(I114:T114) -> 74954 | I114: =SUMIFS(FACILITIES!T:T,FACILITIES!B:B,B114) -> 0 | J114: 0 | K114: 0 | L114: 0 | M114: - | N114: 0 | O114: =SUMIFS('F & B'!G:G,'F & B'!B:B,B114) -> 21629 | P114: 0 | Q114: 6315 | R114: 26750 | S114: 14310 | T114: 5950 | U114: 60000 | V114: =IF(U114-H114>0, U114-H114, "")
A115: 114 | B115: HCFM-0680 | C115: MR. AYAZ JAMRO | D115: 45992 | E115: 0 | F115: 0 | G115: 7000 | H115: =SUM(I115:T115) -> 99805 | I115: =SUMIFS(FACILITIES!T:T,FACILITIES!B:B,B115) -> 7000 | J115: 0 | K115: 0 | L115: 0 | M115: - | N115: 0 | O115: =SUMIFS('F & B'!G:G,'F & B'!B:B,B115) -> 5770 | P115: 0 | Q115: 20220 | R115: 28490 | S115: 21785 | T115: 16540 | U115: 60000 | V115: =IF(U115-H115>0, U115-H115, "")
A116: 115 | B116: HCFM-0681 | C116: BAHRIA ADVENTURE LAND | D116: 45992 | E116: 0 | F116: 0 | G116: 0 | H116: =SUM(I116:T116) -> 26500 | I116: =SUMIFS(FACILITIES!T:T,FACILITIES!B:B,B116) -> 0 | J116: 0 | K116: 0 | L116: 0 | M116: - | N116: 0 | O116: =SUMIFS('F & B'!G:G,'F & B'!B:B,B116) -> 0 | P116: 0 | Q116: 14400 | R116: 1300 | S116: 2600 | T116: 8200 | U116: 0 | V116: =IF(U116-H116>0, U116-H116, "")
A117: 116 | B117: HCFM-0682 | C117: MR. ZAHIR REHMAN | D117: 45992 | E117: 0 | F117: 0 | G117: 7000 | H117: =SUM(I117:T117) -> 91370 | I117: =SUMIFS(FACILITIES!T:T,FACILITIES!B:B,B117) -> 0 | J117: 0 | K117: 0 | L117: 0 | M117: - | N117: 0 | O117: =SUMIFS('F & B'!G:G,'F & B'!B:B,B117) -> 24300 | P117: 0 | Q117: 0 | R117: 28550 | S117: 17070 | T117: 21450 | U117: 60000 | V117: =IF(U117-H117>0, U117-H117, "")
A118: 117 | B118: HCFM-0683 | C118: MR. YASIR RASHEED | D118: 45992 | E118: 0 | F118: 0 | G118: 7000 | H118: =SUM(I118:T118) -> 238726 | I118: =SUMIFS(FACILITIES!T:T,FACILITIES!B:B,B118) -> 0 | J118: 0 | K118: 0 | L118: 0 | M118: - | N118: 4500 | O118: =SUMIFS('F & B'!G:G,'F & B'!B:B,B118) -> 4650 | P118: 0 | Q118: 0 | R118: 70445 | S118: 134302 | T118: 24829 | U118: 60000 | V118: =IF(U118-H118>0, U118-H118, "")
A119: 118 | B119: HCFM-0684 | C119: MR. ZAMIR ALI SHAH | D119: 45992 | E119: 0 | F119: 0 | G119: 7000 | H119: =SUM(I119:T119) -> 467674 | I119: =SUMIFS(FACILITIES!T:T,FACILITIES!B:B,B119) -> 0 | J119: 0 | K119: 0 | L119: 0 | M119: - | N119: 3000 | O119: =SUMIFS('F & B'!G:G,'F & B'!B:B,B119) -> 84916 | P119: 0 | Q119: 0 | R119: 15798 | S119: 168250 | T119: 195710 | U119: 60000 | V119: =IF(U119-H119>0, U119-H119, "")
... A122: 121 | B122: HCFM-0687 | C122: MR. IKRAMULLAH | D122: 45992 | E122: 0 | F122: 0 | G122: 7000 | H122: =SUM(I122:T122) -> 44850 | I122: =SUMIFS(FACILITIES!T:T,FACILITIES!B:B,B122) -> 0 | J122: 0 | K122: 0 | L122: 0 | M122: - | N122: 0 | O122: =SUMIFS('F & B'!G:G,'F & B'!B:B,B122) -> 0 | P122: 0 | Q122: 0 | R122: 0 | S122: 11050 | T122: 33800 | U122: 30000 | V122: =IF(U122-H122>0, U122-H122, "")
E123: =SUM(E2:E116) -> 0 | F123: 0 | G123: =SUM(G2:G122) -> 819000 | H123: =SUM(I123:T123) -> 16360738 | I123: =SUM(I2:I122) -> 508000 | J123: =SUM(J2:J122) -> 0 | K123: =SUM(K2:K122) -> 931000 | L123: =SUM(L2:L122) -> 637615 | M123: =SUM(M2:M122) -> 0 | N123: =SUM(N2:N122) -> 1001660 | O123: =SUM(O2:O122) -> 5370466 | P123: =SUM(P2:P122) -> 1638831.7 | ... S123: =SUM(S2:S122) -> 1756337 | T123: 0 | U123: =SUM(U2:U122) -> 6940000 | V123: =SUMIFS(V2:V122, V2:V122, ">0",V2:V122, "<=60000") -> 1153996
V124: =SUMIF(V2:V122, "<0") -> 0

Sheet FACILITIES
A1: S.no | B1: Membership number | C1: Name | D1: Date | E1: Bowling Alley | F1: Gym | G1: Family Pool | H1: Squash Court | I1: Ladies Pool | J1: Amusement Arcade | K1: Cinema | L1: Cigar Lounge | M1: Pool Lockers | N1: SPA | O1: Padel Court | P1: Ladies Saloon | Q1: HC Chambers | R1: Gym Sub | S1: Vanue Charges | T1: PARTY CHARGES | U1: TOTAL
A2: =IF(D2<>"", ROW()-1, "") -> 1 | B2: HCFM-0684 | C2: =VLOOKUP(B2,MEMBERS!B:C,2, ) -> MR. ZAMIR ALI SHAH | D2: 45992 | E2: =600*3 -> 1800 | F2: 0 | G2: 0 | H2: 0 | I2: 0 | J2: 0 | K2: 0 | L2: 0 | M2: 0 | N2: 0 | O2: 0 | P2: 0 | Q2: 0 | R2: 0 | S2: 0 | T2: 0 | U2: =SUM(E2:T2) -> 1800
A3: =IF(D3<>"", ROW()-1, "") -> 2 | B3: HCFM-0526 | C3: =VLOOKUP(B3,MEMBERS!B:C,2, ) -> MR.MUIED AHMED DURRANI | D3: 45992 | E3: 0 | F3: 0 | G3: 0 | H3: 0 | I3: 0 | J3: 300 | K3: 0 | L3: 0 | M3: 0 | N3: 0 | O3: 0 | P3: 0 | Q3: 0 | R3: 0 | S3: 0 | T3: 0 | U3: =SUM(E3:T3) -> 300
A4: =IF(D4<>"", ROW()-1, "") -> 3 | B4: HCFM-0515 | C4: =VLOOKUP(B4,MEMBERS!B:C,2, ) -> MR.TARIQUE ZUBAIR | D4: 45992 | E4: 0 | F4: 150 | G4: 0 | H4: 0 | I4: 0 | J4: 0 | K4: 0 | L4: 0 | M4: 0 | N4: 0 | O4: 0 | P4: 0 | Q4: 0 | R4: 0 | S4: 0 | T4: 0 | U4: =SUM(E4:T4) -> 150
A5: =IF(D5<>"", ROW()-1, "") -> 4 | B5: HCFM-0597 | C5: =VLOOKUP(B5,MEMBERS!B:C,2, ) -> GM GHULAM DASTAGEER | D5: 45992 | E5: 0 | F5: 150 | G5: 0 | H5: 0 | I5: 0 | J5: 0 | K5: 0 | L5: 0 | M5: 0 | N5: 0 | O5: 0 | P5: 0 | Q5: 0 | R5: 0 | S5: 0 | T5: 0 | U5: =SUM(E5:T5) -> 150
A6: =IF(D6<>"", ROW()-1, "") -> 5 | B6: HCFM-0512 | C6: =VLOOKUP(B6,MEMBERS!B:C,2, ) -> MR.ZEESHAN IQBAL | D6: 45992 | E6: 0 | F6: =150+300 -> 450 | G6: 0 | H6: 0 | I6: 0 | J6: 0 | K6: 0 | L6: 0 | M6: 0 | N6: 0 | O6: 0 | P6: 0 | Q6: 0 | R6: 0 | S6: 0 | T6: 0 | U6: =SUM(E6:T6) -> 450
A7: =IF(D7<>"", ROW()-1, "") -> 6 | B7: HCFM-0548 | C7: =VLOOKUP(B7,MEMBERS!B:C,2, ) -> MR.ZAIN FAROOQ | D7: 45992 | E7: 0 | F7: =150*2 -> 300 | G7: 0 | H7: 0 | I7: 0 | J7: 0 | K7: 0 | L7: 0 | M7: 0 | N7: 0 | O7: 0 | P7: 0 | Q7: 0 | R7: 0 | S7: 0 | T7: 0 | U7: =SUM(E7:T7) -> 300
A8: =IF(D8<>"", ROW()-1, "") -> 7 | B8: HCFM-0609 | C8: =VLOOKUP(B8,MEMBERS!B:C,2, ) -> DR.NASEEM MUNSHI | D8: 45992 | E8: 0 | F8: 150 | G8: 0 | H8: 0 | I8: 0 | J8: 0 | K8: 0 | L8: 0 | M8: 0 | N8: 0 | O8: 0 | P8: 0 | Q8: 0 | R8: 0 | S8: 0 | T8: 0 | U8: =SUM(E8:T8) -> 150
A9: =IF(D9<>"", ROW()-1, "") -> 8 | B9: HCFM-0586 | C9: =VLOOKUP(B9,MEMBERS!B:C,2, ) -> MR.SYED MURTAZA ALI | D9: 45993 | E9: 0 | F9: 0 | G9: 150 | H9: 0 | I9: 0 | J9: 0 | K9: 0 | L9: 0 | M9: 0 | N9: 0 | O9: 0 | P9: 0 | Q9: 0 | R9: 0 | S9: 0 | T9: 0 | U9: =SUM(E9:T9) -> 150
A10: =IF(D10<>"", ROW()-1, "") -> 9 | B10: HCFM-0596 | C10: =VLOOKUP(B10,MEMBERS!B:C,2, ) -> DGM AZFAR ALI | D10: 45993 | E10: =600*2 -> 1200 | F10: 0 | G10: 0 | H10: 0 | I10: 0 | J10: 0 | K10: 0 | L10: 0 | M10: 0 | N10: 0 | O10: 0 | P10: 0 | Q10: 0 | R10: 0 | S10: 0 | T10: 0 | U10: =SUM(E10:T10) -> 1200
A11: =IF(D11<>"", ROW()-1, "") -> 10 | B11: HCFM-0515 | C11: =VLOOKUP(B11,MEMBERS!B:C,2, ) -> MR.TARIQUE ZUBAIR | D11: 45993 | E11: 0 | F11: 150 | G11: 0 | H11: 0 | I11: 0 | J11: 0 | K11: 0 | L11: 0 | M11: 0 | N11: 0 | O11: 0 | P11: 0 | Q11: 0 | R11: 0 | S11: 0 | T11: 0 | U11: =SUM(E11:T11) -> 150
A12: =IF(D12<>"", ROW()-1, "") -> 11 | B12: HCFM-0597 | C12: =VLOOKUP(B12,MEMBERS!B:C,2, ) -> GM GHULAM DASTAGEER | D12: 45993 | E12: 0 | F12: 150 | G12: 0 | H12: 0 | I12: 0 | J12: 0 | K12: 0 | L12: 0 | M12: 0 | N12: 0 | O12: 0 | P12: 0 | Q12: 0 | R12: 0 | S12: 0 | T12: 0 | U12: =SUM(E12:T12) -> 150
A13: =IF(D13<>"", ROW()-1, "") -> 12 | B13: HCFM-0512 | C13: =VLOOKUP(B13,MEMBERS!B:C,2, ) -> MR.ZEESHAN IQBAL | D13: 45993 | E13: 0 | F13: =150*2+300 -> 600 | G13: 0 | H13: 0 | I13: 0 | J13: 0 | K13: 0 | L13: 0 | M13: 0 | N13: 0 | O13: 0 | P13: 0 | Q13: 0 | R13: 0 | S13: 0 | T13: 0 | U13: =SUM(E13:T13) -> 600
A14: =IF(D14<>"", ROW()-1, "") -> 13 | B14: HCFM-0664 | C14: =VLOOKUP(B14,MEMBERS!B:C,2, ) -> SHAHBAZ AHMED | D14: 45993 | E14: 0 | F14: =150*2 -> 300 | G14: 0 | H14: 0 | I14: 0 | J14: 0 | K14: 0 | L14: 0 | M14: 0 | N14: 0 | O14: 0 | P14: 0 | Q14: 0 | R14: 0 | S14: 0 | T14: 0 | U14: =SUM(E14:T14) -> 300
A15: =IF(D15<>"", ROW()-1, "") -> 14 | B15: HCFM-0642 | C15: =VLOOKUP(B15,MEMBERS!B:C,2, ) -> ASIF ASHFAQ | D15: 45993 | E15: 0 | F15: =150*2 -> 300 | G15: 0 | H15: 0 | I15: 0 | J15: 0 | K15: 0 | L15: 0 | M15: 0 | N15: 0 | O15: 0 | P15: 0 | Q15: 0 | R15: 0 | S15: 0 | T15: 0 | U15: =SUM(E15:T15) -> 300
A16: =IF(D16<>"", ROW()-1, "") -> 15 | B16: HCFM-0657 | C16: =VLOOKUP(B16,MEMBERS!B:C,2, ) -> NASIR ABBAS | D16: 45993 | E16: 0 | F16: 150 | G16: 0 | H16: 0 | I16: 0 | J16: 0 | K16: 0 | L16: 0 | M16: 0 | N16: 0 | O16: 0 | P16: 0 | Q16: 0 | R16: 0 | S16: 0 | T16: 0 | U16: =SUM(E16:T16) -> 150
A17: =IF(D17<>"", ROW()-1, "") -> 16 | B17: HCFM-0548 | C17: =VLOOKUP(B17,MEMBERS!B:C,2, ) -> MR.ZAIN FAROOQ | D17: 45993 | E17: 0 | F17: 150 | G17: 0 | H17: 0 | I17: 0 | J17: 0 | K17: 0 | L17: 0 | M17: 0 | N17: 0 | O17: 0 | P17: 0 | Q17: 0 | R17: 0 | S17: 0 | T17: 0 | U17: =SUM(E17:T17) -> 150
A18: =IF(D18<>"", ROW()-1, "") -> 17 | B18: HCFM-0609 | C18: =VLOOKUP(B18,MEMBERS!B:C,2, ) -> DR.NASEEM MUNSHI | D18: 45993 | E18: 0 | F18: 150 | G18: 0 | H18: 0 | I18: 0 | J18: 0 | K18: 0 | L18: 0 | M18: 0 | N18: 0 | O18: 0 | P18: 0 | Q18: 0 | R18: 0 | S18: 0 | T18: 0 | U18: =SUM(E18:T18) -> 150
A19: =IF(D19<>"", ROW()-1, "") -> 18 | B19: HCFM-0534 | C19: =VLOOKUP(B19,MEMBERS!B:C,2, ) -> MR.PIR MUJEEB JAN SARHANDI | D19: 45993 | E19: 0 | F19: =150*2 -> 300 | G19: 0 | H19: 0 | I19: 0 | J19: 0 | K19: 0 | L19: 0 | M19: 0 | N19: 0 | O19: 0 | P19: 0 | Q19: 0 | R19: 0 | S19: 0 | T19: 0 | U19: =SUM(E19:T19) -> 300
A20: =IF(D20<>"", ROW()-1, "") -> 19 | B20: HCFM-0502 | C20: =VLOOKUP(B20,MEMBERS!B:C,2, ) -> MR. JABIR SHAHZAD | D20: 45993 | E20: 0 | F20: 150 | G20: 0 | H20: 0 | I20: 0 | J20: 0 | K20: 0 | L20: 0 | M20: 0 | N20: 0 | O20: 0 | P20: 0 | Q20: 0 | R20: 0 | S20: 0 | T20: 0 | U20: =SUM(E20:T20) -> 150
A21: =IF(D21<>"", ROW()-1, "") -> 20 | B21: HCFM-0509 | C21: =VLOOKUP(B21,MEMBERS!B:C,2, ) -> MR.SYED ABDULLAH ALI | D21: 45993 | E21: 0 | F21: 150 | G21: 0 | H21: 0 | I21: 0 | J21: 0 | K21: 0 | L21: 0 | M21: 0 | N21: 0 | O21: 0 | P21: 0 | Q21: 0 | R21: 0 | S21: 0 | T21: 0 | U21: =SUM(E21:T21) -> 150
A22: =IF(D22<>"", ROW()-1, "") -> 21 | B22: HCFM-0543 | C22: =VLOOKUP(B22,MEMBERS!B:C,2, ) -> MR.MUHAMMAD ATIF USMANI | D22: 45993 | E22: 0 | F22: 150 | G22: 0 | H22: 0 | I22: 0 | J22: 0 | K22: 0 | L22: 0 | M22: 0 | N22: 0 | O22: 0 | P22: 0 | Q22: 0 | R22: 0 | S22: 0 | T22: 0 | U22: =SUM(E22:T22) -> 150
A23: =IF(D23<>"", ROW()-1, "") -> 22 | B23: HCFM-0526 | C23: =VLOOKUP(B23,MEMBERS!B:C,2, ) -> MR.MUIED AHMED DURRANI | D23: 45993 | E23: 0 | F23: 0 | G23: 0 | H23: 0 | I23: 0 | J23: 300 | K23: 0 | L23: 0 | M23: 0 | N23: 0 | O23: 0 | P23: 0 | Q23: 0 | R23: 0 | S23: 0 | T23: 0 | U23: =SUM(E23:T23) -> 300
A24: =IF(D24<>"", ROW()-1, "") -> 23 | B24: HCFM-0524 | C24: =VLOOKUP(B24,MEMBERS!B:C,2, ) -> MR.MANOJ KUMAR | D24: 45993 | E24: 0 | F24: 0 | G24: 0 | H24: 0 | I24: 0 | J24: 300 | K24: 0 | L24: 0 | M24: 0 | N24: 0 | O24: 0 | P24: 0 | Q24: 0 | R24: 0 | S24: 0 | T24: 0 | U24: =SUM(E24:T24) -> 300
A25: =IF(D25<>"", ROW()-1, "") -> 24 | B25: HCFM-0644 | C25: =VLOOKUP(B25,MEMBERS!B:C,2, ) -> SABA AHSAN | D25: 45994 | E25: 0 | F25: 0 | G25: 0 | H25: 0 | I25: 0 | J25: 0 | K25: 0 | L25: 0 | M25: 0 | N25: 0 | O25: 0 | P25: 5000 | Q25: 0 | R25: 0 | S25: 0 | T25: 0 | U25: =SUM(E25:T25) -> 5000
A26: =IF(D26<>"", ROW()-1, "") -> 25 | B26: HCFM-0648 | C26: =VLOOKUP(B26,MEMBERS!B:C,2, ) -> AYSM MIRZA | D26: 45994 | E26: 0 | F26: 150 | G26: 0 | H26: 0 | I26: 0 | J26: 0 | K26: 0 | L26: 0 | M26: 0 | N26: 0 | O26: 0 | P26: 0 | Q26: 0 | R26: 0 | S26: 0 | T26: 0 | U26: =SUM(E26:T26) -> 150
A27: =IF(D27<>"", ROW()-1, "") -> 26 | B27: HCFM-0597 | C27: =VLOOKUP(B27,MEMBERS!B:C,2, ) -> GM GHULAM DASTAGEER | D27: 45994 | E27: 0 | F27: 150 | G27: 0 | H27: 0 | I27: 0 | J27: 0 | K27: 0 | L27: 0 | M27: 0 | N27: 0 | O27: 0 | P27: 0 | Q27: 0 | R27: 0 | S27: 0 | T27: 0 | U27: =SUM(E27:T27) -> 150
A28: =IF(D28<>"", ROW()-1, "") -> 27 | B28: HCFM-0515 | C28: =VLOOKUP(B28,MEMBERS!B:C,2, ) -> MR.TARIQUE ZUBAIR | D28: 45994 | E28: 0 | F28: 150 | G28: 0 | H28: 0 | I28: 0 | J28: 0 | K28: 0 | L28: 0 | M28: 0 | N28: 0 | O28: 0 | P28: 0 | Q28: 0 | R28: 0 | S28: 0 | T28: 0 | U28: =SUM(E28:T28) -> 150
A29: =IF(D29<>"", ROW()-1, "") -> 28 | B29: HCFM-0518 | C29: =VLOOKUP(B29,MEMBERS!B:C,2, ) -> DR.SANTOSH KUMAR | D29: 45994 | E29: 0 | F29: 150 | G29: 0 | H29: 0 | I29: 0 | J29: 0 | K29: 0 | L29: 0 | M29: 0 | N29: 0 | O29: 0 | P29: 0 | Q29: 0 | R29: 0 | S29: 0 | T29: 0 | U29: =SUM(E29:T29) -> 150
A30: =IF(D30<>"", ROW()-1, "") -> 29 | B30: HCFM-0512 | C30: =VLOOKUP(B30,MEMBERS!B:C,2, ) -> MR.ZEESHAN IQBAL | D30: 45994 | E30: 0 | F30: =150*2+300 -> 600 | G30: 0 | H30: 0 | I30: 0 | J30: 0 | K30: 0 | L30: 0 | M30: 0 | N30: 0 | O30: 0 | P30: 0 | Q30: 0 | R30: 0 | S30: 0 | T30: 0 | U30: =SUM(E30:T30) -> 600
A31: =IF(D31<>"", ROW()-1, "") -> 30 | B31: HCFM-0664 | C31: =VLOOKUP(B31,MEMBERS!B:C,2, ) -> SHAHBAZ AHMED | D31: 45994 | E31: 0 | F31: 300 | G31: 0 | H31: 0 | I31: 0 | J31: 0 | K31: 0 | L31: 0 | M31: 0 | N31: 0 | O31: 0 | P31: 0 | Q31: 0 | R31: 0 | S31: 0 | T31: 0 | U31: =SUM(E31:T31) -> 300
A32: =IF(D32<>"", ROW()-1, "") -> 31 | B32: HCFM-0642 | C32: =VLOOKUP(B32,MEMBERS!B:C,2, ) -> ASIF ASHFAQ | D32: 45994 | E32: 0 | F32: =150*2 -> 300 | G32: 0 | H32: 0 | I32: 0 | J32: 0 | K32: 0 | L32: 0 | M32: 0 | N32: 0 | O32: 0 | P32: 0 | Q32: 0 | R32: 0 | S32: 0 | T32: 0 | U32: =SUM(E32:T32) -> 300
A33: =IF(D33<>"", ROW()-1, "") -> 32 | B33: HCFM-0548 | C33: =VLOOKUP(B33,MEMBERS!B:C,2, ) -> MR.ZAIN FAROOQ | D33: 45994 | E33: 0 | F33: =150*2 -> 300 | G33: 0 | H33: 0 | I33: 0 | J33: 0 | K33: 0 | L33: 0 | M33: 0 | N33: 0 | O33: 0 | P33: 0 | Q33: 0 | R33: 0 | S33: 0 | T33: 0 | U33: =SUM(E33:T33) -> 300
A34: =IF(D34<>"", ROW()-1, "") -> 33 | B34: HCFM-0543 | C34: =VLOOKUP(B34,MEMBERS!B:C,2, ) -> MR.MUHAMMAD ATIF USMANI | D34: 45994 | E34: 0 | F34: 150 | G34: 0 | H34: 0 | I34: 0 | J34: 0 | K34: 0 | L34: 0 | M34: 0 | N34: 0 | O34: 0 | P34: 0 | Q34: 0 | R34: 0 | S34: 0 | T34: 0 | U34: =SUM(E34:T34) -> 150
A35: =IF(D35<>"", ROW()-1, "") -> 34 | B35: HCFM-0684 | C35: =VLOOKUP(B35,MEMBERS!B:C,2, ) -> MR. ZAMIR ALI SHAH | D35: 45995 | E35: 0 | F35: 0 | G35: 0 | H35: 0 | I35: 0 | J35: 0 | K35: 0 | L35: 0 | M35: 0 | N35: 0 | O35: 0 | P35: 16000 | Q35: 0 | R35: 0 | S35: 0 | T35: 0 | U35: =SUM(E35:T35) -> 16000
A36: =IF(D36<>"", ROW()-1, "") -> 35 | B36: HCFM-0515 | C36: =VLOOKUP(B36,MEMBERS!B:C,2, ) -> MR.TARIQUE ZUBAIR | D36: 45995 | E36: 0 | F36: 150 | G36: 0 | H36: 0 | I36: 0 | J36: 0 | K36: 0 | L36: 0 | M36: 0 | N36: 0 | O36: 0 | P36: 0 | Q36: 0 | R36: 0 | S36: 0 | T36: 0 | U36: =SUM(E36:T36) -> 150
A37: =IF(D37<>"", ROW()-1, "") -> 36 | B37: HCFM-0597 | C37: =VLOOKUP(B37,MEMBERS!B:C,2, ) -> GM GHULAM DASTAGEER | D37: 45995 | E37: 0 | F37: 150 | G37: 0 | H37: 0 | I37: 0 | J37: 0 | K37: 0 | L37: 0 | M37: 0 | N37: 0 | O37: 0 | P37: 0 | Q37: 0 | R37: 0 | S37: 0 | T37: 0 | U37: =SUM(E37:T37) -> 150
A38: =IF(D38<>"", ROW()-1, "") -> 37 | B38: HCFM-0518 | C38: =VLOOKUP(B38,MEMBERS!B:C,2, ) -> DR.SANTOSH KUMAR | D38: 45995 | E38: 0 | F38: 150 | G38: 0 | H38: 0 | I38: 0 | J38: 0 | K38: 0 | L38: 0 | M38: 0 | N38: 0 | O38: 0 | P38: 0 | Q38: 0 | R38: 0 | S38: 0 | T38: 0 | U38: =SUM(E38:T38) -> 150
A39: =IF(D39<>"", ROW()-1, "") -> 38 | B39: HCFM-0664 | C39: =VLOOKUP(B39,MEMBERS!B:C,2, ) -> SHAHBAZ AHMED | D39: 45995 | E39: 0 | F39: 300 | G39: 0 | H39: 0 | I39: 0 | J39: 0 | K39: 0 | L39: 0 | M39: 0 | N39: 0 | O39: 0 | P39: 0 | Q39: 0 | R39: 0 | S39: 0 | T39: 0 | U39: =SUM(E39:T39) -> 300
A40: =IF(D40<>"", ROW()-1, "") -> 39 | B40: HCFM-0648 | C40: =VLOOKUP(B40,MEMBERS!B:C,2, ) -> AYSM MIRZA | D40: 45995 | E40: 0 | F40: 150 | G40: 0 | H40: 0 | I40: 0 | J40: 0 | K40: 0 | L40: 0 | M40: 0 | N40: 0 | O40: 0 | P40: 0 | Q40: 0 | R40: 0 | S40: 0 | T40: 0 | U40: =SUM(E40:T40) -> 150
A41: =IF(D41<>"", ROW()-1, "") -> 40 | B41: HCFM-0548 | C41: =VLOOKUP(B41,MEMBERS!B:C,2, ) -> MR.ZAIN FAROOQ | D41: 45995 | E41: 0 | F41: 150 | G41: 0 | H41: 0 | I41: 0 | J41: 0 | K41: 0 | L41: 0 | M41: 0 | N41: 0 | O41: 0 | P41: 0 | Q41: 0 | R41: 0 | S41: 0 | T41: 0 | U41: =SUM(E41:T41) -> 150
A42: =IF(D42<>"", ROW()-1, "") -> 41 | B42: HCFM-0657 | C42: =VLOOKUP(B42,MEMBERS!B:C,2, ) -> NASIR ABBAS | D42: 45995 | E42: 0 | F42: 150 | G42: 0 | H42: 0 | I42: 0 | J42: 0 | K42: 0 | L42: 0 | M42: 0 | N42: 0 | O42: 0 | P42: 0 | Q42: 0 | R42: 0 | S42: 0 | T42: 0 | U42: =SUM(E42:T42) -> 150
A43: =IF(D43<>"", ROW()-1, "") -> 42 | B43: HCFM-0543 | C43: =VLOOKUP(B43,MEMBERS!B:C,2, ) -> MR.MUHAMMAD ATIF USMANI | D43: 45995 | E43: 0 | F43: 150 | G43: 0 | H43: 0 | I43: 0 | J43: 0 | K43: 0 | L43: 0 | M43: 0 | N43: 0 | O43: 0 | P43: 0 | Q43: 0 | R43: 0 | S43: 0 | T43: 0 | U43: =SUM(E43:T43) -> 150
A44: =IF(D44<>"", ROW()-1, "") -> 43 | B44: HCFM-0534 | C44: =VLOOKUP(B44,MEMBERS!B:C,2, ) -> MR.PIR MUJEEB JAN SARHANDI | D44: 45995 | E44: 0 | F44: 150 | G44: 0 | H44: 0 | I44: 0 | J44: 0 | K44: 0 | L44: 0 | M44: 0 | N44: 0 | O44: 0 | P44: 0 | Q44: 0 | R44: 0 | S44: 0 | T44: 0 | U44: =SUM(E44:T44) -> 150
A45: =IF(D45<>"", ROW()-1, "") -> 44 | B45: HCFM-0512 | C45: =VLOOKUP(B45,MEMBERS!B:C,2, ) -> MR.ZEESHAN IQBAL | D45: 45995 | E45: 0 | F45: 150 | G45: 0 | H45: 0 | I45: 0 | J45: 0 | K45: 0 | L45: 0 | M45: 0 | N45: 0 | O45: 0 | P45: 0 | Q45: 0 | R45: 0 | S45: 0 | T45: 0 | U45: =SUM(E45:T45) -> 150
... A47: =IF(D47<>"", ROW()-1, "") -> 46 | B47: HCFM-0502 | C47: =VLOOKUP(B47,MEMBERS!B:C,2, ) -> MR. JABIR SHAHZAD | D47: 45995 | E47: 0 | F47: 150 | G47: 0 | H47: 0 | I47: 0 | J47: 0 | K47: 0 | L47: 0 | M47: 0 | N47: 0 | O47: 0 | P47: 0 | Q47: 0 | R47: 0 | S47: 0 | T47: 0 | U47: =SUM(E47:T47) -> 150
A48: =IF(D48<>"", ROW()-1, "") -> 47 | B48: HCFM-0542 | C48: =VLOOKUP(B48,MEMBERS!B:C,2, ) -> MR.HANIF AHSAN ZUBEDI | D48: 45995 | E48: 0 | F48: 0 | G48: 0 | H48: 0 | I48: 0 | J48: =300+500*3 -> 1800 | K48: 0 | L48: 0 | M48: 0 | N48: 0 | O48: 0 | P48: 0 | Q48: 0 | R48: 0 | S48: 0 | T48: 0 | U48: =SUM(E48:T48) -> 1800
A49: =IF(D49<>"", ROW()-1, "") -> 48 | B49: HCFM-0654 | C49: =VLOOKUP(B49,MEMBERS!B:C,2, ) -> SYED JIBRAN MUSHTAQ | D49: 45995 | E49: 0 | F49: 0 | G49: 0 | H49: 0 | I49: 0 | J49: =300+500*5 -> 2800 | K49: 0 | L49: 0 | M49: 0 | N49: 0 | O49: 0 | P49: 0 | Q49: 0 | R49: 0 | S49: 0 | T49: 0 | U49: =SUM(E49:T49) -> 2800
A50: =IF(D50<>"", ROW()-1, "") -> 49 | B50: HCFM-0650 | C50: =VLOOKUP(B50,MEMBERS!B:C,2, ) -> KHURRAM FIRDOUS | D50: 45996 | E50: 0 | F50: 0 | G50: 0 | H50: 0 | I50: 0 | J50: 0 | K50: 0 | L50: 0 | M50: 0 | N50: 0 | O50: =1000+1500*3 -> 5500 | P50: 0 | Q50: 0 | R50: 0 | S50: 0 | T50: 0 | U50: =SUM(E50:T50) -> 5500
A51: =IF(D51<>"", ROW()-1, "") -> 50 | B51: HCFM-0664 | C51: =VLOOKUP(B51,MEMBERS!B:C,2, ) -> SHAHBAZ AHMED | D51: 45996 | E51: 0 | F51: 300 | G51: 0 | H51: 0 | I51: 0 | J51: 0 | K51: 0 | L51: 0 | M51: 0 | N51: 0 | O51: 6000 | P51: 0 | Q51: 0 | R51: 0 | S51: 0 | T51: 0 | U51: =SUM(E51:T51) -> 6300
A52: =IF(D52<>"", ROW()-1, "") -> 51 | B52: HCFM-0515 | C52: =VLOOKUP(B52,MEMBERS!B:C,2, ) -> MR.TARIQUE ZUBAIR | D52: 45996 | E52: 0 | F52: 0 | G52: 0 | H52: 0 | I52: 0 | J52: =500*3 -> 1500 | K52: 0 | L52: 0 | M52: 0 | N52: 0 | O52: 0 | P52: 0 | Q52: 0 | R52: 0 | S52: 0 | T52: 0 | U52: =SUM(E52:T52) -> 1500
A53: =IF(D53<>"", ROW()-1, "") -> 52 | B53: HCFM-0641 | C53: =VLOOKUP(B53,MEMBERS!B:C,2, ) -> AAMIR RASOOL | D53: 45996 | E53: =300+600*4 -> 2700 | F53: 0 | G53: 0 | H53: 0 | I53: 0 | J53: =300*2+500*4 -> 2600 | K53: 0 | L53: 0 | M53: 0 | N53: 0 | O53: 0 | P53: 0 | Q53: 0 | R53: 0 | S53: 0 | T53: 0 | U53: =SUM(E53:T53) -> 5300
A54: =IF(D54<>"", ROW()-1, "") -> 53 | B54: HCFM-0648 | C54: =VLOOKUP(B54,MEMBERS!B:C,2, ) -> AYSM MIRZA | D54: 45996 | E54: 0 | F54: 150 | G54: 0 | H54: 0 | I54: 0 | J54: =300+500*2 -> 1300 | K54: 0 | L54: 0 | M54: 0 | N54: 0 | O54: 0 | P54: 0 | Q54: 0 | R54: 0 | S54: 0 | T54: 0 | U54: =SUM(E54:T54) -> 1450
A55: =IF(D55<>"", ROW()-1, "") -> 54 | B55: HCFM-0510 | C55: =VLOOKUP(B55,MEMBERS!B:C,2, ) -> MR.MUHAMMAD RIZWAN | D55: 45996 | E55: =300+600 -> 900 | F55: 0 | G55: 0 | H55: 0 | I55: 0 | J55: 0 | K55: 0 | L55: 0 | M55: 0 | N55: 0 | O55: 0 | P55: 0 | Q55: 0 | R55: 0 | S55: 0 | T55: 0 | U55: =SUM(E55:T55) -> 900
A56: =IF(D56<>"", ROW()-1, "") -> 55 | B56: HCFM-0642 | C56: =VLOOKUP(B56,MEMBERS!B:C,2, ) -> ASIF ASHFAQ | D56: 45996 | E56: 0 | F56: =150*2 -> 300 | G56: 0 | H56: 0 | I56: 0 | J56: 0 | K56: 0 | L56: 0 | M56: 0 | N56: 0 | O56: 0 | P56: 0 | Q56: 0 | R56: 0 | S56: 0 | T56: 0 | U56: =SUM(E56:T56) -> 300
A57: =IF(D57<>"", ROW()-1, "") -> 56 | B57: HCFM-0554 | C57: =VLOOKUP(B57,MEMBERS!B:C,2, ) -> MR.IMRAN WAZEER | D57: 45996 | E57: 0 | F57: 150 | G57: 0 | H57: 0 | I57: 0 | J57: 0 | K57: 0 | L57: 0 | M57: 0 | N57: 0 | O57: 0 | P57: 0 | Q57: 0 | R57: 0 | S57: 0 | T57: 0 | U57: =SUM(E57:T57) -> 150
A58: =IF(D58<>"", ROW()-1, "") -> 57 | B58: HCFM-0512 | C58: =VLOOKUP(B58,MEMBERS!B:C,2, ) -> MR.ZEESHAN IQBAL | D58: 45996 | E58: 0 | F58: =150*2 -> 300 | G58: 0 | H58: 0 | I58: 0 | J58: 0 | K58: 0 | L58: 0 | M58: 0 | N58: 0 | O58: 0 | P58: 0 | Q58: 0 | R58: 0 | S58: 0 | T58: 0 | U58: =SUM(E58:T58) -> 300
A59: =IF(D59<>"", ROW()-1, "") -> 58 | B59: HCFM-0518 | C59: =VLOOKUP(B59,MEMBERS!B:C,2, ) -> DR.SANTOSH KUMAR | D59: 45996 | E59: 0 | F59: 150 | G59: 0 | H59: 0 | I59: 0 | J59: 0 | K59: 0 | L59: 0 | M59: 0 | N59: 0 | O59: 0 | P59: 0 | Q59: 0 | R59: 0 | S59: 0 | T59: 0 | U59: =SUM(E59:T59) -> 150
A60: =IF(D60<>"", ROW()-1, "") -> 59 | B60: HCFM-0548 | C60: =VLOOKUP(B60,MEMBERS!B:C,2, ) -> MR.ZAIN FAROOQ | D60: 45996 | E60: 0 | F60: 150 | G60: 0 | H60: 0 | I60: 0 | J60: 0 | K60: 0 | L60: 0 | M60: 0 | N60: 0 | O60: 0 | P60: 0 | Q60: 0 | R60: 0 | S60: 0 | T60: 0 | U60: =SUM(E60:T60) -> 150
A61: =IF(D61<>"", ROW()-1, "") -> 60 | B61: HCFM-0657 | C61: =VLOOKUP(B61,MEMBERS!B:C,2, ) -> NASIR ABBAS | D61: 45996 | E61: 0 | F61: =150*2 -> 300 | G61: 0 | H61: 0 | I61: 0 | J61: 0 | K61: 0 | L61: 0 | M61: 0 | N61: 0 | O61: 0 | P61: 0 | Q61: 0 | R61: 0 | S61: 0 | T61: 0 | U61: =SUM(E61:T61) -> 300
A62: =IF(D62<>"", ROW()-1, "") -> 61 | B62: HCFM-0502 | C62: =VLOOKUP(B62,MEMBERS!B:C,2, ) -> MR. JABIR SHAHZAD | D62: 45996 | E62: 0 | F62: 150 | G62: 0 | H62: 0 | I62: 0 | J62: 0 | K62: 0 | L62: 0 | M62: 0 | N62: 0 | O62: 0 | P62: 0 | Q62: 0 | R62: 0 | S62: 0 | T62: 0 | U62: =SUM(E62:T62) -> 150
A63: =IF(D63<>"", ROW()-1, "") -> 62 | B63: HCFM-0 | C63: CARD | D63: 45997 | E63: 0 | F63: 0 | G63: 0 | H63: 0 | I63: 0 | J63: 0 | K63: 0 | L63: 0 | M63: 0 | N63: 0 | O63: 11200 | P63: 0 | Q63: 0 | R63: 0 | S63: 0 | T63: 0 | U63: =SUM(E63:T63) -> 11200
A64: =IF(D64<>"", ROW()-1, "") -> 63 | B64: HCFM-0554 | C64: =VLOOKUP(B64,MEMBERS!B:C,2, ) -> MR.IMRAN WAZEER | D64: 45997 | E64: 0 | F64: 150 | G64: 0 | H64: 0 | I64: 0 | J64: =300*3 -> 900 | K64: 0 | L64: 0 | M64: 0 | N64: 0 | O64: 2250 | P64: 0 | Q64: 0 | R64: 0 | S64: 0 | T64: 0 | U64: =SUM(E64:T64) -> 3300
A65: =IF(D65<>"", ROW()-1, "") -> 64 | B65: HCFM-0684 | C65: =VLOOKUP(B65,MEMBERS!B:C,2, ) -> MR. ZAMIR ALI SHAH | D65: 45997 | E65: 0 | F65: 0 | G65: 0 | H65: 0 | I65: 0 | J65: =500*6 -> 3000 | K65: 0 | L65: 0 | M65: 0 | N65: 0 | O65: 4000 | P65: 0 | Q65: 0 | R65: 0 | S65: 0 | T65: 0 | U65: =SUM(E65:T65) -> 7000
A66: =IF(D66<>"", ROW()-1, "") -> 65 | B66: HCFM-0512 | C66: =VLOOKUP(B66,MEMBERS!B:C,2, ) -> MR.ZEESHAN IQBAL | D66: 45997 | E66: 0 | F66: =150*2 -> 300 | G66: 0 | H66: 0 | I66: 0 | J66: 0 | K66: 0 | L66: 0 | M66: 0 | N66: 0 | O66: 0 | P66: 0 | Q66: 0 | R66: 0 | S66: 0 | T66: 0 | U66: =SUM(E66:T66) -> 300
A67: =IF(D67<>"", ROW()-1, "") -> 66 | B67: HCFM-0509 | C67: =VLOOKUP(B67,MEMBERS!B:C,2, ) -> MR.SYED ABDULLAH ALI | D67: 45997 | E67: 0 | F67: 150 | G67: 0 | H67: 0 | I67: 0 | J67: 0 | K67: 0 | L67: 0 | M67: 0 | N67: 0 | O67: 0 | P67: 0 | Q67: 0 | R67: 0 | S67: 0 | T67: 0 | U67: =SUM(E67:T67) -> 150
A68: =IF(D68<>"", ROW()-1, "") -> 67 | B68: HCFM-0542 | C68: =VLOOKUP(B68,MEMBERS!B:C,2, ) -> MR.HANIF AHSAN ZUBEDI | D68: 45997 | E68: 0 | F68: =150*2+300 -> 600 | G68: 0 | H68: 0 | I68: 0 | J68: =300*2+500 -> 1100 | K68: 0 | L68: 0 | M68: 0 | N68: 0 | O68: 0 | P68: 0 | Q68: 0 | R68: 0 | S68: 0 | T68: 0 | U68: =SUM(E68:T68) -> 1700
A69: =IF(D69<>"", ROW()-1, "") -> 68 | B69: HCFM-0548 | C69: =VLOOKUP(B69,MEMBERS!B:C,2, ) -> MR.ZAIN FAROOQ | D69: 45997 | E69: 0 | F69: 150 | G69: 0 | H69: 0 | I69: 0 | J69: 0 | K69: 0 | L69: 0 | M69: 0 | N69: 0 | O69: 0 | P69: 0 | Q69: 0 | R69: 0 | S69: 0 | T69: 0 | U69: =SUM(E69:T69) -> 150
A70: =IF(D70<>"", ROW()-1, "") -> 69 | B70: HCFM-0657 | C70: =VLOOKUP(B70,MEMBERS!B:C,2, ) -> NASIR ABBAS | D70: 45997 | E70: 0 | F70: 150 | G70: 0 | H70: 0 | I70: 0 | J70: 0 | K70: 0 | L70: 0 | M70: 0 | N70: 0 | O70: 0 | P70: 0 | Q70: 0 | R70: 0 | S70: 0 | T70: 0 | U70: =SUM(E70:T70) -> 150
A71: =IF(D71<>"", ROW()-1, "") -> 70 | B71: HCFM-0506 | C71: =VLOOKUP(B71,MEMBERS!B:C,2, ) -> MR.MUHAMMAD ARIF | D71: 45997 | E71: =300*3+600*3 -> 2700 | F71: 0 | G71: 0 | H71: 0 | I71: 0 | J71: =300*2 -> 600 | K71: 0 | L71: 0 | M71: 0 | N71: 0 | O71: 0 | P71: 0 | Q71: 0 | R71: 0 | S71: 0 | T71: 0 | U71: =SUM(E71:T71) -> 3300
A72: =IF(D72<>"", ROW()-1, "") -> 71 | B72: HCFM-0682 | C72: =VLOOKUP(B72,MEMBERS!B:C,2, ) -> MR. ZAHIR REHMAN | D72: 45997 | E72: 0 | F72: 0 | G72: 0 | H72: 0 | I72: 0 | J72: =300*5 -> 1500 | K72: 0 | L72: 0 | M72: 0 | N72: 0 | O72: 0 | P72: 0 | Q72: 0 | R72: 0 | S72: 0 | T72: 0 | U72: =SUM(E72:T72) -> 1500
A73: =IF(D73<>"", ROW()-1, "") -> 72 | B73: HCFM-0596 | C73: =VLOOKUP(B73,MEMBERS!B:C,2, ) -> DGM AZFAR ALI | D73: 45997 | E73: 0 | F73: 0 | G73: 0 | H73: 0 | I73: 0 | J73: =300*2 -> 600 | K73: 0 | L73: 0 | M73: 0 | N73: 0 | O73: 0 | P73: 0 | Q73: 0 | R73: 0 | S73: 0 | T73: 0 | U73: =SUM(E73:T73) -> 600
A74: =IF(D74<>"", ROW()-1, "") -> 73 | B74: HCFM-0516 | C74: =VLOOKUP(B74,MEMBERS!B:C,2, ) -> MR.ATIF SHAFQAT | D74: 45997 | E74: 0 | F74: 0 | G74: 0 | H74: 0 | I74: 0 | J74: =300*2 -> 600 | K74: 0 | L74: 0 | M74: 0 | N74: 0 | O74: 0 | P74: 0 | Q74: 0 | R74: 0 | S74: 0 | T74: 0 | U74: =SUM(E74:T74) -> 600
A75: =IF(D75<>"", ROW()-1, "") -> 74 | B75: HCFM-0656 | C75: =VLOOKUP(B75,MEMBERS!B:C,2, ) -> ZAIB UR REHMAN | D75: 45997 | E75: 0 | F75: 0 | G75: 0 | H75: 0 | I75: 0 | J75: =300*4+500*2 -> 2200 | K75: 0 | L75: 0 | M75: 0 | N75: 0 | O75: 0 | P75: 0 | Q75: 0 | R75: 0 | S75: 0 | T75: 0 | U75: =SUM(E75:T75) -> 2200
A76: =IF(D76<>"", ROW()-1, "") -> 75 | B76: HCFM-0 | C76: CARD | D76: 45997 | E76: 0 | F76: 0 | G76: 0 | H76: 0 | I76: 0 | J76: 500 | K76: 0 | L76: 0 | M76: 0 | N76: 0 | O76: 0 | P76: 0 | Q76: 0 | R76: 0 | S76: 0 | T76: 0 | U76: =SUM(E76:T76) -> 500
A77: =IF(D77<>"", ROW()-1, "") -> 76 | B77: HCFM-0508 | C77: =VLOOKUP(B77,MEMBERS!B:C,2, ) -> MR.SHIRAZ AHMED | D77: 45997 | E77: =600*4 -> 2400 | F77: 0 | G77: 0 | H77: 0 | I77: 0 | J77: 0 | K77: 0 | L77: 0 | M77: 0 | N77: 0 | O77: 0 | P77: 0 | Q77: 0 | R77: 0 | S77: 0 | T77: 0 | U77: =SUM(E77:T77) -> 2400
A78: =IF(D78<>"", ROW()-1, "") -> 77 | B78: HCFM-0670 | C78: =VLOOKUP(B78,MEMBERS!B:C,2, ) -> MR. TEHSEEN FAIZ | D78: 45997 | E78: =300*4+600*2 -> 2400 | F78: 0 | G78: 0 | H78: 0 | I78: 0 | J78: 0 | K78: 0 | L78: 0 | M78: 0 | N78: 0 | O78: 0 | P78: 0 | Q78: 0 | R78: 0 | S78: 0 | T78: 0 | U78: =SUM(E78:T78) -> 2400
A79: =IF(D79<>"", ROW()-1, "") -> 78 | B79: HCFM-0545 | C79: =VLOOKUP(B79,MEMBERS!B:C,2, ) -> MR. HASAN KARIM | D79: 45997 | E79: 0 | F79: 0 | G79: 0 | H79: 0 | I79: 0 | J79: 0 | K79: 300 | L79: 0 | M79: 0 | N79: 0 | O79: =1000+1500*3 -> 5500 | P79: 0 | Q79: 0 | R79: 0 | S79: 0 | T79: 0 | U79: =SUM(E79:T79) -> 5800
A80: =IF(D80<>"", ROW()-1, "") -> 79 | B80: HCFM-0 | C80: CARD | D80: 45998 | E80: 0 | F80: 0 | G80: 0 | H80: 0 | I80: 0 | J80: 0 | K80: 0 | L80: 0 | M80: 0 | N80: 0 | O80: 0 | P80: 20500 | Q80: 0 | R80: 0 | S80: 0 | T80: 0 | U80: =SUM(E80:T80) -> 20500
A81: =IF(D81<>"", ROW()-1, "") -> 80 | B81: HCFM-0 | C81: =VLOOKUP(B81,MEMBERS!B:C,2, ) -> #N/A | D81: 45998 | E81: 0 | F81: 0 | G81: 0 | H81: 0 | I81: 0 | J81: 0 | K81: 0 | L81: 0 | M81: 0 | N81: 0 | O81: 0 | P81: 0 | Q81: 0 | R81: 0 | S81: 0 | T81: 0 | U81: =SUM(E81:T81) -> 0
A82: =IF(D82<>"", ROW()-1, "") -> 81 | B82: HCFM-0654 | C82: =VLOOKUP(B82,MEMBERS!B:C,2, ) -> SYED JIBRAN MUSHTAQ | D82: 45998 | E82: =600*2 -> 1200 | F82: 0 | G82: 0 | H82: 0 | I82: 0 | J82: =300+500*3 -> 1800 | K82: 0 | L82: 0 | M82: 0 | N82: 1500 | O82: 0 | P82: 0 | Q82: 0 | R82: 0 | S82: 0 | T82: 0 | U82: =SUM(E82:T82) -> 4500
A83: =IF(D83<>"", ROW()-1, "") -> 82 | B83: HCFM-0683 | C83: =VLOOKUP(B83,MEMBERS!B:C,2, ) -> MR. YASIR RASHEED | D83: 45998 | E83: 0 | F83: 0 | G83: 0 | H83: 0 | I83: 0 | J83: 0 | K83: 0 | L83: 0 | M83: 0 | N83: 1500 | O83: 0 | P83: 0 | Q83: 0 | R83: 0 | S83: 0 | T83: 0 | U83: =SUM(E83:T83) -> 1500
A84: =IF(D84<>"", ROW()-1, "") -> 83 | B84: HCFM-0542 | C84: =VLOOKUP(B84,MEMBERS!B:C,2, ) -> MR.HANIF AHSAN ZUBEDI | D84: 45998 | E84: =600*4 -> 2400 | F84: 0 | G84: 0 | H84: 0 | I84: 0 | J84: =300*4+500*4+500*7 -> 6700 | K84: 0 | L84: 0 | M84: 0 | N84: 0 | O84: 0 | P84: 0 | Q84: 0 | R84: 0 | S84: 0 | T84: 0 | U84: =SUM(E84:T84) -> 9100
A85: =IF(D85<>"", ROW()-1, "") -> 84 | B85: HCFM-0650 | C85: =VLOOKUP(B85,MEMBERS!B:C,2, ) -> KHURRAM FIRDOUS | D85: 45998 | E85: 0 | F85: 0 | G85: 0 | H85: 0 | I85: 0 | J85: =300*3 -> 900 | K85: 0 | L85: 0 | M85: 0 | N85: 0 | O85: 0 | P85: 0 | Q85: 0 | R85: 0 | S85: 0 | T85: 0 | U85: =SUM(E85:T85) -> 900
A86: =IF(D86<>"", ROW()-1, "") -> 85 | B86: HCFM-0556 | C86: =VLOOKUP(B86,MEMBERS!B:C,2, ) -> MR.SYED SALMAN RAZA | D86: 45998 | E86: 0 | F86: 0 | G86: 0 | H86: 0 | I86: 0 | J86: =300*3 -> 900 | K86: 0 | L86: 0 | M86: 0 | N86: 0 | O86: 0 | P86: 0 | Q86: 0 | R86: 0 | S86: 0 | T86: 0 | U86: =SUM(E86:T86) -> 900
A87: =IF(D87<>"", ROW()-1, "") -> 86 | B87: HCFM-0 | C87: CARD | D87: 45998 | E87: 0 | F87: 0 | G87: 0 | H87: 0 | I87: 0 | J87: =500*6 -> 3000 | K87: 0 | L87: 0 | M87: 0 | N87: 0 | O87: 0 | P87: 0 | Q87: 0 | R87: 0 | S87: 0 | T87: 0 | U87: =SUM(E87:T87) -> 3000
A88: =IF(D88<>"", ROW()-1, "") -> 87 | B88: HCFM-0519 | C88: =VLOOKUP(B88,MEMBERS!B:C,2, ) -> DR.NAZEER HUSSAIN KALHORO | D88: 45998 | E88: 0 | F88: 0 | G88: 0 | H88: 0 | I88: 0 | J88: =300*2 -> 600 | K88: 0 | L88: 0 | M88: 0 | N88: 0 | O88: 0 | P88: 0 | Q88: 0 | R88: 0 | S88: 0 | T88: 0 | U88: =SUM(E88:T88) -> 600
A89: =IF(D89<>"", ROW()-1, "") -> 88 | B89: HCFM-0512 | C89: =VLOOKUP(B89,MEMBERS!B:C,2, ) -> MR.ZEESHAN IQBAL | D89: 45998 | E89: 0 | F89: 150 | G89: 0 | H89: 0 | I89: 0 | J89: 300 | K89: 0 | L89: 0 | M89: 0 | N89: 0 | O89: 0 | P89: 0 | Q89: 0 | R89: 0 | S89: 0 | T89: 0 | U89: =SUM(E89:T89) -> 450
A90: =IF(D90<>"", ROW()-1, "") -> 89 | B90: HCFM-0657 | C90: =VLOOKUP(B90,MEMBERS!B:C,2, ) -> NASIR ABBAS | D90: 45998 | E90: 0 | F90: 150 | G90: 0 | H90: 0 | I90: 0 | J90: 0 | K90: 0 | L90: 0 | M90: 0 | N90: 0 | O90: 0 | P90: 0 | Q90: 0 | R90: 0 | S90: 0 | T90: 0 | U90: =SUM(E90:T90) -> 150
A91: =IF(D91<>"", ROW()-1, "") -> 90 | B91: HCFM-0548 | C91: =VLOOKUP(B91,MEMBERS!B:C,2, ) -> MR.ZAIN FAROOQ | D91: 45998 | E91: 0 | F91: =150*2 -> 300 | G91: 0 | H91: 0 | I91: 0 | J91: 0 | K91: 0 | L91: 0 | M91: 0 | N91: 0 | O91: 0 | P91: 0 | Q91: 0 | R91: 0 | S91: 0 | T91: 0 | U91: =SUM(E91:T91) -> 300
A92: =IF(D92<>"", ROW()-1, "") -> 91 | B92: HCFM-0543 | C92: =VLOOKUP(B92,MEMBERS!B:C,2, ) -> MR.MUHAMMAD ATIF USMANI | D92: 45998 | E92: 0 | F92: 150 | G92: 0 | H92: 0 | I92: 0 | J92: 0 | K92: 0 | L92: 0 | M92: 0 | N92: 0 | O92: 0 | P92: 0 | Q92: 0 | R92: 0 | S92: 0 | T92: 0 | U92: =SUM(E92:T92) -> 150
A93: =IF(D93<>"", ROW()-1, "") -> 92 | B93: HCFM-0656 | C93: =VLOOKUP(B93,MEMBERS!B:C,2, ) -> ZAIB UR REHMAN | D93: 45998 | E93: =300+600*2 -> 1500 | F93: 0 | G93: 0 | H93: 0 | I93: 0 | J93: 0 | K93: 0 | L93: 0 | M93: 0 | N93: 0 | O93: 0 | P93: 0 | Q93: 0 | R93: 0 | S93: 0 | T93: 0 | U93: =SUM(E93:T93) -> 1500
A94: =IF(D94<>"", ROW()-1, "") -> 93 | B94: HCFM-0 | C94: CARD | D94: 45998 | E94: 6000 | F94: 0 | G94: 0 | H94: 0 | I94: 0 | J94: 0 | K94: 0 | L94: 0 | M94: 0 | N94: 0 | O94: 0 | P94: 0 | Q94: 0 | R94: 0 | S94: 0 | T94: 0 | U94: =SUM(E94:T94) -> 6000
A95: =IF(D95<>"", ROW()-1, "") -> 94 | B95: HCFM-0521 | C95: =VLOOKUP(B95,MEMBERS!B:C,2, ) -> MR.HAFEEZ AHMED SIYAL | D95: 45999 | E95: 0 | F95: 150 | G95: 0 | H95: 0 | I95: 0 | J95: 300 | K95: 0 | L95: 0 | M95: 0 | N95: 0 | O95: 0 | P95: 0 | Q95: 0 | R95: 0 | S95: 0 | T95: 0 | U95: =SUM(E95:T95) -> 450
A96: =IF(D96<>"", ROW()-1, "") -> 95 | B96: HCFM-0655 | C96: =VLOOKUP(B96,MEMBERS!B:C,2, ) -> SADDAM HUSSAIN | D96: 45999 | E96: 0 | F96: 0 | G96: 0 | H96: 0 | I96: 0 | J96: 300 | K96: 0 | L96: 0 | M96: 0 | N96: 0 | O96: 0 | P96: 0 | Q96: 0 | R96: 0 | S96: 0 | T96: 0 | U96: =SUM(E96:T96) -> 300
A97: =IF(D97<>"", ROW()-1, "") -> 96 | B97: HCFM-0515 | C97: =VLOOKUP(B97,MEMBERS!B:C,2, ) -> MR.TARIQUE ZUBAIR | D97: 45999 | E97: 0 | F97: 150 | G97: 0 | H97: 0 | I97: 0 | J97: 0 | K97: 0 | L97: 0 | M97: 0 | N97: 0 | O97: 0 | P97: 0 | Q97: 0 | R97: 0 | S97: 0 | T97: 0 | U97: =SUM(E97:T97) -> 150
A98: =IF(D98<>"", ROW()-1, "") -> 97 | B98: HCFM-0597 | C98: =VLOOKUP(B98,MEMBERS!B:C,2, ) -> GM GHULAM DASTAGEER | D98: 45999 | E98: 0 | F98: 150 | G98: 0 | H98: 0 | I98: 0 | J98: 0 | K98: 0 | L98: 0 | M98: 0 | N98: 0 | O98: 0 | P98: 0 | Q98: 0 | R98: 0 | S98: 0 | T98: 0 | U98: =SUM(E98:T98) -> 150
A99: =IF(D99<>"", ROW()-1, "") -> 98 | B99: HCFM-0512 | C99: =VLOOKUP(B99,MEMBERS!B:C,2, ) -> MR.ZEESHAN IQBAL | D99: 45999 | E99: 0 | F99: 150 | G99: 0 | H99: 0 | I99: 0 | J99: 0 | K99: 0 | L99: 0 | M99: 0 | N99: 0 | O99: 0 | P99: 0 | Q99: 0 | R99: 0 | S99: 0 | T99: 0 | U99: =SUM(E99:T99) -> 150
A100: =IF(D100<>"", ROW()-1, "") -> 99 | B100: HCFM-0642 | C100: =VLOOKUP(B100,MEMBERS!B:C,2, ) -> ASIF ASHFAQ | D100: 45999 | E100: 0 | F100: =150*2 -> 300 | G100: 0 | H100: 0 | I100: 0 | J100: 0 | K100: 0 | L100: 0 | M100: 0 | N100: 0 | O100: 0 | P100: 0 | Q100: 0 | R100: 0 | S100: 0 | T100: 0 | U100: =SUM(E100:T100) -> 300
A101: =IF(D101<>"", ROW()-1, "") -> 100 | B101: HCFM-0554 | C101: =VLOOKUP(B101,MEMBERS!B:C,2, ) -> MR.IMRAN WAZEER | D101: 45999 | E101: 0 | F101: 150 | G101: 0 | H101: 0 | I101: 0 | J101: 0 | K101: 0 | L101: 0 | M101: 0 | N101: 0 | O101: 0 | P101: 0 | Q101: 0 | R101: 0 | S101: 0 | T101: 0 | U101: =SUM(E101:T101) -> 150
...

Sheet F & B
A1: S.NO | B1: MEMBERSHIP ID | C1: NAME | D1: DATE | E1: QTY. | F1: FOOD ORDER | G1: AMOUNT | H1: sst 15% | I1: TOTAL
A2: =IF(D2<>"", ROW()-1, "") -> 1 | B2: HCFM-0684 | C2: =VLOOKUP(B2,MEMBERS!B:C,2, ) -> MR. ZAMIR ALI SHAH | D2: 45992 | E2: 8 | F2: SODA WATER CAN | G2: =IFERROR(VLOOKUP(F2,'menu list'!B:C,2,FALSE)*E2,"0") -> 1600 | H2: =G2*15/100 -> 240 | I2: =G2+H2 -> 1840
A3: =IF(D3<>"", ROW()-1, "") -> 2 | B3: HCFM-0684 | C3: =VLOOKUP(B3,MEMBERS!B:C,2, ) -> MR. ZAMIR ALI SHAH | D3: 45992 | E3: 4 | F3: CORKAGE | G3: =IFERROR(VLOOKUP(F3,'menu list'!B:C,2,FALSE)*E3,"0") -> 4000 | H3: =G3*15/100 -> 600 | I3: =G3+H3 -> 4600
A4: =IF(D4<>"", ROW()-1, "") -> 3 | B4: HCFM-0684 | C4: =VLOOKUP(B4,MEMBERS!B:C,2, ) -> MR. ZAMIR ALI SHAH | D4: 45992 | E4: 1 | F4: PRAWN TEMPURA | G4: =IFERROR(VLOOKUP(F4,'menu list'!B:C,2,FALSE)*E4,"0") -> 2000 | H4: =G4*15/100 -> 300 | I4: =G4+H4 -> 2300
A5: =IF(D5<>"", ROW()-1, "") -> 4 | B5: HCFM-0684 | C5: =VLOOKUP(B5,MEMBERS!B:C,2, ) -> MR. ZAMIR ALI SHAH | D5: 45992 | E5: 1 | F5: CHICKEN ROULADE | G5: =IFERROR(VLOOKUP(F5,'menu list'!B:C,2,FALSE)*E5,"0") -> 850 | H5: =G5*15/100 -> 127.5 | I5: =G5+H5 -> 977.5
A6: =IF(D6<>"", ROW()-1, "") -> 5 | B6: HCFM-0684 | C6: =VLOOKUP(B6,MEMBERS!B:C,2, ) -> MR. ZAMIR ALI SHAH | D6: 45992 | E6: 1 | F6: HC SPECIAL MUTTON KARAHI | G6: =IFERROR(VLOOKUP(F6,'menu list'!B:C,2,FALSE)*E6,"0") -> 1800 | H6: =G6*15/100 -> 270 | I6: =G6+H6 -> 2070
A7: =IF(D7<>"", ROW()-1, "") -> 6 | B7: HCFM-0684 | C7: =VLOOKUP(B7,MEMBERS!B:C,2, ) -> MR. ZAMIR ALI SHAH | D7: 45992 | E7: 1 | F7: DRY BEEF CHILLI | G7: =IFERROR(VLOOKUP(F7,'menu list'!B:C,2,FALSE)*E7,"0") -> 999 | H7: =G7*15/100 -> 149.85 | I7: =G7+H7 -> 1148.85
A8: =IF(D8<>"", ROW()-1, "") -> 7 | B8: HCFM-0684 | C8: =VLOOKUP(B8,MEMBERS!B:C,2, ) -> MR. ZAMIR ALI SHAH | D8: 45992 | E8: 1 | F8: RAITA | G8: =IFERROR(VLOOKUP(F8,'menu list'!B:C,2,FALSE)*E8,"0") -> 200 | H8: =G8*15/100 -> 30 | I8: =G8+H8 -> 230
A9: =IF(D9<>"", ROW()-1, "") -> 8 | B9: HCFM-0684 | C9: =VLOOKUP(B9,MEMBERS!B:C,2, ) -> MR. ZAMIR ALI SHAH | D9: 45992 | E9: 1 | F9: FRESH GARDEN SALAD | G9: =IFERROR(VLOOKUP(F9,'menu list'!B:C,2,FALSE)*E9,"0") -> 800 | H9: =G9*15/100 -> 120 | I9: =G9+H9 -> 920
A10: =IF(D10<>"", ROW()-1, "") -> 9 | B10: HCFM-0684 | C10: =VLOOKUP(B10,MEMBERS!B:C,2, ) -> MR. ZAMIR ALI SHAH | D10: 45992 | E10: 1 | F10: MINERAL WATER LARGE | G10: =IFERROR(VLOOKUP(F10,'menu list'!B:C,2,FALSE)*E10,"0") -> 150 | H10: =G10*15/100 -> 22.5 | I10: =G10+H10 -> 172.5
A11: =IF(D11<>"", ROW()-1, "") -> 10 | B11: HCFM-0503 | C11: =VLOOKUP(B11,MEMBERS!B:C,2, ) -> MR.GHULAM NABI OTHI | D11: 45992 | E11: 1 | F11: SPECIAL CHICKEN POPCORN | G11: =IFERROR(VLOOKUP(F11,'menu list'!B:C,2,FALSE)*E11,"0") -> 500 | H11: =G11*15/100 -> 75 | I11: =G11+H11 -> 575
A12: =IF(D12<>"", ROW()-1, "") -> 11 | B12: HCFM-0503 | C12: =VLOOKUP(B12,MEMBERS!B:C,2, ) -> MR.GHULAM NABI OTHI | D12: 45992 | E12: 1 | F12: CREAM OF MASHROOM SOUP | G12: =IFERROR(VLOOKUP(F12,'menu list'!B:C,2,FALSE)*E12,"0") -> 400 | H12: =G12*15/100 -> 60 | I12: =G12+H12 -> 460
A13: =IF(D13<>"", ROW()-1, "") -> 12 | B13: HCFM-0503 | C13: =VLOOKUP(B13,MEMBERS!B:C,2, ) -> MR.GHULAM NABI OTHI | D13: 45992 | E13: 1 | F13: RAITA | G13: =IFERROR(VLOOKUP(F13,'menu list'!B:C,2,FALSE)*E13,"0") -> 200 | H13: =G13*15/100 -> 30 | I13: =G13+H13 -> 230
... A59: =IF(D59<>"", ROW()-1, "") -> 58 | B59: HCFM-0596 | C59: =VLOOKUP(B59,MEMBERS!B:C,2, ) -> DGM AZFAR ALI | D59: 45993 | E59: 1 | F59: MINERAL WATER LARGE | G59: =IFERROR(VLOOKUP(F59,'menu list'!B:C,2,FALSE)*E59,"0") -> 150 | H59: =G59*15/100 -> 22.5 | I59: =G59+H59 -> 172.5
A60: =IF(D60<>"", ROW()-1, "") -> 59 | B60: HCFM-0646 | C60: =VLOOKUP(B60,MEMBERS!B:C,2, ) -> BAHRIA INTERNATIONAL HOSPITAL | D60: 45993 | E60: 8 | F60: ASSORTED COOKIES | G60: =IFERROR(VLOOKUP(F60,'menu list'!B:C,2,FALSE)*E60,"0") -> 3200 | I60: =G60+H60 -> 3200
A61: =IF(D61<>"", ROW()-1, "") -> 60 | B61: HCFM-0668 | C61: =VLOOKUP(B61,MEMBERS!B:C,2, ) -> MR. KASHIF SAEED | D61: 45993 | E61: 1 | F61: CLUB SANDWICH | G61: =IFERROR(VLOOKUP(F61,'menu list'!B:C,2,FALSE)*E61,"0") -> 1250 | H61: =G61*15/100 -> 187.5 | I61: =G61+H61 -> 1437.5
A62: =IF(D62<>"", ROW()-1, "") -> 61 | B62: HCFM-0646 | C62: =VLOOKUP(B62,MEMBERS!B:C,2, ) -> BAHRIA INTERNATIONAL HOSPITAL | D62: 45993 | E62: 25 | F62: CHICKEN PATTIES | G62: =IFERROR(VLOOKUP(F62,'menu list'!B:C,2,FALSE)*E62,"0") -> 2500 | I62: =G62+H62 -> 2500
A63: =IF(D63<>"", ROW()-1, "") -> 62 | B63: HCFM-0646 | C63: =VLOOKUP(B63,MEMBERS!B:C,2, ) -> BAHRIA INTERNATIONAL HOSPITAL | D63: 45993 | E63: 10 | F63: DOUGHNUTS | G63: =IFERROR(VLOOKUP(F63,'menu list'!B:C,2,FALSE)*E63,"0") -> 1500 | I63: =G63+H63 -> 1500
A64: =IF(D64<>"", ROW()-1, "") -> 63 | B64: HCFM-0646 | C64: =VLOOKUP(B64,MEMBERS!B:C,2, ) -> BAHRIA INTERNATIONAL HOSPITAL | D64: 45993 | E64: 9 | F64: ASSORTED PASTRY | G64: =IFERROR(VLOOKUP(F64,'menu list'!B:C,2,FALSE)*E64,"0") -> 2250 | I64: =G64+H64 -> 2250
A65: =IF(D65<>"", ROW()-1, "") -> 64 | B65: HCFM-0515 | C65: =VLOOKUP(B65,MEMBERS!B:C,2, ) -> MR.TARIQUE ZUBAIR | D65: 45993 | E65: 1 | F65: GRILLED CHICKEN SANDWICH | G65: 0 | H65: =G65*15/100 -> 0 | I65: =G65+H65 -> 0
A66: =IF(D66<>"", ROW()-1, "") -> 65 | B66: HCFM-0515 | C66: =VLOOKUP(B66,MEMBERS!B:C,2, ) -> MR.TARIQUE ZUBAIR | D66: 45993 | E66: 4 | F66: PLAIN NAAN | G66: 0 | H66: =G66*15/100 -> 0 | I66: =G66+H66 -> 0
A67: =IF(D67<>"", ROW()-1, "") -> 66 | B67: HCFM-0641 | C67: =VLOOKUP(B67,MEMBERS!B:C,2, ) -> AAMIR RASOOL | D67: 45995 | E67: 1 | F67: MINERAL WATER LARGE | G67: =IFERROR(VLOOKUP(F67,'menu list'!B:C,2,FALSE)*E67,"0") -> 150 | H67: =G67*15/100 -> 22.5 | I67: =G67+H67 -> 172.5
A68: =IF(D68<>"", ROW()-1, "") -> 67 | B68: HCFM-0641 | C68: =VLOOKUP(B68,MEMBERS!B:C,2, ) -> AAMIR RASOOL | D68: 45995 | E68: 1 | F68: PINA COLADA | G68: =IFERROR(VLOOKUP(F68,'menu list'!B:C,2,FALSE)*E68,"0") -> 450 | H68: =G68*15/100 -> 67.5 | I68: =G68+H68 -> 517.5
A69: =IF(D69<>"", ROW()-1, "") -> 68 | B69: HCFM-0559 | C69: =VLOOKUP(B69,MEMBERS!B:C,2, ) -> MR.SYED HAMID SHAH | D69: 45995 | E69: 1 | F69: CHICKEN ROULADE | G69: =IFERROR(VLOOKUP(F69,'menu list'!B:C,2,FALSE)*E69,"0") -> 850 | H69: =G69*15/100 -> 127.5 | I69: =G69+H69 -> 977.5
A70: =IF(D70<>"", ROW()-1, "") -> 69 | B70: HCFM-0559 | C70: =VLOOKUP(B70,MEMBERS!B:C,2, ) -> MR.SYED HAMID SHAH | D70: 45995 | E70: 1 | F70: MINERAL WATER LARGE | G70: =IFERROR(VLOOKUP(F70,'menu list'!B:C,2,FALSE)*E70,"0") -> 150 | H70: =G70*15/100 -> 22.5 | I70: =G70+H70 -> 172.5
A71: =IF(D71<>"", ROW()-1, "") -> 70 | B71: HCFM-0559 | C71: =VLOOKUP(B71,MEMBERS!B:C,2, ) -> MR.SYED HAMID SHAH | D71: 45995 | E71: 1 | F71: CHICKEN DYNAMITE | G71: =IFERROR(VLOOKUP(F71,'menu list'!B:C,2,FALSE)*E71,"0") -> 850 | H71: =G71*15/100 -> 127.5 | I71: =G71+H71 -> 977.5
A72: =IF(D72<>"", ROW()-1, "") -> 71 | B72: HCFM-0559 | C72: =VLOOKUP(B72,MEMBERS!B:C,2, ) -> MR.SYED HAMID SHAH | D72: 45995 | E72: 1 | F72: CLUB SANDWICH | G72: =IFERROR(VLOOKUP(F72,'menu list'!B:C,2,FALSE)*E72,"0") -> 1250 | H72: =G72*15/100 -> 187.5 | I72: =G72+H72 -> 1437.5
A73: =IF(D73<>"", ROW()-1, "") -> 72 | B73: HCFM-0559 | C73: =VLOOKUP(B73,MEMBERS!B:C,2, ) -> MR.SYED HAMID SHAH | D73: 45995 | E73: 4 | F73: MINT LEMONADE | G73: =IFERROR(VLOOKUP(F73,'menu list'!B:C,2,FALSE)*E73,"0") -> 1400 | H73: =G73*15/100 -> 210 | I73: =G73+H73 -> 1610
A74: =IF(D74<>"", ROW()-1, "") -> 73 | B74: HCFM-0656 | C74: =VLOOKUP(B74,MEMBERS!B:C,2, ) -> ZAIB UR REHMAN | D74: 45995 | E74: 1 | F74: CHICKEN KARAHI | G74: =IFERROR(VLOOKUP(F74,'menu list'!B:C,2,FALSE)*E74,"0") -> 900 | H74: =G74*15/100 -> 135 | I74: =G74+H74 -> 1035
A75: =IF(D75<>"", ROW()-1, "") -> 74 | B75: HCFM-0656 | C75: =VLOOKUP(B75,MEMBERS!B:C,2, ) -> ZAIB UR REHMAN | D75: 45995 | E75: 6 | F75: PLAIN NAAN | G75: =IFERROR(VLOOKUP(F75,'menu list'!B:C,2,FALSE)*E75,"0") -> 420 | H75: =G75*15/100 -> 63 | I75: =G75+H75 -> 483
A76: =IF(D76<>"", ROW()-1, "") -> 75 | B76: HCFM-0656 | C76: =VLOOKUP(B76,MEMBERS!B:C,2, ) -> ZAIB UR REHMAN | D76: 45995 | E76: 3 | F76: MEDITERRANEAN GRILLED FISH | G76: =IFERROR(VLOOKUP(F76,'menu list'!B:C,2,FALSE)*E76,"0") -> 3300 | H76: =G76*15/100 -> 495 | I76: =G76+H76 -> 3795
A77: =IF(D77<>"", ROW()-1, "") -> 76 | B77: HCFM-0541 | C77: =VLOOKUP(B77,MEMBERS!B:C,2, ) -> MR.SHAN ELAHI SEHGAL | D77: 45995 | E77: 1 | F77: SEPRATE RICE | G77: =IFERROR(VLOOKUP(F77,'menu list'!B:C,2,FALSE)*E77,"0") -> 300 | H77: =G77*15/100 -> 45 | I77: =G77+H77 -> 345
A78: =IF(D78<>"", ROW()-1, "") -> 77 | B78: HCFM-0541 | C78: =VLOOKUP(B78,MEMBERS!B:C,2, ) -> MR.SHAN ELAHI SEHGAL | D78: 45995 | E78: 1 | F78: CHICKEN PATTIES | G78: =IFERROR(VLOOKUP(F78,'menu list'!B:C,2,FALSE)*E78,"0") -> 100 | H78: =G78*15/100 -> 15 | I78: =G78+H78 -> 115
... A100: =IF(D100<>"", ROW()-1, "") -> 99 | B100: HCFM-0581 | C100: =VLOOKUP(B100,MEMBERS!B:C,2, ) -> BRIG DR. GHULAM MEHDI (Retd) | D100: 45994 | E100: 1 | F100: ASSORTED COOKIES | G100: =IFERROR(VLOOKUP(F100,'menu list'!B:C,2,FALSE)*E100,"0") -> 400 | H100: =G100*15/100 -> 60 | I100: =G100+H100 -> 460
A101: =IF(D101<>"", ROW()-1, "") -> 100 | B101: HCFM-0646 | C101: =VLOOKUP(B101,MEMBERS!B:C,2, ) -> BAHRIA INTERNATIONAL HOSPITAL | D101: 45994 | E101: 30 | F101: CHICKEN PATTIES | G101: =IFERROR(VLOOKUP(F101,'menu list'!B:C,2,FALSE)*E101,"0") -> 3000 | I101: =G101+H101 -> 3000
A102: =IF(D102<>"", ROW()-1, "") -> 101 | B102: HCFM-0646 | C102: =VLOOKUP(B102,MEMBERS!B:C,2, ) -> BAHRIA INTERNATIONAL HOSPITAL | D102: 45994 | E102: 16 | F102: ASSORTED PASTRY | G102: =IFERROR(VLOOKUP(F102,'menu list'!B:C,2,FALSE)*E102,"0") -> 4000 | I102: =G102+H102 -> 4000
A103: =IF(D103<>"", ROW()-1, "") -> 102 | B103: HCFM-0646 | C103: =VLOOKUP(B103,MEMBERS!B:C,2, ) -> BAHRIA INTERNATIONAL HOSPITAL | D103: 45994 | E103: 10 | F103: DOUGHNUTS | G103: =IFERROR(VLOOKUP(F103,'menu list'!B:C,2,FALSE)*E103,"0") -> 1500 | I103: =G103+H103 -> 1500
A104: =IF(D104<>"", ROW()-1, "") -> 103 | B104: HCFM-0641 | C104: =VLOOKUP(B104,MEMBERS!B:C,2, ) -> AAMIR RASOOL | D104: 45994 | E104: 5 | F104: HOT N SOUR SOUP | G104: =IFERROR(VLOOKUP(F104,'menu list'!B:C,2,FALSE)*E104,"0") -> 1750 | H104: =G104*15/100 -> 262.5 | I104: =G104+H104 -> 2012.5
A105: =IF(D105<>"", ROW()-1, "") -> 104 | B105: HCFM-0641 | C105: =VLOOKUP(B105,MEMBERS!B:C,2, ) -> AAMIR RASOOL | D105: 45994 | E105: 2 | F105: MINERAL WATER LARGE | G105: =IFERROR(VLOOKUP(F105,'menu list'!B:C,2,FALSE)*E105,"0") -> 300 | H105: =G105*15/100 -> 45 | I105: =G105+H105 -> 345
A106: =IF(D106<>"", ROW()-1, "") -> 105 | B106: HCFM-0661 | C106: =VLOOKUP(B106,MEMBERS!B:C,2, ) -> ARSLAN KHAN ABRO | D106: 45994 | E106: 1 | F106: CLUB SANDWICH | G106: =IFERROR(VLOOKUP(F106,'menu list'!B:C,2,FALSE)*E106,"0") -> 1250 | H106: =G106*15/100 -> 187.5 | I106: =G106+H106 -> 1437.5
A107: =IF(D107<>"", ROW()-1, "") -> 106 | B107: HCFM-0661 | C107: =VLOOKUP(B107,MEMBERS!B:C,2, ) -> ARSLAN KHAN ABRO | D107: 45994 | E107: 4 | F107: MIX TEA | G107: =IFERROR(VLOOKUP(F107,'menu list'!B:C,2,FALSE)*E107,"0") -> 800 | H107: =G107*15/100 -> 120 | I107: =G107+H107 -> 920
A108: =IF(D108<>"", ROW()-1, "") -> 107 | B108: HCFM-0661 | C108: =VLOOKUP(B108,MEMBERS!B:C,2, ) -> ARSLAN KHAN ABRO | D108: 45994 | E108: 2 | F108: MINERAL WATER LARGE | G108: =IFERROR(VLOOKUP(F108,'menu list'!B:C,2,FALSE)*E108,"0") -> 300 | H108: =G108*15/100 -> 45 | I108: =G108+H108 -> 345
A109: =IF(D109<>"", ROW()-1, "") -> 108 | B109: HCFM-0661 | C109: =VLOOKUP(B109,MEMBERS!B:C,2, ) -> ARSLAN KHAN ABRO | D109: 45994 | E109: 1 | F109: HC SPECIAL CHICKEN POPCORN | G109: =IFERROR(VLOOKUP(F109,'menu list'!B:C,2,FALSE)*E109,"0") -> 500 | H109: =G109*15/100 -> 75 | I109: =G109+H109 -> 575
A110: =IF(D110<>"", ROW()-1, "") -> 109 | B110: HCFM-0661 | C110: =VLOOKUP(B110,MEMBERS!B:C,2, ) -> ARSLAN KHAN ABRO | D110: 45994 | E110: 2 | F110: PLAIN COOKIES | G110: =IFERROR(VLOOKUP(F110,'menu list'!B:C,2,FALSE)*E110,"0") -> 800 | H110: =G110*15/100 -> 120 | I110: =G110+H110 -> 920
A111: =IF(D111<>"", ROW()-1, "") -> 110 | B111: HCFM-0650 | C111: =VLOOKUP(B111,MEMBERS!B:C,2, ) -> KHURRAM FIRDOUS | D111: 45996 | E111: 4 | F111: MINERAL WATER SMALL | G111: =IFERROR(VLOOKUP(F111,'menu list'!B:C,2,FALSE)*E111,"0") -> 400 | H111: =G111*15/100 -> 60 | I111: =G111+H111 -> 460
A112: =IF(D112<>"", ROW()-1, "") -> 111 | B112: HCFM-0650 | C112: =VLOOKUP(B112,MEMBERS!B:C,2, ) -> KHURRAM FIRDOUS | D112: 45996 | E112: 1 | F112: MINERAL WATER LARGE | G112: =IFERROR(VLOOKUP(F112,'menu list'!B:C,2,FALSE)*E112,"0") -> 150 | H112: =G112*15/100 -> 22.5 | I112: =G112+H112 -> 172.5
A113: =IF(D113<>"", ROW()-1, "") -> 112 | B113: HCFM-0650 | C113: =VLOOKUP(B113,MEMBERS!B:C,2, ) -> KHURRAM FIRDOUS | D113: 45996 | E113: 3 | F113: HOT N SOUR SOUP | G113: =IFERROR(VLOOKUP(F113,'menu list'!B:C,2,FALSE)*E113,"0") -> 1050 | H113: =G113*15/100 -> 157.5 | I113: =G113+H113 -> 1207.5
A114: =IF(D114<>"", ROW()-1, "") -> 113 | B114: HCFM-0650 | C114: =VLOOKUP(B114,MEMBERS!B:C,2, ) -> KHURRAM FIRDOUS | D114: 45996 | E114: 1 | F114: MADRASI HANDI | G114: =IFERROR(VLOOKUP(F114,'menu list'!B:C,2,FALSE)*E114,"0") -> 900 | H114: =G114*15/100 -> 135 | I114: =G114+H114 -> 1035
A115: =IF(D115<>"", ROW()-1, "") -> 114 | B115: HCFM-0650 | C115: =VLOOKUP(B115,MEMBERS!B:C,2, ) -> KHURRAM FIRDOUS | D115: 45996 | E115: 2 | F115: SHISH TAOUK | G115: =IFERROR(VLOOKUP(F115,'menu list'!B:C,2,FALSE)*E115,"0") -> 2400 | H115: =G115*15/100 -> 360 | I115: =G115+H115 -> 2760
... A149: =IF(D149<>"", ROW()-1, "") -> 148 | B149: HCFM-0510 | C149: =VLOOKUP(B149,MEMBERS!B:C,2, ) -> MR.MUHAMMAD RIZWAN | D149: 45996 | E149: 1 | F149: MINERAL WATER SMALL | G149: =IFERROR(VLOOKUP(F149,'menu list'!B:C,2,FALSE)*E149,"0") -> 100 | H149: =G149*15/100 -> 15 | I149: =G149+H149 -> 115
A150: =IF(D150<>"", ROW()-1, "") -> 149 | B150: HCFM-0646 | C150: =VLOOKUP(B150,MEMBERS!B:C,2, ) -> BAHRIA INTERNATIONAL HOSPITAL | D150: 45996 | E150: 8 | F150: PLAIN COOKIES | G150: =IFERROR(VLOOKUP(F150,'menu list'!B:C,2,FALSE)*E150,"0") -> 3200 | I150: =G150+H150 -> 3200
A151: =IF(D151<>"", ROW()-1, "") -> 150 | B151: HCFM-0646 | C151: =VLOOKUP(B151,MEMBERS!B:C,2, ) -> BAHRIA INTERNATIONAL HOSPITAL | D151: 45996 | E151: 30 | F151: CHICKEN PATTIES | G151: =IFERROR(VLOOKUP(F151,'menu list'!B:C,2,FALSE)*E151,"0") -> 3000 | I151: =G151+H151 -> 3000
A152: =IF(D152<>"", ROW()-1, "") -> 151 | B152: HCFM-0646 | C152: =VLOOKUP(B152,MEMBERS!B:C,2, ) -> BAHRIA INTERNATIONAL HOSPITAL | D152: 45996 | E152: 15 | F152: ASSORTED PASTRY | G152: =IFERROR(VLOOKUP(F152,'menu list'!B:C,2,FALSE)*E152,"0") -> 3750 | I152: =G152+H152 -> 3750
A153: =IF(D153<>"", ROW()-1, "") -> 152 | B153: HCFM-0646 | C153: =VLOOKUP(B153,MEMBERS!B:C,2, ) -> BAHRIA INTERNATIONAL HOSPITAL | D153: 45996 | E153: 6 | F153: DOUGHNUTS | G153: =IFERROR(VLOOKUP(F153,'menu list'!B:C,2,FALSE)*E153,"0") -> 900 | I153: =G153+H153 -> 900
A154: =IF(D154<>"", ROW()-1, "") -> 153 | B154: HCFM-0581 | C154: =VLOOKUP(B154,MEMBERS!B:C,2, ) -> BRIG DR. GHULAM MEHDI (Retd) | D154: 45997 | E154: 2 | F154: POMFRAT | G154: =IFERROR(VLOOKUP(F154,'menu list'!B:C,2,FALSE)*E154,"0") -> 2000 | H154: =G154*15/100 -> 300 | I154: =G154+H154 -> 2300
A155: =IF(D155<>"", ROW()-1, "") -> 154 | B155: HCFM-0581 | C155: =VLOOKUP(B155,MEMBERS!B:C,2, ) -> BRIG DR. GHULAM MEHDI (Retd) | D155: 45997 | E155: 2 | F155: JAMBO PRAWN | G155: =IFERROR(VLOOKUP(F155,'menu list'!B:C,2,FALSE)*E155,"0") -> 3600 | H155: =G155*15/100 -> 540 | I155: =G155+H155 -> 4140
A156: =IF(D156<>"", ROW()-1, "") -> 155 | B156: HCFM-0581 | C156: =VLOOKUP(B156,MEMBERS!B:C,2, ) -> BRIG DR. GHULAM MEHDI (Retd) | D156: 45997 | E156: 1 | F156: VENSION | G156: =IFERROR(VLOOKUP(F156,'menu list'!B:C,2,FALSE)*E156,"0") -> 1800 | H156: =G156*15/100 -> 270 | I156: =G156+H156 -> 2070
A157: =IF(D157<>"", ROW()-1, "") -> 156 | B157: HCFM-0581 | C157: =VLOOKUP(B157,MEMBERS!B:C,2, ) -> BRIG DR. GHULAM MEHDI (Retd) | D157: 45997 | E157: 1 | F157: PEANUT AND NIMCO | G157: =IFERROR(VLOOKUP(F157,'menu list'!B:C,2,FALSE)*E157,"0") -> 300 | H157: =G157*15/100 -> 45 | I157: =G157+H157 -> 345
A158: =IF(D158<>"", ROW()-1, "") -> 157 | B158: HCFM-0581 | C158: =VLOOKUP(B158,MEMBERS!B:C,2, ) -> BRIG DR. GHULAM MEHDI (Retd) | D158: 45997 | E158: 2 | F158: MINERAL WATER SMALL | G158: =IFERROR(VLOOKUP(F158,'menu list'!B:C,2,FALSE)*E158,"0") -> 200 | H158: =G158*15/100 -> 30 | I158: =G158+H158 -> 230
A159: =IF(D159<>"", ROW()-1, "") -> 158 | B159: HCFM-0657 | C159: =VLOOKUP(B159,MEMBERS!B:C,2, ) -> NASIR ABBAS | D159: 45997 | E159: 3 | F159: DASI QUIL BBQ | G159: =IFERROR(VLOOKUP(F159,'menu list'!B:C,2,FALSE)*E159,"0") -> 3300 | H159: =G159*15/100 -> 495 | I159: =G159+H159 -> 3795
A160: =IF(D160<>"", ROW()-1, "") -> 159 | B160: HCFM-0657 | C160: =VLOOKUP(B160,MEMBERS!B:C,2, ) -> NASIR ABBAS | D160: 45997 | E160: 3 | F160: PARTRIGE | G160: =IFERROR(VLOOKUP(F160,'menu list'!B:C,2,FALSE)*E160,"0") -> 4200 | H160: =G160*15/100 -> 630 | I160: =G160+H160 -> 4830
A161: =IF(D161<>"", ROW()-1, "") -> 160 | B161: HCFM-0657 | C161: =VLOOKUP(B161,MEMBERS!B:C,2, ) -> NASIR ABBAS | D161: 45997 | E161: 3 | F161: JAMBO PRAWN | G161: =IFERROR(VLOOKUP(F161,'menu list'!B:C,2,FALSE)*E161,"0") -> 5400 | H161: =G161*15/100 -> 810 | I161: =G161+H161 -> 6210
A162: =IF(D162<>"", ROW()-1, "") -> 161 | B162: HCFM-0657 | C162: =VLOOKUP(B162,MEMBERS!B:C,2, ) -> NASIR ABBAS | D162: 45997 | E162: 2 | F162: POMFRAT | G162: =IFERROR(VLOOKUP(F162,'menu list'!B:C,2,FALSE)*E162,"0") -> 2000 | H162: =G162*15/100 -> 300 | I162: =G162+H162 -> 2300
A163: =IF(D163<>"", ROW()-1, "") -> 162 | B163: HCFM-0657 | C163: =VLOOKUP(B163,MEMBERS!B:C,2, ) -> NASIR ABBAS | D163: 45997 | E163: 3 | F163: VENSION | G163: =IFERROR(VLOOKUP(F163,'menu list'!B:C,2,FALSE)*E163,"0") -> 5400 | H163: =G163*15/100 -> 810 | I163: =G163+H163 -> 6210
A164: =IF(D164<>"", ROW()-1, "") -> 163 | B164: HCFM-0657 | C164: =VLOOKUP(B164,MEMBERS!B:C,2, ) -> NASIR ABBAS | D164: 45997 | E164: 1 | F164: MINERAL WATER LARGE | G164: =IFERROR(VLOOKUP(F164,'menu list'!B:C,2,FALSE)*E164,"0") -> 150 | H164: =G164*15/100 -> 22.5 | I164: =G164+H164 -> 172.5
A165: =IF(D165<>"", ROW()-1, "") -> 164 | B165: HCFM-0657 | C165: =VLOOKUP(B165,MEMBERS!B:C,2, ) -> NASIR ABBAS | D165: 45997 | E165: 3 | F165: GAJAR HALWA | G165: =IFERROR(VLOOKUP(F165,'menu list'!B:C,2,FALSE)*E165,"0") -> 1350 | H165: =G165*15/100 -> 202.5 | I165: =G165+H165 -> 1552.5
... A191: =IF(D191<>"", ROW()-1, "") -> 190 | B191: HCFM-0542 | C191: =VLOOKUP(B191,MEMBERS!B:C,2, ) -> MR.HANIF AHSAN ZUBEDI | D191: 45997 | E191: 1 | F191: MALAI BOTI | G191: =IFERROR(VLOOKUP(F191,'menu list'!B:C,2,FALSE)*E191,"0") -> 1150 | H191: =G191*15/100 -> 172.5 | I191: =G191+H191 -> 1322.5
A192: =IF(D192<>"", ROW()-1, "") -> 191 | B192: HCFM-0542 | C192: =VLOOKUP(B192,MEMBERS!B:C,2, ) -> MR.HANIF AHSAN ZUBEDI | D192: 45997 | E192: 1 | F192: BEEF BOTI | G192: 900 | H192: =G192*15/100 -> 135 | I192: =G192+H192 -> 1035
A193: =IF(D193<>"", ROW()-1, "") -> 192 | B193: HCFM-0542 | C193: =VLOOKUP(B193,MEMBERS!B:C,2, ) -> MR.HANIF AHSAN ZUBEDI | D193: 45997 | E193: 1 | F193: BEEF SEEKH KABAB | G193: =IFERROR(VLOOKUP(F193,'menu list'!B:C,2,FALSE)*E193,"0") -> 1200 | H193: =G193*15/100 -> 180 | I193: =G193+H193 -> 1380
A194: =IF(D194<>"", ROW()-1, "") -> 193 | B194: HCFM-0542 | C194: =VLOOKUP(B194,MEMBERS!B:C,2, ) -> MR.HANIF AHSAN ZUBEDI | D194: 45997 | E194: 2 | F194: MINERAL WATER SMALL | G194: =IFERROR(VLOOKUP(F194,'menu list'!B:C,2,FALSE)*E194,"0") -> 200 | H194: =G194*15/100 -> 30 | I194: =G194+H194 -> 230
A195: =IF(D195<>"", ROW()-1, "") -> 194 | B195: HCFM-0542 | C195: =VLOOKUP(B195,MEMBERS!B:C,2, ) -> MR.HANIF AHSAN ZUBEDI | D195: 45997 | E195: 2 | F195: SOFT DRINKS | G195: =IFERROR(VLOOKUP(F195,'menu list'!B:C,2,FALSE)*E195,"0") -> 300 | H195: =G195*15/100 -> 45 | I195: =G195+H195 -> 345
A196: =IF(D196<>"", ROW()-1, "") -> 195 | B196: HCFM-0522 | C196: =VLOOKUP(B196,MEMBERS!B:C,2, ) -> MR.IQBAL AHMED MALLAH | D196: 45997 | E196: 1 | F196: BEEF SEEKH KABAB | G196: =IFERROR(VLOOKUP(F196,'menu list'!B:C,2,FALSE)*E196,"0") -> 1200 | H196: =G196*15/100 -> 180 | I196: =G196+H196 -> 1380
A197: =IF(D197<>"", ROW()-1, "") -> 196 | B197: HCFM-0522 | C197: =VLOOKUP(B197,MEMBERS!B:C,2, ) -> MR.IQBAL AHMED MALLAH | D197: 45997 | E197: 2 | F197: POMFRAT | G197: =IFERROR(VLOOKUP(F197,'menu list'!B:C,2,FALSE)*E197,"0") -> 2000 | H197: =G197*15/100 -> 300 | I197: =G197+H197 -> 2300
A198: =IF(D198<>"", ROW()-1, "") -> 197 | B198: HCFM-0522 | C198: =VLOOKUP(B198,MEMBERS!B:C,2, ) -> MR.IQBAL AHMED MALLAH | D198: 45997 | E198: 2 | F198: MINERAL WATER LARGE | G198: =IFERROR(VLOOKUP(F198,'menu list'!B:C,2,FALSE)*E198,"0") -> 300 | H198: =G198*15/100 -> 45 | I198: =G198+H198 -> 345
A199: =IF(D199<>"", ROW()-1, "") -> 198 | B199: HCFM-0522 | C199: =VLOOKUP(B199,MEMBERS!B:C,2, ) -> MR.IQBAL AHMED MALLAH | D199: 45997 | E199: 2 | F199: PLAIN NAAN | G199: =IFERROR(VLOOKUP(F199,'menu list'!B:C,2,FALSE)*E199,"0") -> 140 | H199: =G199*15/100 -> 21 | I199: =G199+H199 -> 161
A200: =IF(D200<>"", ROW()-1, "") -> 199 | B200: HCFM-0668 | C200: =VLOOKUP(B200,MEMBERS!B:C,2, ) -> MR. KASHIF SAEED | D200: 45997 | E200: 1 | F200: CLUB SANDWICH | G200: =IFERROR(VLOOKUP(F200,'menu list'!B:C,2,FALSE)*E200,"0") -> 1250 | H200: =G200*15/100 -> 187.5 | I200: =G200+H200 -> 1437.5
A201: =IF(D201<>"", ROW()-1, "") -> 200 | B201: HCFM-0598 | C201: =VLOOKUP(B201,MEMBERS!B:C,2, ) -> DGM FATIMA ZAHID | D201: 45997 | E201: 2 | F201: LATTE COFFEE | G201: =IFERROR(VLOOKUP(F201,'menu list'!B:C,2,FALSE)*E201,"0") -> 700 | H201: =G201*15/100 -> 105 | I201: =G201+H201 -> 805
A202: =IF(D202<>"", ROW()-1, "") -> 201 | B202: HCFM-0598 | C202: =VLOOKUP(B202,MEMBERS!B:C,2, ) -> DGM FATIMA ZAHID | D202: 45997 | E202: 1 | F202: MIX TEA | G202: =IFERROR(VLOOKUP(F202,'menu list'!B:C,2,FALSE)*E202,"0") -> 200 | H202: =G202*15/100 -> 30 | I202: =G202+H202 -> 230
A203: =IF(D203<>"", ROW()-1, "") -> 202 | B203: HCFM-0598 | C203: =VLOOKUP(B203,MEMBERS!B:C,2, ) -> DGM FATIMA ZAHID | D203: 45997 | E203: 2 | F203: PANE CAKE | G203: =IFERROR(VLOOKUP(F203,'menu list'!B:C,2,FALSE)*E203,"0") -> 900 | H203: =G203*15/100 -> 135 | I203: =G203+H203 -> 1035
A204: =IF(D204<>"", ROW()-1, "") -> 203 | B204: HCFM-0598 | C204: =VLOOKUP(B204,MEMBERS!B:C,2, ) -> DGM FATIMA ZAHID | D204: 45997 | E204: 2 | F204: MINERAL WATER SMALL | G204: =IFERROR(VLOOKUP(F204,'menu list'!B:C,2,FALSE)*E204,"0") -> 200 | H204: =G204*15/100 -> 30 | I204: =G204+H204 -> 230
... A361: =IF(D361<>"", ROW()-1, "") -> 360 | B361: HCFM-0654 | C361: =VLOOKUP(B361,MEMBERS!B:C,2, ) -> SYED JIBRAN MUSHTAQ | D361: 45998 | E361: 1 | F361: PLAIN FRIES | G361: =IFERROR(VLOOKUP(F361,'menu list'!B:C,2,FALSE)*E361,"0") -> 250 | H361: =G361*15/100 -> 37.5 | I361: =G361+H361 -> 287.5
A362: =IF(D362<>"", ROW()-1, "") -> 361 | B362: HCFM-0654 | C362: =VLOOKUP(B362,MEMBERS!B:C,2, ) -> SYED JIBRAN MUSHTAQ | D362: 45998 | E362: 6 | F362: DOUGHNUTS | G362: TAMBOLA
A363: =IF(D363<>"", ROW()-1, "") -> 362 | B363: HCFM-0654 | C363: =VLOOKUP(B363,MEMBERS!B:C,2, ) -> SYED JIBRAN MUSHTAQ | D363: 45998 | E363: 4 | F363: SUNDAY BRUNCH | G363: TAMBOLA
A364: =IF(D364<>"", ROW()-1, "") -> 363 | B364: HCFM-0586 | C364: =VLOOKUP(B364,MEMBERS!B:C,2, ) -> MR.SYED MURTAZA ALI | D364: 45998 | E364: 2 | F364: SUNDAY BRUNCH | G364: TAMBOLA
A365: =IF(D365<>"", ROW()-1, "") -> 364 | B365: HCFM-0583 | C365: =VLOOKUP(B365,MEMBERS!B:C,2, ) -> MR.CAREL HEDRIK BURGER | D365: 45998 | E365: 8 | F365: SUNDAY BRUNCH | G365: =IFERROR(VLOOKUP(F365,'menu list'!B:C,2,FALSE)*E365,"0") -> 14800 | H365: =G365*15/100 -> 2220 | I365: =G365+H365 -> 17020
A366: =IF(D366<>"", ROW()-1, "") -> 365 | B366: HCFM-0583 | C366: =VLOOKUP(B366,MEMBERS!B:C,2, ) -> MR.CAREL HEDRIK BURGER | D366: 45998 | E366: 2 | F366: MINERAL WATER LARGE | G366: =IFERROR(VLOOKUP(F366,'menu list'!B:C,2,FALSE)*E366,"0") -> 300 | H366: =G366*15/100 -> 45 | I366: =G366+H366 -> 345
A367: =IF(D367<>"", ROW()-1, "") -> 366 | B367: HCFM-0583 | C367: =VLOOKUP(B367,MEMBERS!B:C,2, ) -> MR.CAREL HEDRIK BURGER | D367: 45998 | E367: 4 | F367: LASSI | G367: =IFERROR(VLOOKUP(F367,'menu list'!B:C,2,FALSE)*E367,"0") -> 1200 | H367: =G367*15/100 -> 180 | I367: =G367+H367 -> 1380
A368: =IF(D368<>"", ROW()-1, "") -> 367 | B368: HCFM-0583 | C368: =VLOOKUP(B368,MEMBERS!B:C,2, ) -> MR.CAREL HEDRIK BURGER | D368: 45998 | E368: 2 | F368: COFFEE CAPPUCINO | G368: =IFERROR(VLOOKUP(F368,'menu list'!B:C,2,FALSE)*E368,"0") -> 700 | H368: =G368*15/100 -> 105 | I368: =G368+H368 -> 805
A369: =IF(D369<>"", ROW()-1, "") -> 368 | B369: HCFM-0588 | C369: =VLOOKUP(B369,MEMBERS!B:C,2, ) -> ZULFIQAR AHMED MEMON | D369: 45998 | E369: 8 | F369: SUNDAY BRUNCH | G369: =IFERROR(VLOOKUP(F369,'menu list'!B:C,2,FALSE)*E369,"0") -> 14800 | H369: =G369*15/100 -> 2220 | I369: =G369+H369 -> 17020
A370: =IF(D370<>"", ROW()-1, "") -> 369 | B370: HCFM-0588 | C370: =VLOOKUP(B370,MEMBERS!B:C,2, ) -> ZULFIQAR AHMED MEMON | D370: 45998 | E370: 2 | F370: MINERAL WATER LARGE | G370: =IFERROR(VLOOKUP(F370,'menu list'!B:C,2,FALSE)*E370,"0") -> 300 | H370: =G370*15/100 -> 45 | I370: =G370+H370 -> 345
A371: =IF(D371<>"", ROW()-1, "") -> 370 | B371: HCFM-0588 | C371: =VLOOKUP(B371,MEMBERS!B:C,2, ) -> ZULFIQAR AHMED MEMON | D371: 45998 | E371: 4 | F371: LASSI | G371: =IFERROR(VLOOKUP(F371,'menu list'!B:C,2,FALSE)*E371,"0") -> 1200 | H371: =G371*15/100 -> 180 | I371: =G371+H371 -> 1380
A372: =IF(D372<>"", ROW()-1, "") -> 371 | B372: HCFM-0586 | C372: =VLOOKUP(B372,MEMBERS!B:C,2, ) -> MR.SYED MURTAZA ALI | D372: 45998 | E372: 1 | F372: SUNDAY BRUNCH | G372: =IFERROR(VLOOKUP(F372,'menu list'!B:C,2,FALSE)*E372,"0") -> 1550 | H372: =G372*15/100 -> 232.5 | I372: =G372+H372 -> 1782.5
A373: =IF(D373<>"", ROW()-1, "") -> 372 | B373: HCFM-0586 | C373: =VLOOKUP(B373,MEMBERS!B:C,2, ) -> MR.SYED MURTAZA ALI | D373: 45998 | E373: 1 | F373: MINERAL WATER LARGE | G373: =IFERROR(VLOOKUP(F373,'menu list'!B:C,2,FALSE)*E373,"0") -> 150 | H373: =G373*15/100 -> 22.5 | I373: =G373+H373 -> 172.5
A374: =IF(D374<>"", ROW()-1, "") -> 373 | B374: HCFM-0586 | C374: =VLOOKUP(B374,MEMBERS!B:C,2, ) -> MR.SYED MURTAZA ALI | D374: 45998 | E374: 2 | F374: LASSI | G374: =IFERROR(VLOOKUP(F374,'menu list'!B:C,2,FALSE)*E374,"0") -> 600 | H374: =G374*15/100 -> 90 | I374: =G374+H374 -> 690
A375: =IF(D375<>"", ROW()-1, "") -> 374 | B375: HCFM-0586 | C375: =VLOOKUP(B375,MEMBERS!B:C,2, ) -> MR.SYED MURTAZA ALI | D375: 45998 | E375: 1 | F375: BLACK COFFEE | G375: =IFERROR(VLOOKUP(F375,'menu list'!B:C,2,FALSE)*E375,"0") -> 300 | H375: =G375*15/100 -> 45 | I375: =G375+H375 -> 345
A376: =IF(D376<>"", ROW()-1, "") -> 375 | B376: HCFM-0657 | C376: =VLOOKUP(B376,MEMBERS!B:C,2, ) -> NASIR ABBAS | D376: 45998 | E376: 7 | F376: SUNDAY BRUNCH | G376: =IFERROR(VLOOKUP(F376,'menu list'!B:C,2,FALSE)*E376,"0") -> 10850 | H376: =G376*15/100 -> 1627.5 | I376: =G376+H376 -> 12477.5
... A381: =IF(D381<>"", ROW()-1, "") -> 380 | B381: HCFM-0532 | C381: =VLOOKUP(B381,MEMBERS!B:C,2, ) -> MR.KHALID JAVED | D381: 45998 | E381: 1 | F381: MINERAL WATER LARGE | G381: =IFERROR(VLOOKUP(F381,'menu list'!B:C,2,FALSE)*E381,"0") -> 150 | H381: =G381*15/100 -> 22.5 | I381: =G381+H381 -> 172.5
A382: =IF(D382<>"", ROW()-1, "") -> 381 | B382: HCFM-0542 | C382: =VLOOKUP(B382,MEMBERS!B:C,2, ) -> MR.HANIF AHSAN ZUBEDI | D382: 45998 | E382: =12+2 -> 14 | F382: SUNDAY BRUNCH | G382: =IFERROR(VLOOKUP(F382,'menu list'!B:C,2,FALSE)*E382,"0") -> 21700 | H382: =G382*15/100 -> 3255 | I382: =G382+H382 -> 24955
A383: =IF(D383<>"", ROW()-1, "") -> 382 | B383: HCFM-0542 | C383: =VLOOKUP(B383,MEMBERS!B:C,2, ) -> MR.HANIF AHSAN ZUBEDI | D383: 45998 | E383: =3+1 -> 4 | F383: MINERAL WATER LARGE | G383: =IFERROR(VLOOKUP(F383,'menu list'!B:C,2,FALSE)*E383,"0") -> 600 | H383: =G383*15/100 -> 90 | I383: =G383+H383 -> 690
A384: =IF(D384<>"", ROW()-1, "") -> 383 | B384: HCFM-0542 | C384: =VLOOKUP(B384,MEMBERS!B:C,2, ) -> MR.HANIF AHSAN ZUBEDI | D384: 45998 | E384: 5 | F384: SUNDAY BRUNCH KIDS | G384: =IFERROR(VLOOKUP(F384,'menu list'!B:C,2,FALSE)*E384,"0") -> 3875 | H384: =G384*15/100 -> 581.25 | I384: =G384+H384 -> 4456.25
...

Sheet menu list
A1: HERITAGE CLUB BAHRIA TOWN KARACHI
A2: s.no | B2: product name | C2: price | D2: categories | J2: (Italian, Mexican, Chinese), the style of service (fast food, casual dining, fine dining), and the meal structure (appetizers, main courses, desserts, drinks
A3: =IF(B3<>"", ROW()-2, "") -> 1 | B3: AGAVE NECTAR | C3: 550
A4: =IF(B4<>"", ROW()-2, "") -> 2 | B4: AKBERI BOTI TIKKA | C4: 600
A5: =IF(B5<>"", ROW()-2, "") -> 3 | B5: ALMOND CAKE | C5: 1500
A6: =IF(B6<>"", ROW()-2, "") -> 4 | B6: ALMOND COOKIES | C6: 400
A7: =IF(B7<>"", ROW()-2, "") -> 5 | B7: ALMOND COOKIES 500GM | C7: 800
A8: =IF(B8<>"", ROW()-2, "") -> 6 | B8: ALOO SAMOSA | C8: 100
A9: =IF(B9<>"", ROW()-2, "") -> 7 | B9: AMBERI FISH TIKKA | C9: 1450
A10: =IF(B10<>"", ROW()-2, "") -> 8 | B10: AMERICAN ALMOND BROWNE | C10: 400
A11: =IF(B11<>"", ROW()-2, "") -> 9 | B11: AMERICAN CHOPSUEY | C11: 950
A12: =IF(B12<>"", ROW()-2, "") -> 10 | B12: APPLE JUICE | C12: 200
A13: =IF(B13<>"", ROW()-2, "") -> 11 | B13: APPLE PIE | C13: 450
A14: =IF(B14<>"", ROW()-2, "") -> 12 | B14: APPLE PIE ALA MODE | C14: 300
... A56: =IF(B56<>"", ROW()-2, "") -> 54 | B56: BUFFET LUNCH | C56: 3000
A57: =IF(B57<>"", ROW()-2, "") -> 55 | B57: BUFFET PARTY | C57: 3700 | D57: FOR ASHOK KUMAR
A58: =IF(B58<>"", ROW()-2, "") -> 56 | B58: BUN | C58: 60
A59: =IF(B59<>"", ROW()-2, "") -> 57 | B59: BUTTER CHICKEN | C59: 750
A60: =IF(B60<>"", ROW()-2, "") -> 58 | B60: BUTTER NAAN | C60: 150
A61: =IF(B61<>"", ROW()-2, "") -> 59 | B61: CAKE PLATE | C61: 200
A62: =IF(B62<>"", ROW()-2, "") -> 60 | B62: CAPPUCCINO COFFEE | C62: 350
A63: =IF(B63<>"", ROW()-2, "") -> 61 | B63: CHANDAN KABAB | C63: 1500
A64: =IF(B64<>"", ROW()-2, "") -> 62 | B64: CHEESE CAKE | C64: 350
A65: =IF(B65<>"", ROW()-2, "") -> 63 | B65: CHEESE NAAN | C65: 200
A66: =IF(B66<>"", ROW()-2, "") -> 64 | B66: CHEESE PASTRY | C66: 250
A67: =IF(B67<>"", ROW()-2, "") -> 65 | B67: CHICKEN BIRYANI | C67: 600
A68: =IF(B68<>"", ROW()-2, "") -> 66 | B68: CHICKEN BURGER | C68: 550
A69: =IF(B69<>"", ROW()-2, "") -> 67 | B69: CHICKEN CAESAR SALAD | C69: 1200
... A201: =IF(B201<>"", ROW()-2, "") -> 199 | B201: HENCHI CANE BEER | C201: 1500
A202: =IF(B202<>"", ROW()-2, "") -> 200 | B202: HOT COFFEE | C202: 300 | Q202: F
A203: =IF(B203<>"", ROW()-2, "") -> 201 | B203: HOT GARLIC PRAWNS | C203: 1600
A204: =IF(B204<>"", ROW()-2, "") -> 202 | B204: HOT N SOUR SOUP | C204: 350
A205: =IF(B205<>"", ROW()-2, "") -> 203 | B205: ICE | C205: 100
A206: =IF(B206<>"", ROW()-2, "") -> 204 | B206: ICE CREAM DOUBLE SCOOP | C206: 220
A207: =IF(B207<>"", ROW()-2, "") -> 205 | B207: ICE CREAM SINGLE SCOOP | C207: 120
A208: =IF(B208<>"", ROW()-2, "") -> 206 | B208: ICE CREAM TRIPLE SCOOP | C208: 330
A209: =IF(B209<>"", ROW()-2, "") -> 207 | B209: J DANIEL DOUBLE | C209: 2000
A210: =IF(B210<>"", ROW()-2, "") -> 208 | B210: J DANIEL SINGLE | C210: 1000
A211: =IF(B211<>"", ROW()-2, "") -> 209 | B211: JAM COOKIES | C211: 400
A212: =IF(B212<>"", ROW()-2, "") -> 210 | B212: JAM COOKIES 500GM | C212: 800
A213: =IF(B213<>"", ROW()-2, "") -> 211 | B213: JASMINE TEA | C213: 250
A214: =IF(B214<>"", ROW()-2, "") -> 212 | B214: JELLY PUDDING SLICE | C214: 150
... A267: =IF(B267<>"", ROW()-2, "") -> 265 | B267: MUTTON STEW | C267: 1950
A268: =IF(B268<>"", ROW()-2, "") -> 266 | B268: NAWABI KABAB | C268: 1400 | P268: 1
A269: =IF(B269<>"", ROW()-2, "") -> 267 | B269: ORANGE JUICE | C269: 200
A270: =IF(B270<>"", ROW()-2, "") -> 268 | B270: OREO CAKE | C270: 2800
A271: =IF(B271<>"", ROW()-2, "") -> 269 | B271: OREO PASTRY | C271: 250
A272: =IF(B272<>"", ROW()-2, "") -> 270 | B272: OREO SHAKE | C272: 450
A273: =IF(B273<>"", ROW()-2, "") -> 271 | B273: PEACH MOJITO | C273: 399
A274: =IF(B274<>"", ROW()-2, "") -> 272 | B274: PAKISTANI OMELETTE | C274: 300
A275: =IF(B275<>"", ROW()-2, "") -> 273 | B275: PANE CAKE | C275: 450
A276: =IF(B276<>"", ROW()-2, "") -> 274 | B276: PANEER RESHMI HANDI | C276: 1000
A277: =IF(B277<>"", ROW()-2, "") -> 275 | B277: PASTA | C277: 1200
A278: =IF(B278<>"", ROW()-2, "") -> 276 | B278: PEANUT AND NIMCO | C278: 300
A279: =IF(B279<>"", ROW()-2, "") -> 277 | B279: PEG BALLANTINES SINGLE | C279: 550
A280: =IF(B280<>"", ROW()-2, "") -> 278 | B280: CHIVAS SINGLE PEG | C280: 750
... A480: =IF(B480<>"", ROW()-2, "") -> 478 | B480: BUFFET DINNER KIDS | C480: 1250

Sheet EXTRACT
A9: Row Labels | B9: Sum of AMOUNT | C9: Sum of sst 15% | F9: Row Labels | G9: Sum of Bowling Alley | H9: Sum of Gym | I9: Sum of Family Pool | J9: Sum of Squash Court | K9: Sum of Ladies Pool | L9: Sum of Amusement Arcade | M9: Sum of Cinema | N9: Sum of Cigar Lounge | O9: Sum of Pool Lockers | P9: Sum of SPA | Q9: Sum of Padel Court | R9: Sum of Ladies Saloon | S9: Sum of Gym Sub | T9: Sum of HC Chambers | U9: Sum of Vanue Charges | V9: Sum of PARTY CHARGES
A10: 45992 | B10: 20219 | C10: 3032.85 | F10: 45992 | G10: 1800 | H10: 1200 | I10: 0 | J10: 0 | K10: 0 | L10: 300 | M10: 0 | N10: 0 | O10: 0 | P10: 0 | Q10: 0 | R10: 0 | S10: 0 | T10: 0 | U10: 0 | V10: 0
A11: 45993 | B11: 35314 | C11: 3879.6 | F11: 45993 | G11: 1200 | H11: 2700 | I11: 150 | J11: 0 | K11: 0 | L11: 600 | M11: 0 | N11: 0 | O11: 0 | P11: 0 | Q11: 0 | R11: 0 | S11: 0 | T11: 0 | U11: 0 | V11: 0
A12: 45994 | B12: 22550 | C12: 2107.5 | F12: 45994 | G12: 0 | H12: 2250 | I12: 0 | J12: 0 | K12: 0 | L12: 0 | M12: 0 | N12: 0 | O12: 0 | P12: 0 | Q12: 0 | R12: 5000 | S12: 0 | T12: 0 | U12: 0 | V12: 0
A13: 45995 | B13: 17530 | C13: 2629.5 | F13: 45995 | G13: 0 | H13: 1950 | I13: 0 | J13: 0 | K13: 0 | L13: 4600 | M13: 0 | N13: 0 | O13: 0 | P13: 0 | Q13: 0 | R13: 16000 | S13: 0 | T13: 0 | U13: 0 | V13: 0
A14: 45996 | B14: 36240 | C14: 3808.5 | F14: 45996 | G14: 3600 | H14: 1950 | I14: 0 | J14: 0 | K14: 0 | L14: 5400 | M14: 0 | N14: 0 | O14: 0 | P14: 0 | Q14: 11500 | R14: 0 | S14: 0 | T14: 0 | U14: 0 | V14: 0
A15: 45997 | B15: 233400 | C15: 35010 | F15: 45997 | G15: 7500 | H15: 1500 | I15: 0 | J15: 0 | K15: 0 | L15: 11000 | M15: 300 | N15: 0 | O15: 0 | P15: 0 | Q15: 22950 | R15: 0 | S15: 0 | T15: 0 | U15: 0 | V15: 0
A16: 45998 | B16: 157350 | C16: 23602.5 | F16: 45998 | G16: 11100 | H16: 750 | I16: 0 | J16: 0 | K16: 0 | L16: 14200 | M16: 0 | N16: 0 | O16: 0 | P16: 3000 | Q16: 0 | R16: 20500 | S16: 0 | T16: 0 | U16: 0 | V16: 0
A17: 45999 | B17: 23265 | C17: 3489.75 | F17: 45999 | G17: 0 | H17: 1500 | I17: 0 | J17: 0 | K17: 0 | L17: 600 | M17: 0 | N17: 0 | O17: 0 | P17: 0 | Q17: 0 | R17: 0 | S17: 0 | T17: 0 | U17: 0 | V17: 0
A18: 46000 | B18: 37589 | C18: 4385.85 | F18: 46000 | G18: 1500 | H18: 2550 | I18: 0 | J18: 0 | K18: 0 | L18: 0 | M18: 0 | N18: 0 | O18: 0 | P18: 0 | Q18: 0 | R18: 20500 | S18: 0 | T18: 0 | U18: 0 | V18: 0
A19: 46001 | B19: 27209 | C19: 4081.35 | F19: 46001 | G19: 0 | H19: 2550 | I19: 0 | J19: 0 | K19: 0 | L19: 900 | M19: 7500 | N19: 0 | O19: 0 | P19: 0 | Q19: 0 | R19: 2950 | S19: 0 | T19: 0 | U19: 0 | V19: 0
A20: 46002 | B20: 14238 | C20: 2135.7 | F20: 46002 | G20: 0 | H20: 1800 | I20: 0 | J20: 0 | K20: 0 | L20: 0 | M20: 0 | N20: 0 | O20: 0 | P20: 0 | Q20: 0 | R20: 12000 | S20: 0 | T20: 0 | U20: 5000 | V20: 0
A21: 46003 | B21: 83201 | C21: 11137.65 | F21: 46003 | G21: 2700 | H21: 1050 | I21: 150 | J21: 0 | K21: 0 | L21: 5800 | M21: 0 | N21: 0 | O21: 0 | P21: 0 | Q21: 0 | R21: 0 | S21: 0 | T21: 0 | U21: 150000 | V21: 0
... A34: 46016 | B34: 235737 | C34: 35360.55 | F34: 46016 | G34: 8100 | H34: 600 | I34: 0 | J34: 0 | K34: 0 | L34: 5700 | M34: 300 | N34: 0 | O34: 0 | P34: 0 | Q34: 10000 | R34: 6500 | S34: 0 | T34: 0 | U34: 0 | V34: 0
A35: Grand Total | B35: 5319274 | C35: 784571.1 | F35: Grand Total | G35: 89100 | H35: 34050 | I35: 1500 | J35: 7500 | K35: 300 | L35: 109100 | M35: 17000 | N35: 0 | O35: 200 | P35: 3000 | Q35: 78450 | R35: 261400 | S35: 0 | T35: 0 | U35: 635000 | V35: 508000

Sheet REPORT
A1: BAHRIA HERITAGE CLUB
A2: DAILY SALE REPORT
A3: FROM 1ST-DEC-2025, TILL 25TH-DEC-2025.
A4: S.no | B4: Date | C4: Bowling Alley | D4: Gym | E4: Family Pool | F4: Squash Court | G4: Ladies Pool | H4: Amusement Arcade | I4: Cinema | J4: Cigar launge | K4: Pool Lockers | L4: SPA | M4: Padel Court | N4: Ladies Saloon | O4: HC Chambers | P4: Gym Sub | Q4: Vanue Charges | R4: Party Charges | S4: Food And beverages | T4: TOTAL
A5: 1 | B5: 45992 | C5: 1800 | D5: 1200 | E5: 0 | F5: 0 | G5: 0 | H5: 300 | I5: 0 | J5: 0 | K5: 0 | L5: 0 | M5: 0 | N5: 0 | O5: 0 | P5: 0 | Q5: 0 | R5: 0 | S5: 20219 | T5: =SUM(C5:S5) -> 23519 | U5: 29769 | V5: =T5-U5 -> -6250
A6: 2 | B6: 45993 | C6: 1200 | D6: 2700 | E6: 150 | F6: 0 | G6: 0 | H6: 600 | I6: 0 | J6: 0 | K6: 0 | L6: 0 | M6: 0 | N6: 0 | O6: 0 | P6: 0 | Q6: 0 | R6: 0 | S6: 35314 | T6: =SUM(C6:S6) -> 39964 | U6: 32509 | V6: =T6-U6 -> 7455
A7: 3 | B7: 45994 | C7: 0 | D7: 2250 | E7: 0 | F7: 0 | G7: 0 | H7: 0 | I7: 0 | J7: 0 | K7: 0 | L7: 0 | M7: 0 | N7: 5000 | O7: 0 | P7: 0 | Q7: 0 | R7: 0 | S7: 22550 | T7: =SUM(C7:S7) -> 29800 | U7: 30250 | V7: =T7-U7 -> -450
A8: 4 | B8: 45995 | C8: 0 | D8: 1950 | E8: 0 | F8: 0 | G8: 0 | H8: 4600 | I8: 0 | J8: 0 | K8: 0 | L8: 0 | M8: 0 | N8: 16000 | O8: 0 | P8: 0 | Q8: 0 | R8: 0 | S8: 17530 | T8: =SUM(C8:S8) -> 40080 | U8: 39970 | V8: =T8-U8 -> 110
A9: 5 | B9: 45996 | C9: 3600 | D9: 1950 | E9: 0 | F9: 0 | G9: 0 | H9: 5400 | I9: 0 | J9: 0 | K9: 0 | L9: 0 | M9: 11500 | N9: 0 | O9: 0 | P9: 0 | Q9: 0 | R9: 0 | S9: 36240 | T9: =SUM(C9:S9) -> 58690 | U9: 58890 | V9: =T9-U9 -> -200
A10: 6 | B10: 45997 | C10: 7500 | D10: 1500 | E10: 0 | F10: 0 | G10: 0 | H10: 11000 | I10: 300 | J10: 0 | K10: 0 | L10: 0 | M10: 22950 | N10: 0 | O10: 0 | P10: 0 | Q10: 0 | R10: 0 | S10: 233400 | T10: =SUM(C10:S10) -> 276650 | U10: 283840 | V10: =T10-U10 -> -7190
A11: 7 | B11: 45998 | C11: 11100 | D11: 750 | E11: 0 | F11: 0 | G11: 0 | H11: 14200 | I11: 0 | J11: 0 | K11: 0 | L11: 3000 | M11: 0 | N11: 20500 | O11: 0 | P11: 0 | Q11: 0 | R11: 0 | S11: 157350 | T11: =SUM(C11:S11) -> 206900 | U11: 243600 | V11: =T11-U11 -> -36700
A12: 8 | B12: 45999 | C12: 0 | D12: 1500 | E12: 0 | F12: 0 | G12: 0 | H12: 600 | I12: 0 | J12: 0 | K12: 0 | L12: 0 | M12: 0 | N12: 0 | O12: 0 | P12: 0 | Q12: 0 | R12: 0 | S12: 23265 | T12: =SUM(C12:S12) -> 25365 | U12: 26990 | V12: =T12-U12 -> -1625
A13: 9 | B13: 46000 | C13: 1500 | D13: 2550 | E13: 0 | F13: 0 | G13: 0 | H13: 0 | I13: 0 | J13: 0 | K13: 0 | L13: 0 | M13: 0 | N13: 20500 | O13: 0 | P13: 0 | Q13: 0 | R13: 0 | S13: 37589 | T13: =SUM(C13:S13) -> 62139 | U13: 55300 | V13: =T13-U13 -> 6839
A14: 10 | B14: 46001 | C14: 0 | D14: 2550 | E14: 0 | F14: 0 | G14: 0 | H14: 900 | I14: 7500 | J14: 0 | K14: 0 | L14: 0 | M14: 0 | N14: 2950 | O14: 0 | P14: 0 | Q14: 0 | R14: 0 | S14: 27209 | T14: =SUM(C14:S14) -> 41109 | U14: 41809 | V14: =T14-U14 -> -700
A15: 11 | B15: 46002 | C15: 0 | D15: 1800 | E15: 0 | F15: 0 | G15: 0 | H15: 0 | I15: 0 | J15: 0 | K15: 0 | L15: 0 | M15: 0 | N15: 12000 | O15: 0 | P15: 0 | Q15: 5000 | R15: 0 | S15: 14238 | T15: =SUM(C15:S15) -> 33038 | U15: 31558 | V15: =T15-U15 -> 1480
A16: 12 | B16: 46003 | C16: 2700 | D16: 1050 | E16: 150 | F16: 0 | G16: 0 | H16: 5800 | I16: 0 | J16: 0 | K16: 0 | L16: 0 | M16: 0 | N16: 0 | O16: 0 | P16: 0 | Q16: 150000 | R16: 0 | S16: 83201 | T16: =SUM(C16:S16) -> 242901 | U16: 241401 | V16: =T16-U16 -> 1500
A17: 13 | B17: 46004 | C17: 1800 | D17: 1050 | E17: 0 | F17: 0 | G17: 0 | H17: 4000 | I17: 300 | J17: 0 | K17: 0 | L17: 0 | M17: 0 | N17: 11500 | O17: 0 | P17: 0 | Q17: 0 | R17: 143000 | S17: 223374 | T17: =SUM(C17:S17) -> 385024 | U17: 384824 | V17: =T17-U17 -> 200
A18: 14 | B18: 46005 | C18: 12300 | D18: 1050 | E18: 0 | F18: 900 | G18: 0 | H18: 12300 | I18: 0 | J18: 0 | K18: 0 | L18: 0 | M18: 5500 | N18: 20000 | O18: 0 | P18: 0 | Q18: 0 | R18: 0 | S18: 156695 | T18: =SUM(C18:S18) -> 208745 | U18: 208525 | V18: =T18-U18 -> 220 | W18: MISTAKE IN TOTAL
A19: 15 | B19: 46006 | C19: 0 | D19: 1200 | E19: 0 | F19: 0 | G19: 0 | H19: 0 | I19: 900 | J19: 0 | K19: 0 | L19: 0 | M19: 0 | N19: 0 | O19: 0 | P19: 0 | Q19: 0 | R19: 0 | S19: 7380 | T19: =SUM(C19:S19) -> 9480 | U19: 9480 | V19: =T19-U19 -> 0
A20: 16 | B20: 46007 | C20: 1500 | D20: 1800 | E20: 0 | F20: 0 | G20: 0 | H20: 800 | I20: 0 | J20: 0 | K20: 0 | L20: 0 | M20: 0 | N20: 2000 | O20: 0 | P20: 0 | Q20: 0 | R20: 0 | S20: 32658 | T20: =SUM(C20:S20) -> 38758 | U20: 38758 | V20: =T20-U20 -> 0
A21: 17 | B21: 46008 | C21: 0 | D21: 1800 | E21: 0 | F21: 0 | G21: 0 | H21: 4000 | I21: 4700 | J21: 0 | K21: 0 | L21: 0 | M21: 6000 | N21: 6000 | O21: 0 | P21: 0 | Q21: 0 | R21: 0 | S21: 46908 | T21: =SUM(C21:S21) -> 69408 | U21: 70008 | V21: =T21-U21 -> -600
A22: 18 | B22: 46009 | C22: 0 | D22: 0 | E22: 0 | F22: 0 | G22: 0 | H22: 4100 | I22: 0 | J22: 0 | K22: 0 | L22: 0 | M22: 6000 | N22: 38650 | O22: 0 | P22: 0 | Q22: 0 | R22: 0 | S22: 20799 | T22: =SUM(C22:S22) -> 69549 | V22: =T22-U22 -> 69549
A23: 19 | B23: 46010 | C23: 1800 | D23: 1200 | E23: 0 | F23: 0 | G23: 0 | H23: 3200 | I23: 0 | J23: 0 | K23: 0 | L23: 0 | M23: 0 | N23: 11750 | O23: 0 | P23: 0 | Q23: 0 | R23: 0 | S23: 31595 | T23: =SUM(C23:S23) -> 49545 | V23: =T23-U23 -> 49545
A24: 20 | B24: 46011 | C24: 6600 | D24: 750 | E24: 0 | F24: 0 | G24: 0 | H24: 6300 | I24: 0 | J24: 0 | K24: 0 | L24: 0 | M24: 0 | N24: 40300 | O24: 0 | P24: 0 | Q24: 0 | R24: 0 | S24: 111364 | T24: =SUM(C24:S24) -> 165314 | V24: =T24-U24 -> 165314
A25: 21 | B25: 46012 | C25: 10500 | D25: 300 | E25: 1200 | F25: 3600 | G25: 0 | H25: 7700 | I25: 300 | J25: 0 | K25: 200 | L25: 0 | M25: 16500 | N25: 7500 | O25: 0 | P25: 0 | Q25: 0 | R25: 365000 | S25: 379588 | T25: =SUM(C25:S25) -> 792388 | V25: =T25-U25 -> 792388
A26: 22 | B26: 46013 | C26: 10200 | D26: 750 | E26: 0 | F26: 0 | G26: 0 | H26: 8200 | I26: 0 | J26: 0 | K26: 0 | L26: 0 | M26: 0 | N26: 0 | O26: 0 | P26: 0 | Q26: 0 | R26: 0 | S26: 147243 | T26: =SUM(C26:S26) -> 166393 | V26: =T26-U26 -> 166393
A27: 23 | B27: 46014 | C27: 5400 | D27: 1200 | E27: 0 | F27: 0 | G27: 0 | H27: 7700 | I27: 0 | J27: 0 | K27: 0 | L27: 0 | M27: 0 | N27: 28750 | O27: 0 | P27: 0 | Q27: 0 | R27: 0 | S27: 77700 | T27: =SUM(C27:S27) -> 120750 | V27: =T27-U27 -> 120750
A28: 24 | B28: 46015 | C28: 1500 | D28: 600 | E28: 0 | F28: 3000 | G28: 300 | H28: 1700 | I28: 2700 | J28: 0 | K28: 0 | L28: 0 | M28: 0 | N28: 11500 | O28: 0 | P28: 0 | Q28: 480000 | R28: 0 | S28: 3140128 | T28: =SUM(C28:S28) -> 3641428 | V28: =T28-U28 -> 3641428
A29: 25 | B29: 46016 | C29: 8100 | D29: 600 | E29: 0 | F29: 0 | G29: 0 | H29: 5700 | I29: 300 | J29: 0 | K29: 0 | L29: 0 | M29: 10000 | N29: 6500 | O29: 0 | P29: 0 | Q29: 0 | R29: 0 | S29: 235737 | T29: =SUM(C29:S29) -> 266937 | U29: 247040 | V29: =T29-U29 -> 19897
B30: TOTAL | C30: =SUM(C5:C29) -> 89100 | D30: =SUM(D5:D29) -> 34050 | E30: =SUM(E5:E29) -> 1500 | F30: =SUM(F5:F29) -> 7500 | G30: =SUM(G5:G29) -> 300 | H30: =SUM(H5:H29) -> 109100 | I30: =SUM(I5:I29) -> 17000 | J30: =SUM(J5:J29) -> 0 | ... T30: =SUM(T5:T29) -> 7063874 | V30: =T30-U30 -> 7063874
E31: TOTAL SALE | H31: =T30 -> 7063874
E32: 15 % SST ON ONLY F& B | H32: ='data base '!U124 -> 791409.9
E33: TOTAL MONTHLY CHARGES | H33: 819000
E34: GRAND TOTAL | H34: =SUM(H31:H33) -> 8674283.9

Sheet CARD SALE
A4: DATE | B4: INVOICE NUMBER | C4: BATCH NO | D4: transaction_amount | E4: mdr_deducted | F4: fed_deducted | G4: net_payout_amount | H4: facility | I4: MEMBER SHIP ID /GUEST | J4: name
A5: 45984.941 | B5: 000146 | C5: 000018 | D5: 6140 | E5: =+D5*1.5/100 -> 92.1 | F5: =E5*15/100 -> 13.815 | G5: =D5-E5-F5 -> 6034.085 | H5: PADDLE | I5: HCFM-0683 | J5: yasir awan
A6: 45985.941 | B6: 000147 | C6: 000018 | D6: 6375 | E6: =+D6*1.5/100 -> 95.625 | F6: =E6*15/100 -> 14.34375 | G6: =D6-E6-F6 -> 6265.0312 | H6: SALOON | I6: GUEST | J6: AAYAT ZUBAIR
A7: 45986.941 | B7: 000149 | C7: 000018 | D7: 6140 | E7: =+D7*1.5/100 -> 92.1 | F7: =E7*15/100 -> 13.815 | G7: =D7-E7-F7 -> 6034.085 | H7: PADDLE | I7: HCFM-0683 | J7: yasir awan
A8: 45987.941 | B8: 000151 | C8: 000018 | D8: 1020 | E8: =+D8*1.5/100 -> 15.3 | F8: =E8*15/100 -> 2.295 | G8: =D8-E8-F8 -> 1002.405 | H8: SALOON | I8: GUEST
A9: 45988.941 | B9: 000152 | C9: 000018 | D9: 6140 | E9: =+D9*1.5/100 -> 92.1 | F9: =E9*15/100 -> 13.815 | G9: =D9-E9-F9 -> 6034.085 | H9: PADDLE | I9: HCFM-0683 | J9: yasir awan
A10: 45989.941 | B10: 000153 | C10: 000018 | D10: 1020 | E10: =+D10*1.5/100 -> 15.3 | F10: =E10*15/100 -> 2.295 | G10: =D10-E10-F10 -> 1002.405 | H10: KIDS PLAY ARE | I10: HCFM-0664 | J10: SHAHBAZ
A11: 45990.941 | B11: 000157 | C11: 000018 | D11: 7038 | E11: =+D11*1.5/100 -> 105.57 | F11: =E11*15/100 -> 15.8355 | G11: =D11-E11-F11 -> 6916.5945 | H11: SALOON
A12: 45991.941 | B12: 000158 | C12: 000018 | D12: 6140 | E12: =+D12*1.5/100 -> 92.1 | F12: =E12*15/100 -> 13.815 | G12: =D12-E12-F12 -> 6034.085 | H12: PADDLE | I12: HCFM-0683 | J12: yasir awan
A13: 45991.941 | B13: 000159 | C13: 000018 | D13: 142227.78 | E13: =+D13*1.5/100 -> 2133.4167 | F13: =E13*15/100 -> 320.0125 | G13: =D13-E13-F13 -> 139774.35
A14: 45993.941 | B14: 000177 | C14: 000019 | D14: 2040 | E14: =+D14*1.5/100 -> 30.6 | F14: =E14*15/100 -> 4.59 | G14: =D14-E14-F14 -> 2004.81
A15: 45994.941 | B15: 000176 | C15: 000019 | D15: 35109 | E15: =+D15*1.5/100 -> 526.635 | F15: =E15*15/100 -> 78.99525 | G15: =D15-E15-F15 -> 34503.37
A16: 45995.941 | B16: 000175 | C16: 000019 | D16: 10200 | E16: =+D16*1.5/100 -> 153 | F16: =E16*15/100 -> 22.95 | G16: =D16-E16-F16 -> 10024.05
A17: 45996.941 | B17: 000174 | C17: 000019 | D17: 5100 | E17: =+D17*1.5/100 -> 76.5 | F17: =E17*15/100 -> 11.475 | G17: =D17-E17-F17 -> 5012.025
A18: 45997.941 | B18: 000172 | C18: 000019 | D18: 1173 | E18: =+D18*1.5/100 -> 17.595 | F18: =E18*15/100 -> 2.63925 | G18: =D18-E18-F18 -> 1152.7658
A19: 45998.941 | B19: 000171 | C19: 000019 | D19: 2448 | E19: =+D19*1.5/100 -> 36.72 | F19: =E19*15/100 -> 5.508 | G19: =D19-E19-F19 -> 2405.772
A20: 45999.941 | B20: 000170 | C20: 000019 | D20: 12240 | E20: =+D20*1.5/100 -> 183.6 | F20: =E20*15/100 -> 27.54 | G20: =D20-E20-F20 -> 12028.86
A21: 46000.941 | B21: 000169 | C21: 000019 | D21: 821 | E21: =+D21*1.5/100 -> 12.315 | F21: =E21*15/100 -> 1.84725 | G21: =D21-E21-F21 -> 806.83775
A22: 46001.941 | B22: 000168 | C22: 000019 | D22: 20910 | E22: =+D22*1.5/100 -> 313.65 | F22: =E22*15/100 -> 47.0475 | G22: =D22-E22-F22 -> 20549.302
A23: 46002.941 | B23: 000166 | C23: 000019 | D23: 500 | E23: =+D23*1.5/100 -> 7.5 | F23: =E23*15/100 -> 1.125 | G23: =D23-E23-F23 -> 491.375
A24: 46003.941 | B24: 000165 | C24: 000019 | D24: 2448 | E24: =+D24*1.5/100 -> 36.72 | F24: =E24*15/100 -> 5.508 | G24: =D24-E24-F24 -> 2405.772
... A26: 46005.941 | B26: 000163 | C26: 000019 | D26: 6140 | E26: =+D26*1.5/100 -> 92.1 | F26: =E26*15/100 -> 13.815 | G26: =D26-E26-F26 -> 6034.085

Sheet BILL
C1: HERITAGE CLUB
C2: BANK INFORMATION A/C TITLE : PARKLANE HOTELS & RESORTS PVT LTD HERITAGE CLUB BANK : UBL A/C NO : 0339-310426415
A3: EVENTS | C3: HCFM-0503 | F3: =VLOOKUP(C3,MEMBERS!B:C,2, ) -> MR.GHULAM NABI OTHI
C4: SUMMARY
C5: PAYABLE AMOUNT FOR THE MONTH OF OCTOBER | F5: =F8+F10+F11-F9 -> 72464.7
C6: LATE PAYMENT SURCHARGE | F6: =F11*0.1 -> 7246.47
C7: TOTAL AMOUNT AFTER DUE DATE | F7: =F5+F6 -> 79711.17
C8: AREARS | F8: =SUMIFS('FIXED AMOUNT'!E:E,'FIXED AMOUNT'!B:B,BILL!C3) -> 0
C9: ADVANCED PAID | F9: =SUMIFS('FIXED AMOUNT'!F:F,'FIXED AMOUNT'!B:B,BILL!C3) -> 0
C10: REMAINING MANDATORY DINE IN CHARGE | F10: =F39 -> 0
C11: TOTAL DUE | F11: =SUM(F17,F35) -> 72464.7
C12: DUE DATE | F12: 15th NOVEMBER 2025
C13: FIXED CHARGES
C14: MONTHLY SUBSCRIPTION | F14: =SUMIFS('FIXED AMOUNT'!G:G,'FIXED AMOUNT'!B:B,BILL!C3) -> 7000
C15: SPORTS SUBSCRIPTION | F15: =SUMIFS(FACILITIES!R:R,FACILITIES!B:B,BILL!C3) -> 0
C16: OTHERS (POOL LOCKER) | F16: =SUMIFS(FACILITIES!M:M,FACILITIES!B:B,BILL!C3) -> 0
C17: SUB TOTAL | F17: =SUM(F14:F16) -> 7000
C18: USAGE CHARGES
C19: FOOD & BEVERAGES | F19: =SUMIFS('F & B'!G:G,'F & B'!B:B,BILL!C3) -> 52578
C20: SPA | F20: =SUMIFS(FACILITIES!N:N,FACILITIES!B:B,BILL!C3) -> 0
C21: GYM | F21: =SUMIFS(FACILITIES!F:F,FACILITIES!B:B,BILL!C3) -> 0
C22: BOWLING ALLEY | F22: =SUMIFS(FACILITIES!E:E,FACILITIES!B:B,BILL!C3) -> 0
C23: CHILDERN PLAY AREA | F23: =SUMIFS(FACILITIES!J:J,FACILITIES!B:B,BILL!C3) -> 0
C24: FAMILY POOL | F24: =SUMIFS(FACILITIES!G:G,FACILITIES!B:B,BILL!C3) -> 0
C25: LADIES POOL | F25: =SUMIFS(FACILITIES!I:I,FACILITIES!B:B,BILL!C3) -> 0
C26: SQUASH COURT | F26: =SUMIFS(FACILITIES!H:H,FACILITIES!B:B,BILL!C3) -> 0
C27: CINEMA | F27: =SUMIFS(FACILITIES!K:K,FACILITIES!B:B,BILL!C3) -> 0
C28: VANUE CHARGES | F28: =SUMIFS(FACILITIES!S:S,FACILITIES!B:B,BILL!C3) -> 5000
C29: PADEL COURT | F29: =SUMIFS(FACILITIES!O:O,FACILITIES!B:B,BILL!C3) -> 0
C30: LADIES SALON | F30: =SUMIFS(FACILITIES!P:P,FACILITIES!B:B,BILL!C3) -> 0
C31: HC CHAMBER | F31: =SUMIFS(FACILITIES!Q:Q,FACILITIES!B:B,BILL!C3) -> 0
C32: PARTY CHARGES | F32: =SUMIFS('FIXED AMOUNT'!I:I,'FIXED AMOUNT'!B:B,BILL!C3) -> 0
C33: SUB TOTAL | F33: =SUM(F19:F32) -> 57578
C34: SERVICES TAX (SST) | F34: =F19*0.15 -> 7886.7
C35: TOTAL USAGE CHARGES INCLUDING SST | F35: =SUM(F33:F34) -> 65464.7
C36: BREAK DOWN OF MANDATORY CHARGES
C37: MINIMUM CHARGE FOR THE CURRENT HALF YEAR (FYI) | F37: =SUMIFS('FIXED AMOUNT'!U:U,'FIXED AMOUNT'!B:B,BILL!C3) -> 60000
C38: USAGE CHARGE FOR THE CURRENT HALF YEAR (FYI) | F38: =SUMIFS('FIXED AMOUNT'!H:H,'FIXED AMOUNT'!B:B,BILL!C3) -> 168251
C39: REMAINING CHARGE FOR THE CURRENT HALF YEAR (FYI) | F39: =IF(F37-F38<0,0,F37-F38) -> 0
C40: AMOUNT BEFORE DUE DATE | F40: =F5 -> 72464.7
C41: AMOUNT AFTER DUE DATE | F41: =F7 -> 79711.17
C42: BILL MONTH: OCTOBER 2025
A44: Detail of food & BEVERAGES
A45: For the month of OCTOBER 2025
A46: TOTAL AMOUNT Rs. | F46: =SUM(F48:F199) -> 52578
A47: MEMBERSHIP ID | C47: DATE | D47: QTY. | E47: FOOD ORDER | F47: AMOUNT
A48: =C3 -> HCFM-0503 | C48: =IFERROR( INDEX('F & B'!D$2:D$10815, _xlfn.AGGREGATE(15,6, (ROW('F & B'!$B$2:$B$10815)-ROW('F & B'!$B$2)+1)/ ('F & B'!$B$2:$B$10815=$A$48), ROW()-47) ), "") -> 45992 | D48: =IFERROR( INDEX('F & B'!E$2:E$10815, _xlfn.AGGREGATE(15,6, (ROW('F & B'!$B$2:$B$10815)-ROW('F & B'!$B$2)+1)/ ('F & B'!$B$2:$B$10815=$A$48), ROW()-47) ), "") -> 1 | E48: =IFERROR( INDEX('F & B'!F$2:F$10815, _xlfn.AGGREGATE(15,6, (ROW('F & B'!$B$2:$B$10815)-ROW('F & B'!$B$2)+1)/ ('F & B'!$B$2:$B$10815=$A$48), ROW()-47) ), "") -> SPECIAL CHICKEN POPCORN | F48: =IFERROR( INDEX('F & B'!G$2:G$10815, _xlfn.AGGREGATE(15,6, (ROW('F & B'!$B$2:$B$10815)-ROW('F & B'!$B$2)+1)/ ('F & B'!$B$2:$B$10815=$A$48), ROW()-47) ), "") -> 500
C49: =IFERROR( INDEX('F & B'!D$2:D$10815, _xlfn.AGGREGATE(15,6, (ROW('F & B'!$B$2:$B$10815)-ROW('F & B'!$B$2)+1)/ ('F & B'!$B$2:$B$10815=$A$48), ROW()-47) ), "") -> 45992 | D49: =IFERROR( INDEX('F & B'!E$2:E$10815, _xlfn.AGGREGATE(15,6, (ROW('F & B'!$B$2:$B$10815)-ROW('F & B'!$B$2)+1)/ ('F & B'!$B$2:$B$10815=$A$48), ROW()-47) ), "") -> 1 | E49: =IFERROR( INDEX('F & B'!F$2:F$10815, _xlfn.AGGREGATE(15,6, (ROW('F & B'!$B$2:$B$10815)-ROW('F & B'!$B$2)+1)/ ('F & B'!$B$2:$B$10815=$A$48), ROW()-47) ), "") -> CREAM OF MASHROOM SOUP | F49: =IFERROR( INDEX('F & B'!G$2:G$10815, _xlfn.AGGREGATE(15,6, (ROW('F & B'!$B$2:$B$10815)-ROW('F & B'!$B$2)+1)/ ('F & B'!$B$2:$B$10815=$A$48), ROW()-47) ), "") -> 400
C50: =IFERROR( INDEX('F & B'!D$2:D$10815, _xlfn.AGGREGATE(15,6, (ROW('F & B'!$B$2:$B$10815)-ROW('F & B'!$B$2)+1)/ ('F & B'!$B$2:$B$10815=$A$48), ROW()-47) ), "") -> 45992 | D50: =IFERROR( INDEX('F & B'!E$2:E$10815, _xlfn.AGGREGATE(15,6, (ROW('F & B'!$B$2:$B$10815)-ROW('F & B'!$B$2)+1)/ ('F & B'!$B$2:$B$10815=$A$48), ROW()-47) ), "") -> 1 | E50: =IFERROR( INDEX('F & B'!F$2:F$10815, _xlfn.AGGREGATE(15,6, (ROW('F & B'!$B$2:$B$10815)-ROW('F & B'!$B$2)+1)/ ('F & B'!$B$2:$B$10815=$A$48), ROW()-47) ), "") -> RAITA | F50: =IFERROR( INDEX('F & B'!G$2:G$10815, _xlfn.AGGREGATE(15,6, (ROW('F & B'!$B$2:$B$10815)-ROW('F & B'!$B$2)+1)/ ('F & B'!$B$2:$B$10815=$A$48), ROW()-47) ), "") -> 200
C51: =IFERROR( INDEX('F & B'!D$2:D$10815, _xlfn.AGGREGATE(15,6, (ROW('F & B'!$B$2:$B$10815)-ROW('F & B'!$B$2)+1)/ ('F & B'!$B$2:$B$10815=$A$48), ROW()-47) ), "") -> 45992 | D51: =IFERROR( INDEX('F & B'!E$2:E$10815, _xlfn.AGGREGATE(15,6, (ROW('F & B'!$B$2:$B$10815)-ROW('F & B'!$B$2)+1)/ ('F & B'!$B$2:$B$10815=$A$48), ROW()-47) ), "") -> 1 | E51: =IFERROR( INDEX('F & B'!F$2:F$10815, _xlfn.AGGREGATE(15,6, (ROW('F & B'!$B$2:$B$10815)-ROW('F & B'!$B$2)+1)/ ('F & B'!$B$2:$B$10815=$A$48), ROW()-47) ), "") -> MINERAL WATER LARGE | F51: =IFERROR( INDEX('F & B'!G$2:G$10815, _xlfn.AGGREGATE(15,6, (ROW('F & B'!$B$2:$B$10815)-ROW('F & B'!$B$2)+1)/ ('F & B'!$B$2:$B$10815=$A$48), ROW()-47) ), "") -> 150
C52: =IFERROR( INDEX('F & B'!D$2:D$10815, _xlfn.AGGREGATE(15,6, (ROW('F & B'!$B$2:$B$10815)-ROW('F & B'!$B$2)+1)/ ('F & B'!$B$2:$B$10815=$A$48), ROW()-47) ), "") -> 45997 | D52: =IFERROR( INDEX('F & B'!E$2:E$10815, _xlfn.AGGREGATE(15,6, (ROW('F & B'!$B$2:$B$10815)-ROW('F & B'!$B$2)+1)/ ('F & B'!$B$2:$B$10815=$A$48), ROW()-47) ), "") -> 1 | E52: =IFERROR( INDEX('F & B'!F$2:F$10815, _xlfn.AGGREGATE(15,6, (ROW('F & B'!$B$2:$B$10815)-ROW('F & B'!$B$2)+1)/ ('F & B'!$B$2:$B$10815=$A$48), ROW()-47) ), "") -> MINERAL WATER LARGE | F52: =IFERROR( INDEX('F & B'!G$2:G$10815, _xlfn.AGGREGATE(15,6, (ROW('F & B'!$B$2:$B$10815)-ROW('F & B'!$B$2)+1)/ ('F & B'!$B$2:$B$10815=$A$48), ROW()-47) ), "") -> 150
C53: =IFERROR( INDEX('F & B'!D$2:D$10815, _xlfn.AGGREGATE(15,6, (ROW('F & B'!$B$2:$B$10815)-ROW('F & B'!$B$2)+1)/ ('F & B'!$B$2:$B$10815=$A$48), ROW()-47) ), "") -> 45997 | D53: =IFERROR( INDEX('F & B'!E$2:E$10815, _xlfn.AGGREGATE(15,6, (ROW('F & B'!$B$2:$B$10815)-ROW('F & B'!$B$2)+1)/ ('F & B'!$B$2:$B$10815=$A$48), ROW()-47) ), "") -> 1 | E53: =IFERROR( INDEX('F & B'!F$2:F$10815, _xlfn.AGGREGATE(15,6, (ROW('F & B'!$B$2:$B$10815)-ROW('F & B'!$B$2)+1)/ ('F & B'!$B$2:$B$10815=$A$48), ROW()-47) ), "") -> BEEF BOTI | F53: =IFERROR( INDEX('F & B'!G$2:G$10815, _xlfn.AGGREGATE(15,6, (ROW('F & B'!$B$2:$B$10815)-ROW('F & B'!$B$2)+1)/ ('F & B'!$B$2:$B$10815=$A$48), ROW()-47) ), "") -> 1200
C54: =IFERROR( INDEX('F & B'!D$2:D$10815, _xlfn.AGGREGATE(15,6, (ROW('F & B'!$B$2:$B$10815)-ROW('F & B'!$B$2)+1)/ ('F & B'!$B$2:$B$10815=$A$48), ROW()-47) ), "") -> 45997 | D54: =IFERROR( INDEX('F & B'!E$2:E$10815, _xlfn.AGGREGATE(15,6, (ROW('F & B'!$B$2:$B$10815)-ROW('F & B'!$B$2)+1)/ ('F & B'!$B$2:$B$10815=$A$48), ROW()-47) ), "") -> 1 | E54: =IFERROR( INDEX('F & B'!F$2:F$10815, _xlfn.AGGREGATE(15,6, (ROW('F & B'!$B$2:$B$10815)-ROW('F & B'!$B$2)+1)/ ('F & B'!$B$2:$B$10815=$A$48), ROW()-47) ), "") -> PLAIN NAAN | F54: =IFERROR( INDEX('F & B'!G$2:G$10815, _xlfn.AGGREGATE(15,6, (ROW('F & B'!$B$2:$B$10815)-ROW('F & B'!$B$2)+1)/ ('F & B'!$B$2:$B$10815=$A$48), ROW()-47) ), "") -> 70
C55: =IFERROR( INDEX('F & B'!D$2:D$10815, _xlfn.AGGREGATE(15,6, (ROW('F & B'!$B$2:$B$10815)-ROW('F & B'!$B$2)+1)/ ('F & B'!$B$2:$B$10815=$A$48), ROW()-47) ), "") -> 45997 | D55: =IFERROR( INDEX('F & B'!E$2:E$10815, _xlfn.AGGREGATE(15,6, (ROW('F & B'!$B$2:$B$10815)-ROW('F & B'!$B$2)+1)/ ('F & B'!$B$2:$B$10815=$A$48), ROW()-47) ), "") -> 7 | E55: =IFERROR( INDEX('F & B'!F$2:F$10815, _xlfn.AGGREGATE(15,6, (ROW('F & B'!$B$2:$B$10815)-ROW('F & B'!$B$2)+1)/ ('F & B'!$B$2:$B$10815=$A$48), ROW()-47) ), "") -> VODKA SINGLE | F55: =IFERROR( INDEX('F & B'!G$2:G$10815, _xlfn.AGGREGATE(15,6, (ROW('F & B'!$B$2:$B$10815)-ROW('F & B'!$B$2)+1)/ ('F & B'!$B$2:$B$10815=$A$48), ROW()-47) ), "") -> 3850
C56: =IFERROR( INDEX('F & B'!D$2:D$10815, _xlfn.AGGREGATE(15,6, (ROW('F & B'!$B$2:$B$10815)-ROW('F & B'!$B$2)+1)/ ('F & B'!$B$2:$B$10815=$A$48), ROW()-47) ), "") -> 45997 | D56: =IFERROR( INDEX('F & B'!E$2:E$10815, _xlfn.AGGREGATE(15,6, (ROW('F & B'!$B$2:$B$10815)-ROW('F & B'!$B$2)+1)/ ('F & B'!$B$2:$B$10815=$A$48), ROW()-47) ), "") -> 3 | E56: =IFERROR( INDEX('F & B'!F$2:F$10815, _xlfn.AGGREGATE(15,6, (ROW('F & B'!$B$2:$B$10815)-ROW('F & B'!$B$2)+1)/ ('F & B'!$B$2:$B$10815=$A$48), ROW()-47) ), "") -> MURREE BEER | F56: =IFERROR( INDEX('F & B'!G$2:G$10815, _xlfn.AGGREGATE(15,6, (ROW('F & B'!$B$2:$B$10815)-ROW('F & B'!$B$2)+1)/ ('F & B'!$B$2:$B$10815=$A$48), ROW()-47) ), "") -> 3000
C57: =IFERROR( INDEX('F & B'!D$2:D$10815, _xlfn.AGGREGATE(15,6, (ROW('F & B'!$B$2:$B$10815)-ROW('F & B'!$B$2)+1)/ ('F & B'!$B$2:$B$10815=$A$48), ROW()-47) ), "") -> 45999 | D57: =IFERROR( INDEX('F & B'!E$2:E$10815, _xlfn.AGGREGATE(15,6, (ROW('F & B'!$B$2:$B$10815)-ROW('F & B'!$B$2)+1)/ ('F & B'!$B$2:$B$10815=$A$48), ROW()-47) ), "") -> 1 | E57: =IFERROR( INDEX('F & B'!F$2:F$10815, _xlfn.AGGREGATE(15,6, (ROW('F & B'!$B$2:$B$10815)-ROW('F & B'!$B$2)+1)/ ('F & B'!$B$2:$B$10815=$A$48), ROW()-47) ), "") -> MINERAL WATER LARGE | F57: =IFERROR( INDEX('F & B'!G$2:G$10815, _xlfn.AGGREGATE(15,6, (ROW('F & B'!$B$2:$B$10815)-ROW('F & B'!$B$2)+1)/ ('F & B'!$B$2:$B$10815=$A$48), ROW()-47) ), "") -> 150
